Workbook

Sheet AREAS
O1: Empreendimentos | P1: Cidades | Q1: UF | R1: Unidades Lotes | S1: Área Total | T1: Hectare | U1: VGV Total | V1: VGV BT
O2: =SUBTOTAL(103,N4:N185) -> 182 | P2: =COUNTA(_xlfn.UNIQUE(L4:L189)) -> 70 | Q2: =COUNTA(_xlfn.UNIQUE(M4:M312)) -> 18 | R2: =SUM(AJ4:AJ295) -> 213609.38 | S2: =SUM(AC4:AC164) -> 38796401 | T2: =S2/10000 -> 3879.6401 | U2: =SUM(AL4:AL164) -> 25412.967 | V2: =SUM(AM4:AM164) -> 17037.866
A3: ID | B3: Nome | C3: Links | D3: [ON / OFF] | E3: Status da área | F3: # UAU LAND-BANK | G3: # Workflow | H3: Empresa UAU | I3: Obra UAU | J3: Código Modelo | K3: Regional | L3: Cidade | M3: UF | N3: Empreendimento | O3: Tipo de Contrato | P3: Valor de Compra da Área - Aquisição (R$mm) | Q3: Tipo | R3: Projeto Feito | S3: Year | T3: Data de Lançamento | U3: Participação Buriti | V3: Participação Terreneiro (não paga obra) | W3: Participação Buriti + Terreneiro | X3: Comisão / Terreneiro | Y3: Adm. E Manutenção / Terreneiro | Z3: Tributos / Terreneiro | AA3: Participação Líquida Terreneiro | AB3: Participação de Sócios Minoritários (paga obra) | AC3: Area Total m2 | AD3: Data de Inicio de Construção | AE3: Custo Total do Terreno (Pré Rateio - R$mm) | AF3: Custo Total do Terreno (% do VGV) | AG3: Custo de Construção (Pré Rateio - R$mm) | AH3: Valor m2 Obra | AI3: m2 por Unidade | AJ3: Total de Unidades | AK3: Valor m2 Venda | AL3: VGV Total (R$mm) | AM3: VGV Total (R$mm) BT | AN3: Valor médio por terreno | AO3: Custo médio por terreno | AP3: % Paga obra | AQ3: Margem | AR3: Situação do Empreendimento
A4: MAP001 | B4: CIDADE JARDIM - ETP I - BELA VISTA | C4: https://earth.google.com/web/search/BELA+VISTA/@-16.96124568,-48.94579579,823.03102905a,3707.10942264d,35y,-0h,0t,0r/data=CnkaSxJFCiUweDkzNWYyNTZjZmU4NDk4OGQ6MHhiNDk0MzE3NTE3MDU3YTA5GVl5E43_-DDAIcOVWL7TeUjAKgpCRUxBIFZJU1RBGAIgASImCiQJ0WMLs4K1IMAREBK2sOjBIMAZM_Z2zLqhSMAh4pu9YBioSMBCAggBOgMKATBCAggASggIl-fxrwUQAA?authuser=0 | D4: 1 | E4: LandBank | G4: 2040 | J4: 355 | K4: CENTRO-OESTE I | L4: BELA VISTA DE GOIÁS | M4: GO | N4: CIDADE JARDIM - ETP I | O4: Arrematação judicial | P4: 11775750 | Q4: Loteamento | R4: Sim | S4: 2026 | T4: 46203 | U4: 0.75 | V4: 0.25 | W4: =SUM(U4:V4) -> 1 | X4: 0.05 | Y4: 0.09 | Z4: 0.068 | AA4: 0.198 | AC4: =AI4*AJ4 -> 265341.3 | AE4: =P4/10^6 -> 11.77575 | AF4: =IF(AL4=0,0,AE4/AL4) -> 0.090570683 | AG4: =(AH4*AI4*AJ4)/10^6 -> 39.270512 | AH4: 148 | AI4: 304.99 | AJ4: 870 | AK4: 490 | AL4: =(AK4*AJ4*AI4)/10^6 -> 130.01724 | AM4: =AL4*U4 -> 97.512928 | AN4: =AI4*AK4 -> 149445.1 | AO4: =AH4*AI4 -> 45138.52 | AP4: =U4+AB4 -> 0.75 | AQ4: =AL4*AP4/(AG4+AE4) -> 1.9102854 | AR4: A lançar
A5: MAP122 | B5: JARDIM DO CERRADO 7 - GOIÂNIA | C5: https://earth.google.com/web/search/GOI%c3%82NIA/@-16.67746594,-49.42770992,858.01737984a,4789.30417081d,35y,9.31126662h,0.18897674t,360r/data=CiwiJgokCTImrsNH8yrAEajobj-t-irAGWOHbhWxkEjAIXn8jCOOlEjAQgIIAToDCgEwQgIIAEoICJfn8a8FEAA?authuser=0 | D5: 1 | E5: LandBank | G5: 2770 | J5: 360 | K5: CENTRO-OESTE II | L5: GOIÂNIA | M5: GO | N5: JARDIM DO CERRADO 7 | O5: Parceria | P5: 0 | Q5: Loteamento | R5: - | S5: 2026 | T5: 46295 | U5: 0.8 | W5: =SUM(U5:V5) -> 0.8 | AA5: 0.198 | AB5: 0.2 | AC5: =AI5*AJ5 -> 192245.77 | AE5: =P5/10^6 -> 0 | AF5: =IF(AL5=0,0,AE5/AL5) -> 0 | AG5: =(AH5*AI5*AJ5)/10^6 -> 28.452374 | AH5: 148 | AI5: 384.49154 | AJ5: 500 | AK5: 500 | AL5: =(AK5*AJ5*AI5)/10^6 -> 96.122886 | AM5: =AL5*U5 -> 76.898309 | AN5: =AI5*AK5 -> 192245.77 | AO5: =AH5*AI5 -> 56904.748 | AP5: =U5+AB5 -> 1 | AQ5: =AL5*AP5/(AG5+AE5) -> 3.3783784 | AR5: A lançar
A6: MAP122 | B6: JARDIM DO CERRADO 8 - GOIÂNIA | C6: https://earth.google.com/web/search/GOI%c3%82NIA/@-16.67746594,-49.42770992,858.01737984a,4789.30417081d,35y,9.31126662h,0.18897674t,360r/data=CiwiJgokCTImrsNH8yrAEajobj-t-irAGWOHbhWxkEjAIXn8jCOOlEjAQgIIAToDCgEwQgIIAEoICJfn8a8FEAA?authuser=0 | D6: 1 | E6: LandBank | G6: 2770 | J6: 361 | K6: CENTRO-OESTE II | L6: GOIÂNIA | M6: GO | N6: JARDIM DO CERRADO 8 | O6: Parceria | P6: 0 | Q6: Loteamento | R6: - | S6: 2026 | T6: 46295 | U6: 0.8 | W6: =SUM(U6:V6) -> 0.8 | AA6: 0.198 | AB6: 0.2 | AC6: =AI6*AJ6 -> 139944.68 | AE6: =P6/10^6 -> 0 | AF6: =IF(AL6=0,0,AE6/AL6) -> 0 | AG6: =(AH6*AI6*AJ6)/10^6 -> 20.711813 | AH6: 148 | AI6: 279.88937 | AJ6: 500 | AK6: 500 | AL6: =(AK6*AJ6*AI6)/10^6 -> 69.972342 | AM6: =AL6*U6 -> 55.977874 | AN6: =AI6*AK6 -> 139944.68 | AO6: =AH6*AI6 -> 41423.627 | AP6: =U6+AB6 -> 1 | AQ6: =AL6*AP6/(AG6+AE6) -> 3.3783784 | AR6: A lançar
A7: MAP122 | B7: JARDIM DO CERRADO 9 - GOIÂNIA | C7: https://earth.google.com/web/search/GOI%c3%82NIA/@-16.67746594,-49.42770992,858.01737984a,4789.30417081d,35y,9.31126662h,0.18897674t,360r/data=CiwiJgokCTImrsNH8yrAEajobj-t-irAGWOHbhWxkEjAIXn8jCOOlEjAQgIIAToDCgEwQgIIAEoICJfn8a8FEAA?authuser=0 | D7: 1 | E7: LandBank | G7: 2770 | J7: 363 | K7: CENTRO-OESTE II | L7: GOIÂNIA | M7: GO | N7: JARDIM DO CERRADO 9 | O7: Parceria | P7: 0 | Q7: Loteamento | R7: - | S7: 2026 | T7: 46387 | U7: 0.8 | W7: =SUM(U7:V7) -> 0.8 | AA7: 0.198 | AB7: 0.2 | AC7: =AI7*AJ7 -> 141436.02 | AE7: =P7/10^6 -> 0 | AF7: =IF(AL7=0,0,AE7/AL7) -> 0 | AG7: =(AH7*AI7*AJ7)/10^6 -> 20.932531 | AH7: 148 | AI7: 282.87205 | AJ7: 500 | AK7: 500 | AL7: =(AK7*AJ7*AI7)/10^6 -> 70.718012 | AM7: =AL7*U7 -> 56.574409 | AN7: =AI7*AK7 -> 141436.02 | AO7: =AH7*AI7 -> 41865.063 | AP7: =U7+AB7 -> 1 | AQ7: =AL7*AP7/(AG7+AE7) -> 3.3783784 | AR7: A lançar
A8: MAP033 | B8: BURITI GARDEN PRIME - MARECHAL DEODORO | C8: https://earth.google.com/web/search/MARECHAL+DEODORO/@-9.75268373,-35.84765408,4.2701174a,3214.95034437d,35y,0h,0t,0r/data=CiwiJgokCWeqOyo7eCPAETh3cFu0hiPAGVxp7S1rVULAIVnrvdbgXELAQgIIAToDCgEwQgIIAEoICJfn8a8FEAA?authuser=0 | D8: 1 | E8: LandBank | G8: 2047 | J8: 196 | K8: NORDESTE I | L8: MARECHAL DEODORO | M8: AL | N8: BURITI GARDEN PRIME | O8: Parceria | P8: 0 | Q8: Condominio | R8: Sim | S8: 2026 | T8: 46203 | U8: 0.5086 | V8: 0.3642 | W8: =SUM(U8:V8) -> 0.8728 | X8: 0.05 | Y8: 0.09 | Z8: 0.068 | AA8: 0.198 | AB8: 0.1272 | AC8: =AI8*AJ8 -> 160666.8 | AE8: =P8/10^6 -> 0 | AF8: =IF(AL8=0,0,AE8/AL8) -> 0 | AG8: =(AH8*AI8*AJ8)/10^6 -> 41.773368 | AH8: 260 | AI8: 246.8 | AJ8: 651 | AK8: 1100 | AL8: =(AK8*AJ8*AI8)/10^6 -> 176.73348 | AM8: =AL8*U8 -> 89.886648 | AN8: =AI8*AK8 -> 271480 | AO8: =AH8*AI8 -> 64168 | AP8: =U8+AB8 -> 0.6358 | AQ8: =AL8*AP8/(AG8+AE8) -> 2.6899231 | AR8: A lançar
A9: MAP033 | B9: BURITI GARDEN PRIME LOTES COMERCIAIS | D9: Ativo | E9: LandBank | K9: NORDESTE I | L9: MARECHAL DEODORO | M9: AL | N9: BURITI GARDEN PRIME LOTES COMERCIAIS | O9: Parceria | P9: 0 | Q9: Condominio | R9: Sim | S9: 2026 | T9: 46203 | U9: 0.5086 | V9: 0.3642 | W9: =SUM(U9:V9) -> 0.8728 | X9: 0.05 | Y9: 0.09 | Z9: 0.068 | AA9: 0.198 | AB9: 0.1272 | AC9: =AI9*AJ9 -> 17948.6 | AE9: =P9/10^6 -> 0 | AF9: =IF(AL9=0,0,AE9/AL9) -> 0 | AG9: =(AH9*AI9*AJ9)/10^6 -> 4.666636 | AH9: 260 | AI9: 527.9 | AJ9: 34 | AK9: 1800 | AL9: =(AK9*AJ9*AI9)/10^6 -> 32.30748 | AM9: =AL9*U9 -> 16.431584 | AN9: =AI9*AK9 -> 950220 | AO9: =AH9*AI9 -> 137254 | AP9: =U9+AB9 -> 0.6358 | AQ9: =AL9*AP9/(AG9+AE9) -> 4.4016923 | AR9: A lançar
A10: MAP034 | B10: RESIDENCIAL CIDADE JARDIM III - RIO LARGO | C10: https://earth.google.com/web/search/RIO+LARGO/@-9.52900304,-35.81653115,112.35298923a,4987.59724811d,35y,0.00000121h,0t,0r/data=CiwiJgokCbfopBmzfCPAEeMgyVIMhiPAGTrKKDMX6kHAIcF9G6ro7kHAQgIIAToDCgEwQgIIAEoICJfn8a8FEAA?authuser=0 | D10: 1 | E10: LandBank | G10: 2049 | J10: 197 | K10: NORDESTE I | L10: RIO LARGO | M10: AL | N10: RESIDENCIAL CIDADE JARDIM III | O10: Compra e Venda | P10: 1923793.1 | Q10: Loteamento | R10: Sim | S10: 2026 | T10: 46264 | U10: 0.8 | W10: =SUM(U10:V10) -> 0.8 | AA10: 0.198 | AB10: 0.2 | AC10: =AI10*AJ10 -> 525997.68 | AE10: =P10/10^6 -> 1.9237931 | AF10: =IF(AL10=0,0,AE10/AL10) -> 0.0069007876 | AG10: =(AH10*AI10*AJ10)/10^6 -> 63.119722 | AH10: 120 | AI10: 164.58 | AJ10: 3196 | AK10: 530 | AL10: =(AK10*AJ10*AI10)/10^6 -> 278.77877 | AM10: =AL10*U10 -> 223.02302 | AN10: =AI10*AK10 -> 87227.4 | AO10: =AH10*AI10 -> 19749.6 | AP10: =U10+AB10 -> 1 | AQ10: =AL10*AP10/(AG10+AE10) -> 4.2860348 | AR10: A lançar
A11: MAP035 | B11: RESIDENCIAL JARDIM AMERICA II - PENEDO | C11: https://earth.google.com/web/search/Penedo,+AL/@-10.25735808,-36.57115779,78.36658822a,3198.69005319d,35y,0h,0t,0r/data=CiwiJgokCSEY7vitZSLAEUE54MEYuCPAGb-vF-6sm0HAIR2ubXgmSkLAQgIIAToDCgEwQgIIAEoICJfn8a8FEAA?authuser=0 | D11: 1 | E11: LandBank | G11: 2048 | J11: 200 | K11: NORDESTE I | L11: PENEDO | M11: AL | N11: RESIDENCIAL JARDIM AMERICA II | O11: Compra e Venda | P11: 4000000 | Q11: Loteamento | R11: Sim | S11: 2026 | T11: 46203 | U11: 0.8 | W11: =SUM(U11:V11) -> 0.8 | AA11: 0.198 | AB11: 0.2 | AC11: =AI11*AJ11 -> 117415.64 | AE11: =P11/10^6 -> 4 | AF11: =IF(AL11=0,0,AE11/AL11) -> 0.079225609 | AG11: =(AH11*AI11*AJ11)/10^6 -> 11.741564 | AH11: 100 | AI11: 207.81529 | AJ11: 565 | AK11: 430 | AL11: =(AK11*AJ11*AI11)/10^6 -> 50.488725 | AM11: =AL11*U11 -> 40.39098 | AN11: =AI11*AK11 -> 89360.576 | AO11: =AH11*AI11 -> 20781.529 | AP11: =U11+AB11 -> 1 | AQ11: =AL11*AP11/(AG11+AE11) -> 3.2073513 | AR11: Lançado
A12: MAP038 | B12: JARDIM TROPICAL - CRATO | C12: https://earth.google.com/web/search/CRATO/@-7.23451766,-39.35968774,395.14410239a,4808.57124561d,35y,0h,0t,0r/data=CiwiJgokCREenKRkwgvAEaRMcJe6-AvAGbMRrrPsyUPAIf7hsFbW0EPAQgIIAToDCgEwQgIIAEoICJfn8a8FEAA?authuser=0 | D12: 1 | E12: LandBank | G12: 2053 | J12: 204 | K12: NORDESTE II | L12: CRATO | M12: CE | N12: JARDIM TROPICAL | O12: Compra e Venda | P12: 750000 | Q12: Loteamento | R12: Sim | S12: 2026 | T12: 46295 | U12: 0.725 | V12: 0.275 | W12: =SUM(U12:V12) -> 1 | X12: 0.05 | Y12: 0 | Z12: 0.068 | AA12: 0.198 | AC12: =AI12*AJ12 -> 188078 | AE12: =P12/10^6 -> 0.75 | AF12: =IF(AL12=0,0,AE12/AL12) -> 0.0066461787 | AG12: =(AH12*AI12*AJ12)/10^6 -> 22.56936 | AH12: 120 | AI12: 206 | AJ12: 913 | AK12: 600 | AL12: =(AK12*AJ12*AI12)/10^6 -> 112.8468 | AM12: =AL12*U12 -> 81.81393 | AN12: =AI12*AK12 -> 123600 | AO12: =AH12*AI12 -> 24720 | AP12: =U12+AB12 -> 0.725 | AQ12: =AL12*AP12/(AG12+AE12) -> 3.5084123 | AR12: A lançar
A13: MAP039 | B13: JARDIM TROPICAL - ITAPIPOCA | C13: https://earth.google.com/web/search/ITAPIPOCA/@-3.48318447,-39.60453858,85.75014124a,4591.68380015d,35y,0h,0t,0r/data=CiwiJgokCSj18Ul83hfAEYrTwO0U8hfAGYnj-uRdJETAIcMsoPJeKUTAQgIIAToDCgEwQgIIAEoICJfn8a8FEAA?authuser=0 | D13: 1 | E13: LandBank | G13: 2054 | J13: 205 | K13: NORDESTE II | L13: ITAPIPOCA | M13: CE | N13: JARDIM TROPICAL | O13: Compra e Venda | P13: 750000 | Q13: Loteamento | R13: Sim | S13: 2026 | T13: 46295 | U13: 0.8 | V13: 0.2 | W13: =SUM(U13:V13) -> 1 | X13: 0.05 | Y13: 0 | Z13: 0.068 | AA13: 0.198 | AC13: =AI13*AJ13 -> 186384 | AE13: =P13/10^6 -> 0.75 | AF13: =IF(AL13=0,0,AE13/AL13) -> 0.0080479011 | AG13: =(AH13*AI13*AJ13)/10^6 -> 24.789072 | AH13: 133 | AI13: 176 | AJ13: 1059 | AK13: 500 | AL13: =(AK13*AJ13*AI13)/10^6 -> 93.192 | AM13: =AL13*U13 -> 74.5536 | AN13: =AI13*AK13 -> 88000 | AO13: =AH13*AI13 -> 23408 | AP13: =U13+AB13 -> 0.8 | AQ13: =AL13*AP13/(AG13+AE13) -> 2.9191977 | AR13: A lançar
A14: MAP041 | B14: RESIDENCIAL CIDADE JARDIM - BALSAS | C14: https://earth.google.com/web/search/BALSAS/@-7.55676262,-46.08364445,276.35723714a,5135.12989945d,35y,0h,0t,0r/data=CiwiJgokCeJxBz6CxDDAEQlwGFeXzDDAGfey9riu6UXAIWSXkF1C8kXAQgIIAToDCgEwQgIIAEoICJfn8a8FEAA?authuser=0 | D14: 1 | E14: LandBank | F14: REVER PROJETOS | G14: 2052 | J14: 209 | K14: NORDESTE II | L14: BALSAS | M14: MA | N14: RESIDENCIAL CIDADE JARDIM I - STP1 | O14: Parceria | P14: 0 | Q14: Loteamento | R14: Sim | S14: 2026 | T14: 46387 | U14: 0.8 | V14: 0.2 | W14: =SUM(U14:V14) -> 1 | X14: 0.05 | Y14: 0 | Z14: 0.068 | AA14: 0.198 | AC14: =AI14*AJ14 -> 306340 | AE14: =P14/10^6 -> 0 | AF14: =IF(AL14=0,0,AE14/AL14) -> 0 | AG14: =(AH14*AI14*AJ14)/10^6 -> 36.7608 | AH14: 120 | AI14: 265 | AJ14: 1156 | AK14: 500 | AL14: =(AK14*AJ14*AI14)/10^6 -> 153.17 | AM14: =AL14*U14 -> 122.536 | AN14: =AI14*AK14 -> 132500 | AO14: =AH14*AI14 -> 31800 | AP14: =U14+AB14 -> 0.8 | AQ14: =AL14*AP14/(AG14+AE14) -> 3.3333333 | AR14: A lançar
A15: MAP008 | B15: CIDADE JARDIM III - SUBETAPA 1 - SANTARÉM | C15: https://earth.google.com/web/search/CIDADE+JARDIM+12+-+PARAUAPEBAS/@-2.45795692,-54.77217012,46.50042218a,6405.178905d,35y,-0h,0t,0r/data=CiwiJgokCdmVqMeMyQbAESVW3mJaMwnAGYI6tUF7jUfAIaCAQToN3EfAQgIIAToDCgEwQgIIAEoICJfn8a8FEAA | D15: 1 | E15: LandBank | G15: 2121 | J15: 147 | K15: NORTE | L15: SANTARÉM | M15: PA | N15: RESIDENCIAL CIDADE JARDIM III | O15: Aquisição de Cotas | P15: 4800000 | Q15: Loteamento | R15: Sim | S15: 2026 | T15: 46387 | U15: 1 | W15: =SUM(U15:V15) -> 1 | AA15: 0.198 | AC15: =AI15*AJ15 -> 538153.29 | AE15: =P15/10^6 -> 4.8 | AF15: =IF(AL15=0,0,AE15/AL15) -> 0.013722141 | AG15: =(AH15*AI15*AJ15)/10^6 -> 71.628203 | AH15: 133.1 | AI15: 279.27 | AJ15: 1927 | AK15: 650 | AL15: =(AK15*AJ15*AI15)/10^6 -> 349.79964 | AM15: =AL15*U15 -> 349.79964 | AN15: =AI15*AK15 -> 181525.5 | AO15: =AH15*AI15 -> 37170.837 | AP15: =U15+AB15 -> 1 | AQ15: =AL15*AP15/(AG15+AE15) -> 4.5768398 | AR15: A lançar
A16: MAP012 | B16: RESIDENCIAL JARDIM IPIRANGA II - XINGUARA | C16: https://earth.google.com/web/search/RESIDENCIAL+JARDIM+IPIRANGA+II+-+XINGUARA/@-7.12104404,-49.92523395,224.47331647a,1424.00240818d,35y,-0h,0t,0r/data=CiwiJgokCUUfzO5U4h_AEV26WHYzKSDAGfKhedaB80jAITi3e0FBEEnAQgIIAToDCgEwQgIIAEoICJfn8a8FEAA?authuser=0 | D16: 1 | E16: LandBank | G16: 2118 | J16: 152 | K16: NORTE | L16: XINGUARA | M16: PA | N16: RESIDENCIAL JARDIM IPIRANGA II | O16: Compra e Venda | P16: 13000000 | Q16: Loteamento | R16: Sim | S16: 2026 | T16: 46387 | U16: 1 | W16: =SUM(U16:V16) -> 1 | AA16: 0.198 | AC16: =AI16*AJ16 -> 195570.85 | AE16: =P16/10^6 -> 13 | AF16: =IF(AL16=0,0,AE16/AL16) -> 0.15458622 | AG16: =(AH16*AI16*AJ16)/10^6 -> 26.03048 | AH16: 133.1 | AI16: 210.97179 | AJ16: 927 | AK16: 430 | AL16: =(AK16*AJ16*AI16)/10^6 -> 84.095466 | AM16: =AL16*U16 -> 84.095466 | AN16: =AI16*AK16 -> 90717.87 | AO16: =AH16*AI16 -> 28080.345 | AP16: =U16+AB16 -> 1 | AQ16: =AL16*AP16/(AG16+AE16) -> 2.1546101 | AR16: A lançar
A17: MAP108 | B17: RESIDENCIAL CIDADE JARDIM I - CÁCERES | C17: https://earth.google.com/web/search/C%c3%81CERES/@-16.11433068,-57.66517767,145.36941085a,5953.03993857d,35y,-0h,0t,0r/data=CiwiJgokCQX_JH53NS3AETlJC9e-RS3AGdinZMrzwEzAIeq1E4h_yUzAQgIIAToDCgEwQgIIAEoICJfn8a8FEAA?authuser=0 | D17: 1 | E17: LandBank | G17: 1865 | J17: 336 | K17: OESTE | L17: CÁCERES | M17: MT | N17: RESIDENCIAL CIDADE JARDIM I | O17: Parceria | P17: 0 | Q17: Loteamento | R17: Sim | S17: 2026 | T17: 46295 | U17: 0.81 | V17: 0.19 | W17: =SUM(U17:V17) -> 1 | X17: 0.05 | Y17: 0 | Z17: 0.068 | AA17: 0.198 | AC17: =AI17*AJ17 -> 338165 | AE17: =P17/10^6 -> 0 | AF17: =IF(AL17=0,0,AE17/AL17) -> 0 | AG17: =(AH17*AI17*AJ17)/10^6 -> 44.975945 | AH17: 133 | AI17: 235 | AJ17: 1439 | AK17: 450 | AL17: =(AK17*AJ17*AI17)/10^6 -> 152.17425 | AM17: =AL17*U17 -> 123.26114 | AN17: =AI17*AK17 -> 105750 | AO17: =AH17*AI17 -> 31255 | AP17: =U17+AB17 -> 0.81 | AQ17: =AL17*AP17/(AG17+AE17) -> 2.7406015 | AR17: A lançar
A18: MAP049 | B18: RESIDENCIAL JARDIM EUROPA - COND. - DUQUE DE CAXIAS | C18: https://earth.google.com/web/search/Duque+de+Caxias,+RJ/@-22.62573879,-43.25838279,18.39588858a,1961.37171176d,35y,0h,0t,0r/data=CiwiJgokCUvDRSzvbjbAEZpP4J6LfDbAGco2nMkqO0bAIdAPxNEhSkbAQgIIAToDCgEwQgIIAEoICJfn8a8FEAA?authuser=0 | D18: 1 | E18: LandBank | G18: 2274 | J18: 224 | K18: SUDESTE | L18: DUQUE DE CAXIAS | M18: RJ | N18: RESIDENCIAL JARDIM EUROPA - COND. | O18: Permuta | P18: 166666.66 | Q18: Condominio | R18: - | S18: 2026 | T18: 46295 | U18: 0.64169 | V18: 0.3 | W18: =SUM(U18:V18) -> 0.94169 | X18: 0.05 | Y18: 0 | Z18: 0.068 | AA18: 0.198 | AB18: 0.05831 | AC18: =AI18*AJ18 -> 220580 | AE18: =P18/10^6 -> 0.16666666 | AF18: =IF(AL18=0,0,AE18/AL18) -> 0.00094447967 | AG18: =(AH18*AI18*AJ18)/10^6 -> 39.7044 | AH18: 180 | AI18: 410 | AJ18: 538 | AK18: 800 | AL18: =(AK18*AJ18*AI18)/10^6 -> 176.464 | AM18: =AL18*U18 -> 113.23518 | AN18: =AI18*AK18 -> 328000 | AO18: =AH18*AI18 -> 73800 | AP18: =U18+AB18 -> 0.7 | AQ18: =AL18*AP18/(AG18+AE18) -> 3.0981062 | AR18: A lançar
A19: MAP068 | B19: RESIDENCIAL SÃO FRANCISCO DE AVARÉ - AVARÉ | C19: https://earth.google.com/web/search/Avar%c3%a9,+SP/@-23.13817295,-48.93466362,759.5009067a,2026.71010604d,35y,0h,0t,0r/data=CiwiJgokCbdqOrTERTTAEdFka3GySTTAGdvcUdEVIUnAIfMq4hhXJUnAQgIIAToDCgEwQgIIAEoICJfn8a8FEAA?authuser=0 | D19: 1 | E19: LandBank | G19: 2270 | J19: 262 | K19: SUDESTE | L19: AVARÉ | M19: SP | N19: RESIDENCIAL SÃO FRANCISCO DE AVARÉ | O19: Parceria | P19: 0 | Q19: Loteamento | R19: Sim | S19: 2026 | T19: 46295 | U19: 0.6417 | V19: 0.3 | W19: =SUM(U19:V19) -> 0.9417 | X19: 0.05 | Y19: 0.09 | Z19: 0.068 | AA19: 0.198 | AB19: 0.0583 | AC19: =AI19*AJ19 -> 132640.2 | AE19: =P19/10^6 -> 0 | AF19: =IF(AL19=0,0,AE19/AL19) -> 0 | AG19: =(AH19*AI19*AJ19)/10^6 -> 21.620353 | AH19: 163 | AI19: 219.24 | AJ19: 605 | AK19: 600 | AL19: =(AK19*AJ19*AI19)/10^6 -> 79.58412 | AM19: =AL19*U19 -> 51.06913 | AN19: =AI19*AK19 -> 131544 | AO19: =AH19*AI19 -> 35736.12 | AP19: =U19+AB19 -> 0.7 | AQ19: =AL19*AP19/(AG19+AE19) -> 2.5766871 | AR19: A lançar
A20: MAP079 | B20: 3DA - POA/CALHA DE PEDRA I - PORTO ALEGRE | C20: https://earth.google.com/web/search/PORTO+ALEGRE/@-30.11127632,-51.12148809,52.85283914a,2914.98585346d,35y,0.00000001h,0t,0r/data=CiwiJgokCdF8eOBcqz3AEVk4mQ0orz3AGW7M2FWxNkrAIVpN-_QgO0rAQgIIAToDCgEwQgIIAEoICJfn8a8FEAA?authuser=0 | D20: 1 | E20: LandBank | G20: 2381 | J20: 290 | K20: SUL | L20: PORTO ALEGRE | M20: RS | N20: 3DA - POA/CALHA DE PEDRA I | O20: Parceria | P20: 0 | Q20: Loteamento | R20: Sim | S20: 2026 | T20: 46387 | U20: 0.328 | V20: 0.18 | W20: =SUM(U20:V20) -> 0.508 | X20: 0.07 | Y20: 0.07 | Z20: 0.068 | AA20: 0.198 | AB20: 0.492 | AC20: =AI20*AJ20 -> 91258 | AE20: =P20/10^6 -> 0 | AF20: =IF(AL20=0,0,AE20/AL20) -> 0 | AG20: =(AH20*AI20*AJ20)/10^6 -> 15.97015 | AH20: 175 | AI20: 206 | AJ20: 443 | AK20: 750 | AL20: =(AK20*AJ20*AI20)/10^6 -> 68.4435 | AM20: =AL20*U20 -> 22.449468 | AN20: =AI20*AK20 -> 154500 | AO20: =AH20*AI20 -> 36050 | AP20: =U20+AB20 -> 0.82 | AQ20: =AL20*AP20/(AG20+AE20) -> 3.5142857 | AR20: A lançar
A21: MAP080 | B21: 4A - SANTA CRUZ DO SUL - SANTA CRUZ DO SUL | C21: https://earth.google.com/web/search/SANTA+CRUZ+DO+SUL/@-29.67679798,-52.44461427,171.97361515a,2440.82594259d,35y,0h,0t,0r/data=CiwiJgokCfCOoxjmrj3AEQTSMIMEsz3AGejaJMRHlUnAIb28UugYmknAQgIIAToDCgEwQgIIAEoICJfn8a8FEAA?authuser=0 | D21: 1 | E21: LandBank | G21: 2394 | J21: 293 | K21: SUL | L21: SANTA CRUZ DO SUL | M21: RS | N21: 4A - SANTA CRUZ DO SUL | O21: Parceria | P21: 0 | Q21: Loteamento | R21: Sim | S21: 2026 | T21: 46295 | U21: 0.544 | V21: 0.32 | W21: =SUM(U21:V21) -> 0.864 | X21: 0.07 | Y21: 0.095 | Z21: 0.068 | AA21: 0.198 | AB21: 0.136 | AC21: =AI21*AJ21 -> 103037 | AE21: =P21/10^6 -> 0 | AF21: =IF(AL21=0,0,AE21/AL21) -> 0 | AG21: =(AH21*AI21*AJ21)/10^6 -> 18.031475 | AH21: 175 | AI21: 323 | AJ21: 319 | AK21: 700 | AL21: =(AK21*AJ21*AI21)/10^6 -> 72.1259 | AM21: =AL21*U21 -> 39.23649 | AN21: =AI21*AK21 -> 226100 | AO21: =AH21*AI21 -> 56525 | AP21: =U21+AB21 -> 0.68 | AQ21: =AL21*AP21/(AG21+AE21) -> 2.72 | AR21: A lançar
A22: MAP082 | B22: 5A - SÃO LEOPOLDO - ABERTO 1ºFASE - SÃO LEOPOLDO | C22: https://earth.google.com/web/search/S%c3%83O+LEOPOLDO/@-29.69124438,-51.18506887,72.72392941a,2763.99436261d,35y,0h,0t,0r/data=CiwiJgokCYgGRBoKGD7AEeRabSOjGz7AGfvFjOgUgEnAIaI5Hn1OhEnAQgIIAToDCgEwQgIIAEoICJfn8a8FEAA?authuser=0 | D22: 1 | E22: LandBank | G22: 2387 | J22: 295 | K22: SUL | L22: SÃO LEOPOLDO | M22: RS | N22: 5A -SÃO LEOPOLDO - ABERTO 1ºFASE | O22: Permuta | P22: 2215500 | Q22: Loteamento | R22: Sim | S22: 2026 | T22: 46203 | U22: 0.556 | V22: 0.305 | W22: =SUM(U22:V22) -> 0.861 | X22: 0.07 | Y22: 0 | Z22: 0.068 | AA22: 0.198 | AB22: 0.139 | AC22: =AI22*AJ22 -> 130830 | AE22: =P22/10^6 -> 2.2155 | AF22: =IF(AL22=0,0,AE22/AL22) -> 0.021167737 | AG22: =(AH22*AI22*AJ22)/10^6 -> 22.89525 | AH22: 175 | AI22: 267 | AJ22: 490 | AK22: 800 | AL22: =(AK22*AJ22*AI22)/10^6 -> 104.664 | AM22: =AL22*U22 -> 58.193184 | AN22: =AI22*AK22 -> 213600 | AO22: =AH22*AI22 -> 46725 | AP22: =U22+AB22 -> 0.695 | AQ22: =AL22*AP22/(AG22+AE22) -> 2.8968263 | AR22: A lançar
A23: MAP084 | B23: 5B - SÃO LEOPOLDO - FECHADO 1ºFASE - SÃO LEOPOLDO | C23: https://earth.google.com/web/search/S%c3%83O+LEOPOLDO/@-29.69124438,-51.18506887,72.72392941a,2763.99436261d,35y,0h,0t,0r/data=CiwiJgokCYgGRBoKGD7AEeRabSOjGz7AGfvFjOgUgEnAIaI5Hn1OhEnAQgIIAToDCgEwQgIIAEoICJfn8a8FEAA?authuser=0 | D23: 1 | E23: LandBank | G23: 2387 | J23: 297 | K23: SUL | L23: SÃO LEOPOLDO | M23: RS | N23: 5B -SÃO LEOPOLDO - FECHADO 1ºFASE | O23: Permuta | P23: 2215500 | Q23: Condominio | R23: Sim | S23: 2026 | T23: 46203 | U23: 0.556 | V23: 0.305 | W23: =SUM(U23:V23) -> 0.861 | X23: 0.07 | Y23: 0 | Z23: 0.068 | AA23: 0.198 | AB23: 0.139 | AC23: =AI23*AJ23 -> 101592 | AE23: =P23/10^6 -> 2.2155 | AF23: =IF(AL23=0,0,AE23/AL23) -> 0.014538546 | AG23: =(AH23*AI23*AJ23)/10^6 -> 35.5572 | AH23: 350 | AI23: 332 | AJ23: 306 | AK23: 1500 | AL23: =(AK23*AJ23*AI23)/10^6 -> 152.388 | AM23: =AL23*U23 -> 84.727728 | AN23: =AI23*AK23 -> 498000 | AO23: =AH23*AI23 -> 116200 | AP23: =U23+AB23 -> 0.695 | AQ23: =AL23*AP23/(AG23+AE23) -> 2.8038679 | AR23: A lançar
A24: MAP087 | B24: 6B - CX. SUL - SIVIERO / CAMINHOS DO SOL - CAXIAS DO SUL | C24: https://earth.google.com/web/search/CAXIAS+DO+SUL/@-29.13850338,-51.12230837,798.77655109a,2732.24624327d,35y,-0h,0t,0r/data=CnwaThJICiUweDk1MWViY2QxNjQzNWYwNzM6MHhmNTE0ZjcwN2I1NzczYmY0GVOObimMLD3AIRz3nKoxl0nAKg1DQVhJQVMgRE8gU1VMGAEgASImCiQJ1tRH0utLPcARa0Tc7klTPcAZjiIdAINaScAhKwpGrRhjScBCAggBOgMKATBCAggASggIl-fxrwUQAA?authuser=0 | D24: 1 | E24: LandBank | G24: 2374 | J24: 300 | K24: SUL | L24: CAXIAS DO SUL | M24: RS | N24: 6B - CX. SUL - SIVIERO / CAMINHOS DO SOL | O24: Parceria | P24: 0 | Q24: Loteamento | R24: Sim | S24: 2026 | T24: 46203 | U24: 0.4 | V24: 0.5 | W24: =SUM(U24:V24) -> 0.9 | X24: 0.07 | Y24: 0.095 | Z24: 0.068 | AA24: 0.198 | AB24: 0.1 | AC24: =AI24*AJ24 -> 264827.8 | AE24: =P24/10^6 -> 0 | AF24: =IF(AL24=0,0,AE24/AL24) -> 0 | AG24: =(AH24*AI24*AJ24)/10^6 -> 46.344865 | AH24: 175 | AI24: 432.72516 | AJ24: 612 | AK24: 900 | AL24: =(AK24*AJ24*AI24)/10^6 -> 238.34502 | AM24: =AL24*U24 -> 95.338008 | AN24: =AI24*AK24 -> 389452.65 | AO24: =AH24*AI24 -> 75726.904 | AP24: =U24+AB24 -> 0.5 | AQ24: =AL24*AP24/(AG24+AE24) -> 2.5714286 | AR24: A lançar
A25: MAP088 | B25: 6C - CX. SUL - SIVIERO / VALE DAS COLINAS - CAXIAS DO SUL | C25: https://earth.google.com/web/search/CAXIAS+DO+SUL/@-29.13038377,-51.22227002,696.92023901a,2558.98775459d,35y,0h,0t,0r/data=CnwaThJICiUweDk1MWViY2QxNjQzNWYwNzM6MHhmNTE0ZjcwN2I1NzczYmY0GVOObimMLD3AIRz3nKoxl0nAKg1DQVhJQVMgRE8gU1VMGAEgASImCiQJ1tRH0utLPcARa0Tc7klTPcAZjiIdAINaScAhKwpGrRhjScBCAggBOgMKATBCAggASggIl-fxrwUQAA?authuser=0 | D25: 1 | E25: LandBank | G25: 2374 | J25: 301 | K25: SUL | L25: CAXIAS DO SUL | M25: RS | N25: 6C - CX. SUL - SIVIERO / VALE DAS COLINAS | O25: Parceria | P25: 0 | Q25: Loteamento | R25: Sim | S25: 2026 | T25: 46387 | U25: 0.4 | V25: 0.5 | W25: =SUM(U25:V25) -> 0.9 | X25: 0.07 | Y25: 0.095 | Z25: 0.068 | AA25: 0.198 | AB25: 0.1 | AC25: =AI25*AJ25 -> 159307.14 | AE25: =P25/10^6 -> 0 | AF25: =IF(AL25=0,0,AE25/AL25) -> 0 | AG25: =(AH25*AI25*AJ25)/10^6 -> 27.87875 | AH25: 175 | AI25: 375.72439 | AJ25: 424 | AK25: 800 | AL25: =(AK25*AJ25*AI25)/10^6 -> 127.44571 | AM25: =AL25*U25 -> 50.978285 | AN25: =AI25*AK25 -> 300579.51 | AO25: =AH25*AI25 -> 65751.768 | AP25: =U25+AB25 -> 0.5 | AQ25: =AL25*AP25/(AG25+AE25) -> 2.2857143 | AR25: A lançar
A26: MAP094 | B26: 8B - VIAMÃO - SURREAX/MONTAINE - VIAMÃO | C26: https://earth.google.com/web/search/VIAM%c3%83O/@-30.06497491,-51.03875844,59.46189546a,2897.51328111d,35y,360h,0t,0r/data=CnYaSBJCCiUweDk1MTk5OGE2ZDhmMjY0NDE6MHgxNWY0MmRhYTgyYjY2ZDQwGXCFZo0wFT7AIQB4nz5dhEnAKgdWSUFNw4NPGAEgASImCiQJsTk0ZNOlP8ARLqkiuNytP8AZ9eUZULQnSsAh8JLJOEwxSsBCAggBOgMKATBCAggASggIl-fxrwUQAA?authuser=0 | D26: 1 | E26: LandBank | G26: 2388 | J26: 310 | K26: SUL | L26: VIAMÃO | M26: RS | N26: 8B - VIAMÃO - SURREAX/MONTAINE | O26: Parceria | P26: 0 | Q26: Loteamento | R26: - | S26: 2026 | T26: 46203 | U26: 0.544 | V26: 0.32 | W26: =SUM(U26:V26) -> 0.864 | X26: 0.07 | Y26: 0.095 | Z26: 0.068 | AA26: 0.198 | AB26: 0.136 | AC26: =AI26*AJ26 -> 84153.46 | AE26: =P26/10^6 -> 0 | AF26: =IF(AL26=0,0,AE26/AL26) -> 0 | AG26: =(AH26*AI26*AJ26)/10^6 -> 14.726856 | AH26: 175 | AI26: 235.06553 | AJ26: 358 | AK26: 650 | AL26: =(AK26*AJ26*AI26)/10^6 -> 54.699749 | AM26: =AL26*U26 -> 29.756663 | AN26: =AI26*AK26 -> 152792.59 | AO26: =AH26*AI26 -> 41136.468 | AP26: =U26+AB26 -> 0.68 | AQ26: =AL26*AP26/(AG26+AE26) -> 2.5257143 | AR26: Lançado
A27: MAP097 | B27: 9B - PELOTAS - INDUSTRIAL RCL - PELOTAS | C27: https://earth.google.com/web/search/PELOTAS/@-31.66345999,-52.34766459,33.86198261a,5500.41331546d,35y,0h,0t,0r/data=CiwiJgokCcTGFe60DEDAEbD1lg7sD0DAGcKY98kGFErAITOrTYO9G0rAQgIIAToDCgEwQgIIAEoICJfn8a8FEAA?authuser=0 | D27: 1 | E27: LandBank | G27: 2380 | J27: 313 | K27: SUL | L27: PELOTAS | M27: RS | N27: 9B - PELOTAS - INDUSTRIAL RCL | O27: Parceria | P27: 0 | Q27: Loteamento | R27: Sim | S27: 2026 | T27: 46203 | U27: 0.552 | V27: 0.31 | W27: =SUM(U27:V27) -> 0.862 | X27: 0.07 | Y27: 0.095 | Z27: 0.068 | AA27: 0.198 | AB27: 0.138 | AC27: =AI27*AJ27 -> 64704 | AE27: =P27/10^6 -> 0 | AF27: =IF(AL27=0,0,AE27/AL27) -> 0 | AG27: =(AH27*AI27*AJ27)/10^6 -> 9.05856 | AH27: 140 | AI27: 1348 | AJ27: 48 | AK27: 900 | AL27: =(AK27*AJ27*AI27)/10^6 -> 58.2336 | AM27: =AL27*U27 -> 32.144947 | AN27: =AI27*AK27 -> 1213200 | AO27: =AH27*AI27 -> 188720 | AP27: =U27+AB27 -> 0.69 | AQ27: =AL27*AP27/(AG27+AE27) -> 4.4357143 | AR27: A lançar
A28: MAP103 | B28: 14A - GUARAPUAVA - 41HA (ELDORADO I) - GUARAPUAVA | C28: https://earth.google.com/web/search/GUARAPUAVA/@-25.39953824,-51.52751542,1024.00734861a,2854.44336804d,35y,360h,0t,0r/data=CiwiJgokCbN0uAN0-znAEZYMuK9MojrAGTg0o7y1VEjAIWKVrBNVEknAQgIIAToDCgEwQgIIAEoICJfn8a8FEAA?authuser=0 | D28: 1 | E28: LandBank | G28: 2378 | J28: 322 | K28: SUL | L28: GUARAPUAVA | M28: PR | N28: 15a- Guarapuava - 41ha (Eldorado I) | O28: Parceria | P28: 0 | Q28: Loteamento | R28: Sim | S28: 2026 | T28: 46295 | U28: 0.536 | V28: 0.33 | W28: =SUM(U28:V28) -> 0.866 | X28: 0.07 | Y28: 0.095 | Z28: 0.068 | AA28: 0.198 | AB28: 0.134 | AC28: =AI28*AJ28 -> 167783.24 | AE28: =P28/10^6 -> 0 | AF28: =IF(AL28=0,0,AE28/AL28) -> 0 | AG28: =(AH28*AI28*AJ28)/10^6 -> 29.362067 | AH28: 175 | AI28: 191.97167 | AJ28: 874 | AK28: 650 | AL28: =(AK28*AJ28*AI28)/10^6 -> 109.05911 | AM28: =AL28*U28 -> 58.455681 | AN28: =AI28*AK28 -> 124781.59 | AO28: =AH28*AI28 -> 33595.042 | AP28: =U28+AB28 -> 0.67 | AQ28: =AL28*AP28/(AG28+AE28) -> 2.4885714 | AR28: A lançar
A29: MAP104 | B29: 14B - GUARAPUAVA - 24HA (ELDORADO II) - GUARAPUAVA | C29: https://earth.google.com/web/search/GUARAPUAVA/@-25.39953824,-51.52751542,1024.00734861a,2854.44336804d,35y,360h,0t,0r/data=CiwiJgokCbN0uAN0-znAEZYMuK9MojrAGTg0o7y1VEjAIWKVrBNVEknAQgIIAToDCgEwQgIIAEoICJfn8a8FEAA?authuser=0 | D29: 1 | E29: LandBank | G29: 2379 | J29: 323 | K29: SUL | L29: GUARAPUAVA | M29: PR | N29: 15b-Guarapuava - 24ha (Eldorado II) | O29: Parceria | P29: 0 | Q29: Loteamento | R29: Sim | S29: 2026 | T29: 46295 | U29: 0.52 | V29: 0.35 | W29: =SUM(U29:V29) -> 0.87 | X29: 0.07 | Y29: 0.095 | Z29: 0.068 | AA29: 0.198 | AB29: 0.13 | AC29: =AI29*AJ29 -> 96232 | AE29: =P29/10^6 -> 0 | AF29: =IF(AL29=0,0,AE29/AL29) -> 0 | AG29: =(AH29*AI29*AJ29)/10^6 -> 16.8406 | AH29: 175 | AI29: 184 | AJ29: 523 | AK29: 650 | AL29: =(AK29*AJ29*AI29)/10^6 -> 62.5508 | AM29: =AL29*U29 -> 32.526416 | AN29: =AI29*AK29 -> 119600 | AO29: =AH29*AI29 -> 32200 | AP29: =U29+AB29 -> 0.65 | AQ29: =AL29*AP29/(AG29+AE29) -> 2.4142857 | AR29: A lançar
A30: MAP021 | B30: ARSO 191 - PALMAS | C30: https://earth.google.com/web/search/Palmas/@-10.25056053,-48.33726188,252.56505595a,47484.59826451d,35y,0h,0t,0r/data=CnQaRhJACiQweDkzM2IzNDM5OTExZjEyNTc6MHg5M2I4MDcwZDA1YzgxOGYZtHQF24h_JMAhUsd0MoIpSMAqBlBhbG1hcxgCIAEiJgokCZ4TQp4rbCTAEd7oz8tIyyTAGZMBVXzHEEjAIR-xYc3lQUjAQgIIAToDCgEwQgIIAEoICJfn8a8FEAA?authuser=0 | D30: 1 | E30: LandBank | G30: PENDENCIA | J30: 162 | K30: TOCANTINS | L30: PALMAS | M30: TO | N30: ARSO 191 | O30: Parceria | P30: 0 | Q30: Loteamento | R30: Sim | S30: 2026 | T30: 46203 | U30: 0.3696 | W30: =SUM(U30:V30) -> 0.3696 | AA30: 0.198 | AB30: 0.6304 | AC30: =AI30*AJ30 -> 224990.22 | AE30: =P30/10^6 -> 0 | AF30: =IF(AL30=0,0,AE30/AL30) -> 0 | AG30: =(AH30*AI30*AJ30)/10^6 -> 28.798748 | AH30: 128 | AI30: 290.68504 | AJ30: 774 | AK30: 550 | AL30: =(AK30*AJ30*AI30)/10^6 -> 123.74462 | AM30: =AL30*U30 -> 45.736012 | AN30: =AI30*AK30 -> 159876.77 | AO30: =AH30*AI30 -> 37207.685 | AP30: =U30+AB30 -> 1 | AQ30: =AL30*AP30/(AG30+AE30) -> 4.296875 | AR30: A lançar
A31: MAP023 | B31: JARDIM CALIFORNIA - PALMAS | C31: https://earth.google.com/web/search/Palmas,+TO/@-10.1436093,-48.30385159,263.38670878a,3734.01843008d,35y,0h,0t,0r/data=CngaShJECiQweDkzM2IzNDM5OTExZjEyNTc6MHg5M2I4MDcwZDA1YzgxOGYZtHQF24h_JMAhUsd0MoIpSMAqClBhbG1hcywgVE8YASABIiYKJAnKmUn74gAbwBGE16-ZZBobwBm4d1Wa5ohJwCHUhDGVbI9JwEICCAE6AwoBMEICCABKCAiX5_GvBRAA?authuser=0 | D31: 1 | E31: LandBank | G31: PENDENCIA | J31: 184 | K31: TOCANTINS | L31: PALMAS | M31: TO | N31: JARDIM CALIFORNIA (JCF) | O31: Parceria | P31: 0 | Q31: Loteamento | R31: Sim | S31: 2026 | T31: 46660 | U31: 0.6 | W31: =SUM(U31:V31) -> 0.6 | AA31: 0.198 | AB31: 0.4 | AC31: =AI31*AJ31 -> 158850 | AE31: =P31/10^6 -> 0 | AF31: =IF(AL31=0,0,AE31/AL31) -> 0 | AG31: =(AH31*AI31*AJ31)/10^6 -> 20.3328 | AH31: 128 | AI31: 225 | AJ31: 706 | AK31: 500 | AL31: =(AK31*AJ31*AI31)/10^6 -> 79.425 | AM31: =AL31*U31 -> 47.655 | AN31: =AI31*AK31 -> 112500 | AO31: =AH31*AI31 -> 28800 | AP31: =U31+AB31 -> 1 | AQ31: =AL31*AP31/(AG31+AE31) -> 3.90625 | AR31: A lançar
A32: MAP024 | B32: RESIDENCIAL ACSV (ÁREA DO PASTOR) - PALMAS | C32: https://earth.google.com/web/search/Palmas/@-10.26832599,-48.31559059,242.67876446a,47835.63394664d,35y,360h,0t,0r/data=CnQaRhJACiQweDkzM2IzNDM5OTExZjEyNTc6MHg5M2I4MDcwZDA1YzgxOGYZtHQF24h_JMAhUsd0MoIpSMAqBlBhbG1hcxgBIAEiJgokCZ4TQp4rbCTAEd7oz8tIyyTAGZMBVXzHEEjAIR-xYc3lQUjAQgIIAToDCgEwQgIIAEoICJfn8a8FEAA?authuser=0 | D32: 1 | E32: LandBank | G32: PENDENCIA | J32: 185 | K32: TOCANTINS | L32: PALMAS | M32: TO | N32: RESIDENCIAL ACSV (MARCO ANTONIO) | O32: Parceria | P32: 0 | Q32: Loteamento | R32: - | S32: 2026 | T32: 46387 | U32: 0.69 | W32: =SUM(U32:V32) -> 0.69 | AA32: 0.198 | AB32: 0.31 | AC32: =AI32*AJ32 -> 327445 | AE32: =P32/10^6 -> 0 | AF32: =IF(AL32=0,0,AE32/AL32) -> 0 | AG32: =(AH32*AI32*AJ32)/10^6 -> 41.91296 | AH32: 128 | AI32: 215 | AJ32: 1523 | AK32: 600 | AL32: =(AK32*AJ32*AI32)/10^6 -> 196.467 | AM32: =AL32*U32 -> 135.56223 | AN32: =AI32*AK32 -> 129000 | AO32: =AH32*AI32 -> 27520 | AP32: =U32+AB32 -> 1 | AQ32: =AL32*AP32/(AG32+AE32) -> 4.6875 | AR32: A lançar
A33: MAP030 | B33: LOTEAMENTO VISTA DO LAGO - FORMOSA | C33: https://earth.google.com/web/search/FORMOSA/@-15.58172122,-47.32794355,897.72742465a,4704.42149765d,35y,0.00000085h,0t,0r/data=CiwiJgokCWIPaQHJuSfAEafTOxpW8SjAGfzlyTCsKUbAIT9JW4C_y0bAQgIIAToDCgEwQgIIAEoICJfn8a8FEAA?authuser=0 | D33: 1 | E33: LandBank | G33: 2039 | J33: 192 | K33: TOCANTINS | L33: FORMOSA | M33: GO | N33: LOTEAMENTO VISTA DO LAGO | O33: Parceria | P33: 0 | Q33: Loteamento | R33: sim | S33: 2026 | T33: 46203 | U33: 0.6 | V33: 0.3 | W33: =SUM(U33:V33) -> 0.9 | X33: 0.05 | Y33: 0.095 | Z33: 0.068 | AA33: 0.198 | AB33: 0.1 | AC33: =AI33*AJ33 -> 168948.74 | AE33: =P33/10^6 -> 0 | AF33: =IF(AL33=0,0,AE33/AL33) -> 0 | AG33: =(AH33*AI33*AJ33)/10^6 -> 21.625439 | AH33: 128 | AI33: 291.29093 | AJ33: 580 | AK33: 650 | AL33: =(AK33*AJ33*AI33)/10^6 -> 109.81668 | AM33: =AL33*U33 -> 65.890009 | AN33: =AI33*AK33 -> 189339.11 | AO33: =AH33*AI33 -> 37285.239 | AP33: =U33+AB33 -> 0.7 | AQ33: =AL33*AP33/(AG33+AE33) -> 3.5546875 | AR33: Lançado
A34: MAP030 | B34: VEREDAS DO LAGO | D34: Ativo | E34: LandBank | K34: TOCANTINS | L34: FORMOSA | M34: GO | N34: VEREDAS DO LAGO | O34: Condominio | P34: - | Q34: Condominio | R34: - | S34: 2026 | T34: 46337 | W34: 0.41 | AA34: 0.35 | AB34: 0.05 | AC34: =AI34*AJ34 -> 128100 | AG34: =(AH34*AI34*AJ34)/10^6 -> 16.3968 | AH34: 128 | AI34: 300 | AJ34: 427 | AK34: 1600 | AL34: =(AK34*AJ34*AI34)/10^6 -> 204.96 | AM34: =AL34*U34 -> 0 | AN34: =AI34*AK34 -> 480000 | AO34: =AH34*AI34 -> 38400 | AP34: =U34+AB34 -> 0.05 | AQ34: =AL34*AP34/(AG34+AE34) -> 0.625 | AR34: A lançar
A35: MAP025 | B35: LOTE PÉ DA PONTE - LUZIMANGUES | C35: https://earth.google.com/web/search/LUZIMANGUES/@-10.2185028,-48.49860748,262.65133073a,44260.3323794d,35y,0h,0t,0r/data=CnoaTBJGCiUweDkzMjRiMjViZWUyY2MyOTU6MHg0MjNiYjhkNzhhZDI2MjdkGWy2TUxyYyTAIa1f-qjQO0jAKgtMVVpJTUFOR1VFUxgBIAEiJgokCc4UM1nC9iPAEZt0OQ_dzCTAGbN2lxLzDEjAIXeF7rCEe0jAQgIIAToDCgEwQgIIAEoICJfn8a8FEAA?authuser=0 | D35: 1 | E35: LandBank | G35: 2315 | J35: 188 | K35: TOCANTINS | L35: LUZIMANGUES | M35: TO | N35: LOTE PÉ DA PONTE | O35: Parceria | P35: 0 | Q35: Loteamento | R35: - | S35: 2026 | T35: 46387 | U35: 0.5323 | W35: =SUM(U35:V35) -> 0.5323 | AA35: 0.198 | AB35: 0.4677 | AC35: =AI35*AJ35 -> 14607 | AE35: =P35/10^6 -> 0 | AF35: =IF(AL35=0,0,AE35/AL35) -> 0 | AG35: =(AH35*AI35*AJ35)/10^6 -> 1.16856 | AH35: 80 | AI35: 14607 | AJ35: 1 | AK35: 500 | AL35: =(AK35*AJ35*AI35)/10^6 -> 7.3035 | AM35: =AL35*U35 -> 3.887653 | AN35: =AI35*AK35 -> 7303500 | AO35: =AH35*AI35 -> 1168560 | AP35: =U35+AB35 -> 1 | AQ35: =AL35*AP35/(AG35+AE35) -> 6.25 | AR35: A lançar
A36: MAP143 | B36: A DEFINIR | D36: Ativo | E36: LandBank | K36: SUL | L36: PASSO FUNDO | M36: RS | N36: 14 - Passo Fundo - Logística | O36: Parceria | Q36: Loteamento | R36: - | S36: 2026 | T36: 46331 | W36: 0.4 | Y36: 0.07 | AA36: 0.5 | AB36: 0.1 | AC36: =AI36*AJ36 -> 249604.85 | AE36: 0 | AF36: 0 | AG36: 127 | AH36: 220 | AI36: 2496.0485 | AJ36: 100 | AK36: 800 | AL36: =(AK36*AJ36*AI36)/10^6 -> 199.68388 | AM36: =AL36*U36 -> 0 | AN36: =AI36*AK36 -> 1996838.8 | AO36: =AH36*AI36 -> 549130.67 | AP36: =U36+AB36 -> 0.1 | AQ36: =AL36*AP36/(AG36+AE36) -> 0.1572314 | AR36: A lançar
A37: MAP122 | B37: JARDIM DO CERRADO 10 - GOIÂNIA | C37: https://earth.google.com/web/search/GOI%c3%82NIA/@-16.67746594,-49.42770992,858.01737984a,4789.30417081d,35y,9.31126662h,0.18897674t,360r/data=CiwiJgokCTImrsNH8yrAEajobj-t-irAGWOHbhWxkEjAIXn8jCOOlEjAQgIIAToDCgEwQgIIAEoICJfn8a8FEAA?authuser=0 | D37: 1 | E37: LandBank | G37: 2770 | J37: 364 | K37: CENTRO-OESTE II | L37: GOIÂNIA | M37: GO | N37: JARDIM DO CERRADO 10 | O37: Parceria | P37: 0 | Q37: Loteamento | R37: - | S37: 2027 | T37: 46752 | U37: 0.8 | W37: =SUM(U37:V37) -> 0.8 | AA37: 0.198 | AB37: 0.2 | AC37: =AI37*AJ37 -> 214171.94 | AE37: =P37/10^6 -> 0 | AF37: =IF(AL37=0,0,AE37/AL37) -> 0 | AG37: =(AH37*AI37*AJ37)/10^6 -> 31.697447 | AH37: 148 | AI37: 428.34388 | AJ37: 500 | AK37: 500 | AL37: =(AK37*AJ37*AI37)/10^6 -> 107.08597 | AM37: =AL37*U37 -> 85.668776 | AN37: =AI37*AK37 -> 214171.94 | AO37: =AH37*AI37 -> 63394.894 | AP37: =U37+AB37 -> 1 | AQ37: =AL37*AP37/(AG37+AE37) -> 3.3783784 | AR37: A lançar
A38: MAP125 | B38: RESIDENCIAL PAINEIRAS | D38: 1 | E38: LandBank | G38: 2177 | K38: CENTRO-OESTE II | L38: PORTO VELHO | M38: RO | N38: RESIDENCIAL PAINEIRAS | O38: Parceria | P38: 0 | Q38: Loteamento | R38: Sim | S38: 2027 | T38: - | U38: 0.8 | W38: =SUM(U38:V38) -> 0.8 | AA38: 0.198 | AB38: 0.2 | AC38: =AI38*AJ38 -> 363235.45 | AE38: =P38/10^6 -> 0 | AF38: =IF(AL38=0,0,AE38/AL38) -> 0 | AG38: =(AH38*AI38*AJ38)/10^6 -> 48.346638 | AH38: 133.1 | AI38: 215.57 | AJ38: 1685 | AK38: 380 | AL38: =(AK38*AJ38*AI38)/10^6 -> 138.02947 | AM38: =AL38*U38 -> 110.42358 | AN38: =AI38*AK38 -> 81916.6 | AO38: =AH38*AI38 -> 28692.367 | AP38: =U38+AB38 -> 1 | AQ38: =AL38*AP38/(AG38+AE38) -> 2.8549962 | AR38: A lançar
A39: MAP032 | B39: RESIDENCIAL ALTO DAS BARAUNAS II - ARAPIRACA | C39: https://earth.google.com/web/search/ARAPIRACA/@-9.74896182,-36.69647245,245.55478327a,4738.09539736d,35y,0h,0t,0r/data=CiwiJgokCclCL3e0IS_AESFNk5j5MS_AGZRIeMyvpUfAIcPoSk9ErkfAQgIIAToDCgEwQgIIAEoICJfn8a8FEAA?authuser=0 | D39: 1 | E39: LandBank | G39: 2045 | J39: 194 | K39: NORDESTE I | L39: ARAPIRACA | M39: AL | N39: RESIDENCIAL ALTO DAS BARAUNAS II | O39: Parceria | P39: 0 | Q39: Loteamento | R39: - | S39: 2027 | T39: 46568 | U39: 0.5304 | V39: 0.337 | W39: =SUM(U39:V39) -> 0.8674 | X39: 0.05 | Y39: 0.09 | Z39: 0.068 | AA39: 0.198 | AB39: 0.1326 | AC39: =AI39*AJ39 -> 169253.49 | AE39: =P39/10^6 -> 0 | AF39: =IF(AL39=0,0,AE39/AL39) -> 0 | AG39: =(AH39*AI39*AJ39)/10^6 -> 20.310419 | AH39: 120 | AI39: 187.64245 | AJ39: 902 | AK39: 426.10642 | AL39: =(AK39*AJ39*AI39)/10^6 -> 72.12 | AM39: =AL39*U39 -> 38.252448 | AN39: =AI39*AK39 -> 79955.654 | AO39: =AH39*AI39 -> 22517.094 | AP39: =U39+AB39 -> 0.663 | AQ39: =AL39*AP39/(AG39+AE39) -> 2.354238 | AR39: A lançar
A40: MAP037 | B40: RESIDENCIAL JARDIM EUROPA - BARRA DOS COQUEIROS | C40: https://earth.google.com/web/search/BARRA+DOS+COQUEIROS/@-10.86709266,-36.98473154,9.11625276a,6838.59037115d,35y,0h,0t,0r/data=CiwiJgokCez0LUwI4RzAEc6AbPlB_xzAGXUWKXAsqkPAIYL6q2XpsUPAQgIIAToDCgEwQgIIAEoICJfn8a8FEAA?authuser=0 | D40: 1 | E40: LandBank | G40: 2046 | J40: 202 | K40: NORDESTE I | L40: BARRA DOS COQUEIROS | M40: SE | N40: RESIDENCIAL JARDIM EUROPA | O40: Compra e Venda | P40: 4000000 | Q40: Loteamento | R40: - | S40: 2027 | T40: 46568 | U40: 0.8 | W40: =SUM(U40:V40) -> 0.8 | AA40: 0.198 | AB40: 0.2 | AC40: =AI40*AJ40 -> 389286.32 | AE40: =P40/10^6 -> 4 | AF40: =IF(AL40=0,0,AE40/AL40) -> 0.023895845 | AG40: =(AH40*AI40*AJ40)/10^6 -> 46.714359 | AH40: 120 | AI40: 216.27018 | AJ40: 1800 | AK40: 430 | AL40: =(AK40*AJ40*AI40)/10^6 -> 167.39312 | AM40: =AL40*U40 -> 133.9145 | AN40: =AI40*AK40 -> 92996.177 | AO40: =AH40*AI40 -> 25952.422 | AP40: =U40+AB40 -> 1 | AQ40: =AL40*AP40/(AG40+AE40) -> 3.3007046 | AR40: A lançar
A41: MAP041 | B41: RESIDENCIAL CIDADE JARDIM - SUBETAPA2 - BALSAS | C41: https://earth.google.com/web/search/BALSAS/@-7.55676262,-46.08364445,276.35723714a,5135.12989945d,35y,0h,0t,0r/data=CiwiJgokCeJxBz6CxDDAEQlwGFeXzDDAGfey9riu6UXAIWSXkF1C8kXAQgIIAToDCgEwQgIIAEoICJfn8a8FEAA?authuser=0 | D41: 1 | E41: LandBank | F41: REVER PROJETOS | G41: 2052 | J41: 210 | K41: NORDESTE II | L41: BALSAS | M41: MA | N41: RESIDENCIAL CIDADE JARDIM I - STP2 | O41: Parceria | P41: 0 | Q41: Loteamento | R41: Sim | S41: 2027 | T41: 46660 | U41: 0.8 | V41: 0.2 | W41: =SUM(U41:V41) -> 1 | X41: 0.05 | Y41: 0 | Z41: 0.068 | AA41: 0.198 | AC41: =AI41*AJ41 -> 306340 | AE41: =P41/10^6 -> 0 | AF41: =IF(AL41=0,0,AE41/AL41) -> 0 | AG41: =(AH41*AI41*AJ41)/10^6 -> 36.7608 | AH41: 120 | AI41: 265 | AJ41: 1156 | AK41: 500 | AL41: =(AK41*AJ41*AI41)/10^6 -> 153.17 | AM41: =AL41*U41 -> 122.536 | AN41: =AI41*AK41 -> 132500 | AO41: =AH41*AI41 -> 31800 | AP41: =U41+AB41 -> 0.8 | AQ41: =AL41*AP41/(AG41+AE41) -> 3.3333333 | AR41: A lançar
A42: MAP007 | B42: RESIDENCIAL BELA VISTA - REDENÇÃO | C42: https://earth.google.com/web/search/Reden%c3%a7%c3%a3o,+PA/@-8.02281704,-50.02474338,207.09019485a,9467.67478846d,35y,-0h,0t,0r/data=Cn0aTxJJCiUweDkyZTAwODAxOTFiMWU4Mzk6MHgzZDhmOGEwNDFiM2MxMGRkGS5nALkODyDAIUkmTL0TBEnAKg5SZWRlbsOnw6NvLCBQQRgCIAEiJgokCVbvBcmbxgfAEZZRXQph6wfAGYZHDZRMrkfAIcoEsIr5skfAQgIIAToDCgEwQgIIAEoICJfn8a8FEAA?authuser=0 | D42: 1 | E42: LandBank | G42: 2116 | J42: 146 | K42: NORTE | L42: REDENÇÃO | M42: PA | N42: RESIDENCIAL CHÁCARAS ELDORADO | O42: Compra e Venda | P42: 2372312.5 | Q42: Loteamento | R42: sim | S42: 2027 | T42: 46752 | U42: 0.99 | W42: =SUM(U42:V42) -> 0.99 | AA42: 0.198 | AB42: 0.01 | AC42: =AI42*AJ42 -> 120780 | AE42: =P42/10^6 -> 2.3723125 | AF42: =IF(AL42=0,0,AE42/AL42) -> 0.045678141 | AG42: =(AH42*AI42*AJ42)/10^6 -> 16.075818 | AH42: 133.1 | AI42: 220 | AJ42: 549 | AK42: 430 | AL42: =(AK42*AJ42*AI42)/10^6 -> 51.9354 | AM42: =AL42*U42 -> 51.416046 | AN42: =AI42*AK42 -> 94600 | AO42: =AH42*AI42 -> 29282 | AP42: =U42+AB42 -> 1 | AQ42: =AL42*AP42/(AG42+AE42) -> 2.8152121 | AR42: A lançar
A43: MAP004 | B43: CIDADE JARDIM 12 - PARAUAPEBAS | C43: https://earth.google.com/web/search/CIDADE+JARDIM+12+-+PARAUAPEBAS/@-6.04487592,-49.83564552,181.81336445a,9406.37838209d,35y,0h,0t,0r/data=CiwiJgokCS03B0TTPhXAEXKT3p9G5BrAGSZGC1wr6UfAISLEcDjXWknAQgIIAToDCgEwQgIIAEoICJfn8a8FEAA?authuser=0 | D43: 1 | E43: LandBank | G43: 2584 | J43: 139 | K43: NORTE | L43: PARAUAPEBAS | M43: PA | N43: CIDADE JARDIM 12 | O43: Compra e Venda | P43: 4000000 | Q43: Loteamento | R43: Sim | S43: 2027 | T43: 46752 | U43: 1 | W43: =SUM(U43:V43) -> 1 | AA43: 0.198 | AC43: =AI43*AJ43 -> 297407.69 | AE43: =P43/10^6 -> 4 | AF43: =IF(AL43=0,0,AE43/AL43) -> 0.022415919 | AG43: =(AH43*AI43*AJ43)/10^6 -> 39.584964 | AH43: 133.1 | AI43: 216.61157 | AJ43: 1373 | AK43: 600 | AL43: =(AK43*AJ43*AI43)/10^6 -> 178.44461 | AM43: =AL43*U43 -> 178.44461 | AN43: =AI43*AK43 -> 129966.94 | AO43: =AH43*AI43 -> 28831 | AP43: =U43+AB43 -> 1 | AQ43: =AL43*AP43/(AG43+AE43) -> 4.0941783 | AR43: A lançar
A44: MAP121 | B44: RES. BURITI GARDEN - CONCEIÇÃO DO ARAGUAIA | C44: https://earth.google.com/web/search/CONCEI%c3%87%c3%83O+DO+ARAGUAIA/@-8.36662137,-49.28837855,171.07324722a,4098.20934676d,35y,-0h,0t,0r/data=CoYBGlgSUgolMHg5MzIwOGVkOGNlMjM0NzkxOjB4YTkyMzUwNTBlYzEzOTgxYhn3G5L_boYgwCGiLq3hfaJIwCoXQ09OQ0VJw4fDg08gRE8gQVJBR1VBSUEYASABIiYKJAmUyRpDBqgwwBHbTnQb0LIwwBktQ1q_GrJIwCGoHPQLYbtIwEICCAE6AwoBMEICCABKCAiX5_GvBRAA?authuser=0 | D44: 1 | E44: LandBank | G44: 2773 | J44: 357 | K44: NORTE | L44: CONCEIÇÃO DO ARAGUAIA | M44: PA | N44: RES. BURITI GARDEN | O44: Parceria | P44: 0 | Q44: Condominio | R44: - | S44: 2027 | T44: 46598 | U44: 1 | W44: =SUM(U44:V44) -> 1 | AA44: 0.198 | AC44: =AI44*AJ44 -> 75000 | AE44: =P44/10^6 -> 0 | AF44: =IF(AL44=0,0,AE44/AL44) -> 0 | AG44: =(AH44*AI44*AJ44)/10^6 -> 19.5 | AH44: 260 | AI44: 300 | AJ44: 250 | AK44: 700 | AL44: =(AK44*AJ44*AI44)/10^6 -> 52.5 | AM44: =AL44*U44 -> 52.5 | AN44: =AI44*AK44 -> 210000 | AO44: =AH44*AI44 -> 78000 | AP44: =U44+AB44 -> 1 | AQ44: =AL44*AP44/(AG44+AE44) -> 2.6923077 | AR44: A lançar
A45: MAP106 | B45: RESIDENCIAL CIDADE JARDIM II - RIO BRANCO | C45: https://earth.google.com/web/search/RIO+BRANCO/@-9.9098996,-67.78102104,162.15508008a,8113.58158257d,35y,360h,0t,0r/data=CnkaSxJFCiUweDkxN2Y3YmI2OGFjYzk2ZjM6MHg4YWI4OGYxZDdmMWQ5YjNjGbb6RWSz8iPAIUaLfRPU81DAKgpSSU8gQlJBTkNPGAEgASImCiQJfzD99xEWMMAR4w_EqB0hMMAZ8L7dRwvPTMAhtzjkj7naTMBCAggBOgMKATBCAggASggIl-fxrwUQAA?authuser=0 | D45: 1 | E45: LandBank | G45: 2106 | J45: 326 | K45: OESTE | L45: RIO BRANCO | M45: AC | N45: RESIDENCIAL CIDADE JARDIM II | O45: Compra e Venda | P45: 1436252.3 | Q45: Loteamento | R45: Sim | S45: 2027 | T45: 46752 | U45: 0.7 | V45: 0.3 | W45: =SUM(U45:V45) -> 1 | X45: 0.05 | Y45: 0.09 | Z45: 0.068 | AA45: 0.198 | AC45: =AI45*AJ45 -> 495642.18 | AE45: =P45/10^6 -> 1.4362523 | AF45: =IF(AL45=0,0,AE45/AL45) -> 0.0057955209 | AG45: =(AH45*AI45*AJ45)/10^6 -> 79.302749 | AH45: 160 | AI45: 260.59 | AJ45: 1902 | AK45: 500 | AL45: =(AK45*AJ45*AI45)/10^6 -> 247.82109 | AM45: =AL45*U45 -> 173.47476 | AN45: =AI45*AK45 -> 130295 | AO45: =AH45*AI45 -> 41694.4 | AP45: =U45+AB45 -> 0.7 | AQ45: =AL45*AP45/(AG45+AE45) -> 2.1485869 | AR45: A lançar
A46: MAP109 | B46: RESIDENCIAL CIDADE JARDIM II - CÁCERES | C46: https://earth.google.com/web/search/C%c3%81CERES/@-16.11433068,-57.66517767,145.36941085a,5953.03993857d,35y,-0h,0t,0r/data=CiwiJgokCQX_JH53NS3AETlJC9e-RS3AGdinZMrzwEzAIeq1E4h_yUzAQgIIAToDCgEwQgIIAEoICJfn8a8FEAA?authuser=0 | D46: 1 | E46: LandBank | G46: 1865 | J46: 338 | K46: OESTE | L46: CÁCERES | M46: MT | N46: RESIDENCIAL CIDADE JARDIM II | O46: Parceria | P46: 0 | Q46: Loteamento | R46: Sim | S46: 2027 | T46: 46660 | U46: 0.81 | V46: 0.19 | W46: =SUM(U46:V46) -> 1 | X46: 0.05 | Y46: 0 | Z46: 0.068 | AA46: 0.198 | AC46: =AI46*AJ46 -> 240800 | AE46: =P46/10^6 -> 0 | AF46: =IF(AL46=0,0,AE46/AL46) -> 0 | AG46: =(AH46*AI46*AJ46)/10^6 -> 32.0264 | AH46: 133 | AI46: 215 | AJ46: 1120 | AK46: 450 | AL46: =(AK46*AJ46*AI46)/10^6 -> 108.36 | AM46: =AL46*U46 -> 87.7716 | AN46: =AI46*AK46 -> 96750 | AO46: =AH46*AI46 -> 28595 | AP46: =U46+AB46 -> 0.81 | AQ46: =AL46*AP46/(AG46+AE46) -> 2.7406015 | AR46: A lançar
A47: MAP111 | B47: RESIDENCIAL CIDADE JARDIM I - TANGARÁ DA SERRA | C47: https://earth.google.com/web/search/TANGAR%c3%81+DA+SERRA/@-14.62032689,-57.54082084,346.92096178a,5258.20888551d,35y,0h,0t,0r/data=CiwiJgokCXA9rQptMS_AEXKWStZFPy_AGehdnQKoD0zAIeamtZ71FkzAQgIIAToDCgEwQgIIAEoICJfn8a8FEAA?authuser=0 | D47: 1 | E47: LandBank | G47: 2107 | J47: 340 | K47: OESTE | L47: TANGARÁ DA SERRA | M47: MT | N47: RESIDENCIAL CIDADE JARDIM I | O47: Compra e Venda | P47: 10682.93 | Q47: Loteamento | R47: Sim | S47: 2027 | T47: 46752 | U47: 0.7 | V47: 0.3 | W47: =SUM(U47:V47) -> 1 | X47: 0.05 | Y47: 0.09 | Z47: 0.068 | AA47: 0.198 | AC47: =AI47*AJ47 -> 720845.33 | AE47: =P47/10^6 -> 0.01068293 | AF47: =IF(AL47=0,0,AE47/AL47) -> 2.9640006e-05 | AG47: =(AH47*AI47*AJ47)/10^6 -> 95.872428 | AH47: 133 | AI47: 324.1211 | AJ47: 2224 | AK47: 500 | AL47: =(AK47*AJ47*AI47)/10^6 -> 360.42266 | AM47: =AL47*U47 -> 252.29586 | AN47: =AI47*AK47 -> 162060.55 | AO47: =AH47*AI47 -> 43108.106 | AP47: =U47+AB47 -> 0.7 | AQ47: =AL47*AP47/(AG47+AE47) -> 2.6312857 | AR47: A lançar
A48: MAP116 | B48: PARK DOS BURITIS II - CACOAL | C48: https://earth.google.com/web/search/CACOAL/@-11.46023209,-61.46392704,192.80524441a,2677.20500742d,35y,0.00000001h,0t,0r/data=CiwiJgokCR-NyuOUryXAEUa9h2WxuCXAGViFzbpE_U7AISHjgBr7AU_AQgIIAToDCgEwQgIIAEoICJfn8a8FEAA?authuser=0 | D48: 1 | E48: LandBank | G48: 2102 | J48: 350 | K48: OESTE | L48: CACOAL | M48: RO | N48: PARK DOS BURITIS II | O48: Parceria | P48: 0 | Q48: Loteamento | R48: Sim | S48: 2027 | T48: 46752 | U48: 0.7 | V48: 0.3 | W48: =SUM(U48:V48) -> 1 | X48: 0.05 | Y48: 0.09 | Z48: 0.068 | AA48: 0.198 | AC48: =AI48*AJ48 -> 227700 | AE48: =P48/10^6 -> 0 | AF48: =IF(AL48=0,0,AE48/AL48) -> 0 | AG48: =(AH48*AI48*AJ48)/10^6 -> 30.2841 | AH48: 133 | AI48: 220 | AJ48: 1035 | AK48: 477.57 | AL48: =(AK48*AJ48*AI48)/10^6 -> 108.74269 | AM48: =AL48*U48 -> 76.119882 | AN48: =AI48*AK48 -> 105065.4 | AO48: =AH48*AI48 -> 29260 | AP48: =U48+AB48 -> 0.7 | AQ48: =AL48*AP48/(AG48+AE48) -> 2.5135263 | AR48: A lançar
A49: MAP130 | B49: CHAPADA DOS GUIMARÃES-LAGO DO MANSO | D49: 1 | E49: Estudo de viabilidade | G49: 2645 | K49: OESTE | L49: CHAPADA DOS GUIMARÃES | M49: MT | N49: A DEFINIR | O49: Parceria | P49: 0 | Q49: Condominio | R49: - | S49: 2027 | U49: 0.8 | V49: 0.2 | W49: =SUM(U49:V49) -> 1 | AA49: 0.198 | AC49: =AI49*AJ49 -> 2062873.3 | AE49: =P49/10^6 -> 0 | AF49: =IF(AL49=0,0,AE49/AL49) -> 0 | AG49: =(AH49*AI49*AJ49)/10^6 -> 274.36215 | AH49: 133 | AI49: 800 | AJ49: 2578.5917 | AK49: 1400 | AL49: =(AK49*AJ49*AI49)/10^6 -> 2888.0227 | AM49: =AL49*U49 -> 2310.4181 | AN49: =AI49*AK49 -> 1120000 | AO49: =AH49*AI49 -> 106400 | AP49: =U49+AB49 -> 0.8 | AQ49: =AL49*AP49/(AG49+AE49) -> 8.4210526 | AR49: A lançar
A50: MAP135 | B50: MUNARO EMPREENDIMENTOS IMOBILIÁRIOS LTDA | D50: 1 | E50: Estudo de viabilidade | G50: 2767 | K50: OESTE | L50: GUARANTÃ DO NORTE | M50: MT | N50: A DEFINIR | O50: Parceria | P50: 0 | Q50: Loteamento | R50: - | S50: 2027 | T50: - | U50: 0.75 | V50: 0.25 | W50: =SUM(U50:V50) -> 1 | AA50: 0.198 | AC50: =AI50*AJ50 -> 230939.46 | AE50: =P50/10^6 -> 0 | AF50: =IF(AL50=0,0,AE50/AL50) -> 0 | AG50: =(AH50*AI50*AJ50)/10^6 -> 30.714948 | AH50: 133 | AI50: 200 | AJ50: 1154.6973 | AK50: 550 | AL50: =(AK50*AJ50*AI50)/10^6 -> 127.0167 | AM50: =AL50*U50 -> 95.262527 | AN50: =AI50*AK50 -> 110000 | AO50: =AH50*AI50 -> 26600 | AP50: =U50+AB50 -> 0.75 | AQ50: =AL50*AP50/(AG50+AE50) -> 3.1015038 | AR50: A lançar
A51: MAP136 | B51: PERGENTINO DE VASCONCELOS JUNIOR | D51: 1 | E51: Estudo de viabilidade | G51: 2726 | K51: SUDESTE | L51: COLATINA | M51: ES | N51: SITÍO COLINA BRANCA | O51: Parceria | P51: 0 | Q51: Loteamento | R51: - | S51: 2027 | T51: 46568 | U51: 0.67 | V51: 0.33 | W51: =SUM(U51:V51) -> 1 | AA51: 0.198 | AC51: =AI51*AJ51 -> 225878.4 | AE51: =P51/10^6 -> 0 | AF51: =IF(AL51=0,0,AE51/AL51) -> 0 | AG51: =(AH51*AI51*AJ51)/10^6 -> 38.399328 | AH51: 170 | AI51: 313.72 | AJ51: 720 | AK51: 700 | AL51: =(AK51*AJ51*AI51)/10^6 -> 158.11488 | AM51: =AL51*U51 -> 105.93697 | AN51: =AI51*AK51 -> 219604 | AO51: =AH51*AI51 -> 53332.4 | AP51: =U51+AB51 -> 0.67 | AQ51: =AL51*AP51/(AG51+AE51) -> 2.7588235 | AR51: A lançar
A52: MAP044 | B52: A DEFINIR I - MONTES CLAROS | C52: https://earth.google.com/web/search/MONTES+CLAROS/@-16.78340211,-43.85914746,708.18079241a,4857.74891966d,35y,0h,0t,0r/data=CiwiJgokCaYkZ-ZvtTPAEWpwuK9tuzPAGWYZIm4r8UfAIR546sKi90fAQgIIAToDCgEwQgIIAEoICJfn8a8FEAA?authuser=0 | D52: 1 | E52: LandBank | G52: 2567 | J52: 216 | K52: SUDESTE | L52: MONTES CLAROS | M52: MG | N52: A DEFINIR | O52: Parceria | P52: 0 | Q52: Loteamento | R52: - | S52: 2027 | T52: 46660 | U52: 0.4844 | V52: 0.47158285 | W52: =SUM(U52:V52) -> 0.95598285 | X52: 0.05 | Y52: 0 | Z52: 0.068 | AA52: 0.198 | AB52: 0.044017148 | AC52: =AI52*AJ52 -> 182214 | AE52: =P52/10^6 -> 0 | AF52: =IF(AL52=0,0,AE52/AL52) -> 0 | AG52: =(AH52*AI52*AJ52)/10^6 -> 29.700882 | AH52: 163 | AI52: 240.07115 | AJ52: 759 | AK52: 680 | AL52: =(AK52*AJ52*AI52)/10^6 -> 123.90552 | AM52: =AL52*U52 -> 60.019834 | AN52: =AI52*AK52 -> 163248.38 | AO52: =AH52*AI52 -> 39131.597 | AP52: =U52+AB52 -> 0.52841715 | AQ52: =AL52*AP52/(AG52+AE52) -> 2.2044396 | AR52: A lançar
A53: MAP052 | B53: BURITI GARDEN I - ITABORAÍ | C53: https://earth.google.com/web/search/ITABORA%c3%8d/@-22.7705662,-42.90251485,16.01615323a,2212.94452737d,35y,0h,0t,0r/data=CiwiJgokCWeuUiREWTbAEf3J2D8_YjbAGShqrBV35ETAIYuIHwFV7kTAQgIIAToDCgEwQgIIAEoICJfn8a8FEAA?authuser=0 | D53: 1 | E53: LandBank | G53: 2275 | J53: 231 | K53: SUDESTE | L53: ITABORAÍ | M53: RJ | N53: BURITI GARDEN I | O53: Compra e Venda | P53: 12546881 | Q53: Condominio | R53: - | S53: 2027 | T53: 46660 | U53: 0.573362 | V53: 0.14 | W53: =SUM(U53:V53) -> 0.713362 | X53: 0.05 | Y53: 0 | Z53: 0.068 | AA53: 0.198 | AB53: 0.286638 | AC53: =AI53*AJ53 -> 135500 | AE53: =P53/10^6 -> 12.546881 | AF53: =IF(AL53=0,0,AE53/AL53) -> 0.084179008 | AG53: =(AH53*AI53*AJ53)/10^6 -> 40.65 | AH53: 300 | AI53: 180.18617 | AJ53: 752 | AK53: 1100 | AL53: =(AK53*AJ53*AI53)/10^6 -> 149.05 | AM53: =AL53*U53 -> 85.459606 | AN53: =AI53*AK53 -> 198204.79 | AO53: =AH53*AI53 -> 54055.851 | AP53: =U53+AB53 -> 0.86 | AQ53: =AL53*AP53/(AG53+AE53) -> 2.4095961 | AR53: A lançar
A54: MAP060 | B54: RESIDENCIAL CIDADE JARDIM - LORENA | C54: https://earth.google.com/web/search/LORENA/@-22.76355759,-45.11165622,554.79907101a,2424.9160967d,35y,0h,0t,0r/data=CiwiJgokCdDYYcMpEDbAEb-si-d6FTbAGdP8OMJ1sEnAIeq0yPtJtknAQgIIAToDCgEwQgIIAEoICJfn8a8FEAA?authuser=0 | D54: 1 | E54: LandBank | G54: 2286 | J54: 249 | K54: SUDESTE | L54: LORENA | M54: SP | N54: RESIDENCIAL CIDADE JARDIM I | O54: Parceria | P54: 0 | Q54: Loteamento | R54: Sim | S54: 2027 | T54: 46477 | U54: 0.45 | V54: 0.5 | W54: =SUM(U54:V54) -> 0.95 | X54: 0.05 | Y54: 0.09 | Z54: 0.068 | AA54: 0.198 | AB54: 0.05 | AC54: =AI54*AJ54 -> 331215.05 | AE54: =P54/10^6 -> 0 | AF54: =IF(AL54=0,0,AE54/AL54) -> 0 | AG54: =(AH54*AI54*AJ54)/10^6 -> 53.988053 | AH54: 163 | AI54: 299.20059 | AJ54: 1107 | AK54: 500 | AL54: =(AK54*AJ54*AI54)/10^6 -> 165.60753 | AM54: =AL54*U54 -> 74.523386 | AN54: =AI54*AK54 -> 149600.29 | AO54: =AH54*AI54 -> 48769.696 | AP54: =U54+AB54 -> 0.5 | AQ54: =AL54*AP54/(AG54+AE54) -> 1.5337423 | AR54: A lançar
A55: MAP067 | B55: RESIDENCIAL PARK DOS BURITIS - CAÇAPAVA | C55: https://earth.google.com/web/search/CA%c3%87APAVA/@-23.07539289,-45.73464968,614.24652742a,2481.52766127d,35y,0h,0t,0r/data=CiwiJgokCcNcRG6evShAEQTyLp3d_zzAGZ9UYKQ7AyBAIVqsCoydTFrAQgIIAToDCgEwQgIIAEoICJfn8a8FEAA?authuser=0 | D55: 1 | E55: LandBank | G55: 2272 | J55: 261 | K55: SUDESTE | L55: CAÇAPAVA | M55: SP | N55: RESIDENCIAL PARK DOS BURITIS | O55: Parceria | P55: 0 | Q55: Loteamento | R55: Sim | S55: 2027 | T55: 46660 | U55: 0.64169 | V55: 0.3 | W55: =SUM(U55:V55) -> 0.94169 | X55: 0.05 | Y55: 0.09 | Z55: 0.068 | AA55: 0.198 | AB55: 0.05831 | AC55: =AI55*AJ55 -> 151810 | AE55: =P55/10^6 -> 0 | AF55: =IF(AL55=0,0,AE55/AL55) -> 0 | AG55: =(AH55*AI55*AJ55)/10^6 -> 24.74503 | AH55: 163 | AI55: 170 | AJ55: 893 | AK55: 650 | AL55: =(AK55*AJ55*AI55)/10^6 -> 98.6765 | AM55: =AL55*U55 -> 63.319723 | AN55: =AI55*AK55 -> 110500 | AO55: =AH55*AI55 -> 27710 | AP55: =U55+AB55 -> 0.7 | AQ55: =AL55*AP55/(AG55+AE55) -> 2.791411 | AR55: A lançar
A56: MAP074 | B56: 1A - CACHOEIRA DO SUL - CACHOEIRA DO SUL | C56: https://earth.google.com/web/search/PORTO+ALEGRE/@-30.02393013,-52.88446203,56.86896845a,3471.83898874d,35y,0h,0t,0r/data=CiwiJgokCdF8eOBcqz3AEVk4mQ0orz3AGW7M2FWxNkrAIVpN-_QgO0rAQgIIAToDCgEwQgIIAEoICJfn8a8FEAA?authuser=0 | D56: 1 | E56: LandBank | G56: 2372 | J56: 272 | K56: SUL | L56: CACHOEIRA DO SUL | M56: RS | N56: 1A - CACHOEIRA DO SUL | O56: Parceria | P56: 0 | Q56: Loteamento | R56: Sim | S56: 2027 | T56: 46752 | U56: 0.572 | V56: 0.285 | W56: =SUM(U56:V56) -> 0.857 | X56: 0.07 | Y56: 0 | Z56: 0.068 | AA56: 0.198 | AB56: 0.143 | AC56: =AI56*AJ56 -> 130240 | AE56: =P56/10^6 -> 0 | AF56: =IF(AL56=0,0,AE56/AL56) -> 0 | AG56: =(AH56*AI56*AJ56)/10^6 -> 22.792 | AH56: 175 | AI56: 220 | AJ56: 592 | AK56: 600 | AL56: =(AK56*AJ56*AI56)/10^6 -> 78.144 | AM56: =AL56*U56 -> 44.698368 | AN56: =AI56*AK56 -> 132000 | AO56: =AH56*AI56 -> 38500 | AP56: =U56+AB56 -> 0.715 | AQ56: =AL56*AP56/(AG56+AE56) -> 2.4514286 | AR56: A lançar
A57: MAP081 | B57: 4A - SANTA CRUZ DO SUL - SANTA CRUZ DO SUL | C57: https://earth.google.com/web/search/SANTA+CRUZ+DO+SUL/@-29.67679798,-52.44461427,171.97361515a,2440.82594259d,35y,0h,0t,0r/data=CiwiJgokCfCOoxjmrj3AEQTSMIMEsz3AGejaJMRHlUnAIb28UugYmknAQgIIAToDCgEwQgIIAEoICJfn8a8FEAA?authuser=0 | D57: 1 | E57: LandBank | G57: 2394 | J57: 294 | K57: SUL | L57: SANTA CRUZ DO SUL | M57: RS | N57: 4B - SANTA CRUZ DO SUL | O57: Parceria | P57: 0 | Q57: Loteamento | R57: Sim | S57: 2027 | T57: 46751 | U57: 0.544 | V57: 0.32 | W57: =SUM(U57:V57) -> 0.864 | X57: 0.07 | Y57: 0.095 | Z57: 0.068 | AA57: 0.198 | AB57: 0.136 | AC57: =AI57*AJ57 -> 191004.48 | AE57: =P57/10^6 -> 0 | AF57: =IF(AL57=0,0,AE57/AL57) -> 0 | AG57: =(AH57*AI57*AJ57)/10^6 -> 33.425784 | AH57: 175 | AI57: 314.15211 | AJ57: 608 | AK57: 700 | AL57: =(AK57*AJ57*AI57)/10^6 -> 133.70314 | AM57: =AL57*U57 -> 72.734506 | AN57: =AI57*AK57 -> 219906.47 | AO57: =AH57*AI57 -> 54976.618 | AP57: =U57+AB57 -> 0.68 | AQ57: =AL57*AP57/(AG57+AE57) -> 2.72 | AR57: A lançar
A58: MAP086 | B58: 6A - CAXIAS DO SUL EURO BR - CAXIAS DO SUL | C58: https://earth.google.com/web/search/CAXIAS+DO+SUL/@-29.15422503,-51.2555687,665.66442378a,3641.27206101d,35y,-0h,0t,0r/data=CnwaThJICiUweDk1MWViY2QxNjQzNWYwNzM6MHhmNTE0ZjcwN2I1NzczYmY0GVOObimMLD3AIRz3nKoxl0nAKg1DQVhJQVMgRE8gU1VMGAEgASImCiQJ1tRH0utLPcARa0Tc7klTPcAZjiIdAINaScAhKwpGrRhjScBCAggBOgMKATBCAggASggIl-fxrwUQAA?authuser=0 | D58: 1 | E58: LandBank | G58: 2375 | J58: 299 | K58: SUL | L58: CAXIAS DO SUL | M58: RS | N58: 6A - CAXIAS DO SUL EURO BR | O58: Parceria | P58: 0 | Q58: Loteamento | R58: Sim | S58: 2027 | T58: 46568 | U58: 0.4 | W58: =SUM(U58:V58) -> 0.4 | X58: 0.07 | Y58: 0.095 | Z58: 0.068 | AA58: 0.198 | AB58: 0.6 | AC58: =AI58*AJ58 -> 273025 | AE58: =P58/10^6 -> 0 | AF58: =IF(AL58=0,0,AE58/AL58) -> 0 | AG58: =(AH58*AI58*AJ58)/10^6 -> 47.779375 | AH58: 175 | AI58: 335 | AJ58: 815 | AK58: 750 | AL58: =(AK58*AJ58*AI58)/10^6 -> 204.76875 | AM58: =AL58*U58 -> 81.9075 | AN58: =AI58*AK58 -> 251250 | AO58: =AH58*AI58 -> 58625 | AP58: =U58+AB58 -> 1 | AQ58: =AL58*AP58/(AG58+AE58) -> 4.2857143 | AR58: A lançar
A59: MAP092 | B59: 7 - CANELA I - CANELA | C59: https://earth.google.com/web/search/CANELA/@-29.31096028,-50.74065533,783.58216028a,4290.20961313d,35y,0h,0t,0r/data=CiwiJgokCaHXsZR7Dj7AEYnRurPGEj7AGVFhjI5xgknAIZdzDtB7h0nAQgIIAToDCgEwQgIIAEoICJfn8a8FEAA?authuser=0 | D59: 1 | E59: LandBank | G59: 2373 | J59: 305 | K59: SUL | L59: CANELA | M59: RS | N59: 7 - CANELA I | O59: Parceria | P59: 0 | Q59: Loteamento | R59: - | S59: 2027 | T59: 46568 | U59: 0.5918 | V59: 0.2603 | W59: =SUM(U59:V59) -> 0.8521 | X59: 0.07 | Y59: 0.095 | Z59: 0.068 | AA59: 0.198 | AB59: 0.1479 | AC59: =AI59*AJ59 -> 375000 | AE59: =P59/10^6 -> 0 | AF59: =IF(AL59=0,0,AE59/AL59) -> 0 | AG59: =(AH59*AI59*AJ59)/10^6 -> 65.625 | AH59: 175 | AI59: 400 | AJ59: 937.5 | AK59: 800 | AL59: =(AK59*AJ59*AI59)/10^6 -> 300 | AM59: =AL59*U59 -> 177.54 | AN59: =AI59*AK59 -> 320000 | AO59: =AH59*AI59 -> 70000 | AP59: =U59+AB59 -> 0.7397 | AQ59: =AL59*AP59/(AG59+AE59) -> 3.3814857 | AR59: A lançar
A60: MAP093 | B60: 8A - VIAMÃO - MARCELO GAMBOGI - VIAMÃO | C60: https://earth.google.com/web/search/VIAM%c3%83O/@-30.10093213,-51.01714168,46.73583292a,2431.1818362d,35y,0h,0t,0r/data=CnYaSBJCCiUweDk1MTk5OGE2ZDhmMjY0NDE6MHgxNWY0MmRhYTgyYjY2ZDQwGXCFZo0wFT7AIQB4nz5dhEnAKgdWSUFNw4NPGAEgASImCiQJsTk0ZNOlP8ARLqkiuNytP8AZ9eUZULQnSsAh8JLJOEwxSsBCAggBOgMKATBCAggASggIl-fxrwUQAA?authuser=0 | D60: 1 | E60: LandBank | G60: 2388 | J60: 309 | K60: SUL | L60: VIAMÃO | M60: RS | N60: 8A - VIAMÃO - MARCELO GAMBOGI | O60: Parceria | P60: 0 | Q60: Loteamento | R60: - | S60: 2027 | T60: 46477 | U60: 0.56 | V60: 0.3 | W60: =SUM(U60:V60) -> 0.86 | X60: 0.07 | Y60: 0.095 | Z60: 0.068 | AA60: 0.198 | AB60: 0.14 | AC60: =AI60*AJ60 -> 148565 | AE60: =P60/10^6 -> 0 | AF60: =IF(AL60=0,0,AE60/AL60) -> 0 | AG60: =(AH60*AI60*AJ60)/10^6 -> 25.998875 | AH60: 175 | AI60: 215 | AJ60: 691 | AK60: 600 | AL60: =(AK60*AJ60*AI60)/10^6 -> 89.139 | AM60: =AL60*U60 -> 49.91784 | AN60: =AI60*AK60 -> 129000 | AO60: =AH60*AI60 -> 37625 | AP60: =U60+AB60 -> 0.7 | AQ60: =AL60*AP60/(AG60+AE60) -> 2.4 | AR60: A lançar
A61: MAP096 | B61: 9A - PELOTAS - RESIDENCIAL RCL - PELOTAS | C61: https://earth.google.com/web/search/PELOTAS/@-31.66345999,-52.34766459,33.86198261a,5500.41331546d,35y,0h,0t,0r/data=CiwiJgokCcTGFe60DEDAEbD1lg7sD0DAGcKY98kGFErAITOrTYO9G0rAQgIIAToDCgEwQgIIAEoICJfn8a8FEAA?authuser=0 | D61: 1 | E61: LandBank | G61: 2380 | J61: 312 | K61: SUL | L61: PELOTAS | M61: RS | N61: 9A - PELOTAS - RESIDENCIAL RCL | O61: Parceria | P61: 0 | Q61: Loteamento | R61: Sim | S61: 2027 | T61: 46477 | U61: 0.56 | V61: 0.3 | W61: =SUM(U61:V61) -> 0.86 | X61: 0.07 | Y61: 0.095 | Z61: 0.068 | AA61: 0.198 | AB61: 0.14 | AC61: =AI61*AJ61 -> 330750 | AE61: =P61/10^6 -> 0 | AF61: =IF(AL61=0,0,AE61/AL61) -> 0 | AG61: =(AH61*AI61*AJ61)/10^6 -> 57.88125 | AH61: 175 | AI61: 225 | AJ61: 1470 | AK61: 550 | AL61: =(AK61*AJ61*AI61)/10^6 -> 181.9125 | AM61: =AL61*U61 -> 101.871 | AN61: =AI61*AK61 -> 123750 | AO61: =AH61*AI61 -> 39375 | AP61: =U61+AB61 -> 0.7 | AQ61: =AL61*AP61/(AG61+AE61) -> 2.2 | AR61: A lançar
A62: MAP124 | B62: 9C - PELOTAS - INDUSTRIAL RCL II | D62: 1 | E62: LandBank | G62: 2380 | K62: SUL | L62: PELOTAS | M62: RS | N62: 9c - Pelotas - Industrial RCL II | O62: Parceria | P62: 0 | Q62: Loteamento | R62: Sim | S62: 2027 | T62: 46568 | U62: 0.552 | V62: 0.31 | W62: =SUM(U62:V62) -> 0.862 | AA62: 0.198 | AC62: =AI62*AJ62 -> 179396 | AE62: =P62/10^6 -> 0 | AF62: =IF(AL62=0,0,AE62/AL62) -> 0 | AG62: =(AH62*AI62*AJ62)/10^6 -> 31.3943 | AH62: 175 | AI62: 1043 | AJ62: 172 | AK62: 900 | AL62: =(AK62*AJ62*AI62)/10^6 -> 161.4564 | AM62: =AL62*U62 -> 89.123933 | AN62: =AI62*AK62 -> 938700 | AO62: =AH62*AI62 -> 182525 | AP62: =U62+AB62 -> 0.552 | AQ62: =AL62*AP62/(AG62+AE62) -> 2.8388571 | AR62: A lançar
A63: MAP021 | B63: ARSO 182 - PALMAS | C63: https://earth.google.com/web/search/Palmas/@-10.25056053,-48.33726188,252.56505595a,47484.59826451d,35y,0h,0t,0r/data=CnQaRhJACiQweDkzM2IzNDM5OTExZjEyNTc6MHg5M2I4MDcwZDA1YzgxOGYZtHQF24h_JMAhUsd0MoIpSMAqBlBhbG1hcxgCIAEiJgokCZ4TQp4rbCTAEd7oz8tIyyTAGZMBVXzHEEjAIR-xYc3lQUjAQgIIAToDCgEwQgIIAEoICJfn8a8FEAA?authuser=0 | D63: 1 | E63: LandBank | G63: PENDENCIA | J63: 161 | K63: TOCANTINS | L63: PALMAS | M63: TO | N63: ARSO 182 | O63: Parceria | P63: 0 | Q63: Loteamento | R63: - | S63: 2027 | T63: 46752 | U63: 0.6055 | W63: =SUM(U63:V63) -> 0.6055 | AA63: 0.198 | AB63: 0.3945 | AC63: =AI63*AJ63 -> 233060 | AE63: =P63/10^6 -> 0 | AF63: =IF(AL63=0,0,AE63/AL63) -> 0 | AG63: =(AH63*AI63*AJ63)/10^6 -> 29.83168 | AH63: 128 | AI63: 275.15939 | AJ63: 847 | AK63: 550 | AL63: =(AK63*AJ63*AI63)/10^6 -> 128.183 | AM63: =AL63*U63 -> 77.614807 | AN63: =AI63*AK63 -> 151337.66 | AO63: =AH63*AI63 -> 35220.401 | AP63: =U63+AB63 -> 1 | AQ63: =AL63*AP63/(AG63+AE63) -> 4.296875 | AR63: A lançar
A64: MAP021 | B64: A DEFINIR - AREA AEROPORTO - PALMAS | C64: https://earth.google.com/web/search/Palmas,+TO/@-10.3121257,-48.32472401,257.8116143a,12197.49387353d,35y,0h,0t,0r/data=CngaShJECiQweDkzM2IzNDM5OTExZjEyNTc6MHg5M2I4MDcwZDA1YzgxOGYZtHQF24h_JMAhUsd0MoIpSMAqClBhbG1hcywgVE8YASABIiYKJAnKmUn74gAbwBGE16-ZZBobwBm4d1Wa5ohJwCHUhDGVbI9JwEICCAE6AwoBMEICCABKCAiX5_GvBRAA?authuser=0 | D64: 1 | E64: LandBank | G64: PENDENCIA | J64: 179 | K64: TOCANTINS | L64: PALMAS | M64: TO | N64: A DEFINIR - AREA AEROPORTO - ÉDER | O64: Compra e Venda | P64: 2781250 | Q64: Loteamento | R64: - | S64: 2027 | T64: 46752 | U64: 0.6 | W64: =SUM(U64:V64) -> 0.6 | AA64: 0.198 | AB64: 0.4 | AC64: =AI64*AJ64 -> 160000 | AE64: =P64/10^6 -> 2.78125 | AF64: =IF(AL64=0,0,AE64/AL64) -> 0.034765625 | AG64: =(AH64*AI64*AJ64)/10^6 -> 20.48 | AH64: 128 | AI64: 300.18762 | AJ64: 533 | AK64: 500 | AL64: =(AK64*AJ64*AI64)/10^6 -> 80 | AM64: =AL64*U64 -> 48 | AN64: =AI64*AK64 -> 150093.81 | AO64: =AH64*AI64 -> 38424.015 | AP64: =U64+AB64 -> 1 | AQ64: =AL64*AP64/(AG64+AE64) -> 3.4391961 | AR64: A lançar
A65: MAP029 | B65: A DEFINIR - BARREIRAS | C65: https://earth.google.com/web/search/BARREIRAS/@-12.12902491,-44.94390721,473.95179666a,4444.42186318d,35y,360h,0t,0r/data=CiwiJgokCbyBSCYESh5AEYWkuzkFYEDAGVnoii3lCChAIf8sz7P4HlvAQgIIAToDCgEwQgIIAEoICJfn8a8FEAA?authuser=0 | D65: 1 | E65: Estudo de viabilidade | G65: 2313 | J65: 191 | K65: TOCANTINS | L65: BARREIRAS | M65: BA | N65: A DEFINIR - André e Isaura Castro de Sá | O65: Compra e Venda | P65: 6000000 | Q65: Loteamento | R65: Sim | S65: 2027 | T65: 46568 | U65: 0.442 | V65: 0.35 | W65: =SUM(U65:V65) -> 0.792 | X65: 0.05 | Y65: 0.09 | Z65: 0.068 | AA65: 0.198 | AB65: 0.208 | AC65: =AI65*AJ65 -> 149072 | AE65: =P65/10^6 -> 6 | AF65: =IF(AL65=0,0,AE65/AL65) -> 0.073180013 | AG65: =(AH65*AI65*AJ65)/10^6 -> 19.081216 | AH65: 128 | AI65: 242 | AJ65: 616 | AK65: 550 | AL65: =(AK65*AJ65*AI65)/10^6 -> 81.9896 | AM65: =AL65*U65 -> 36.239403 | AN65: =AI65*AK65 -> 133100 | AO65: =AH65*AI65 -> 30976 | AP65: =U65+AB65 -> 0.65 | AQ65: =AL65*AP65/(AG65+AE65) -> 2.1248268 | AR65: A lançar
A66: MAP138 | B66: A DEFINIR | D66: 1 | E66: LandBank | K66: NORTE | L66: PARAUAPEBAS | M66: PA | N66: Àrea Catalão | O66: Compra e Venda | P66: 27000000 | Q66: Loteamento | R66: - | S66: 2027 | T66: 46721 | U66: 1 | W66: =SUM(U66:V66) -> 1 | AA66: 1 | AC66: =AI66*AJ66 -> 579800 | AE66: =P66/10^6 -> 27 | AF66: 1 | AG66: =(AH66*AI66*AJ66)/10^6 -> 77.1134 | AH66: 133 | AI66: 223 | AJ66: 2600 | AK66: 600 | AL66: =(AK66*AJ66*AI66)/10^6 -> 347.88 | AM66: =AL66*U66 -> 347.88 | AN66: =AI66*AK66 -> 133800 | AO66: =AH66*AI66 -> 29659 | AP66: 1 | AQ66: =AL66*AP66/(AG66+AE66) -> 3.3413566 | AR66: A lançar
A67: MAP001 | B67: CIDADE JARDIM - ETP II - BELA VISTA | C67: https://earth.google.com/web/search/BELA+VISTA/@-16.96124568,-48.94579579,823.03102905a,3707.10942264d,35y,-0h,0t,0r/data=CnkaSxJFCiUweDkzNWYyNTZjZmU4NDk4OGQ6MHhiNDk0MzE3NTE3MDU3YTA5GVl5E43_-DDAIcOVWL7TeUjAKgpCRUxBIFZJU1RBGAIgASImCiQJ0WMLs4K1IMAREBK2sOjBIMAZM_Z2zLqhSMAh4pu9YBioSMBCAggBOgMKATBCAggASggIl-fxrwUQAA?authuser=0 | D67: 1 | E67: LandBank | G67: 2040 | J67: 356 | K67: CENTRO-OESTE I | L67: BELA VISTA DE GOIÁS | M67: GO | N67: CIDADE JARDIM - ETP II | O67: Arrematação judicial | P67: 11775750 | Q67: Loteamento | R67: Sim | S67: 2028 | T67: 46934 | U67: 0.75 | V67: 0.25 | W67: =SUM(U67:V67) -> 1 | X67: 0.05 | Y67: 0.09 | Z67: 0.068 | AA67: 0.198 | AC67: =AI67*AJ67 -> 180249.09 | AE67: =P67/10^6 -> 11.77575 | AF67: =IF(AL67=0,0,AE67/AL67) -> 0.1333274 | AG67: =(AH67*AI67*AJ67)/10^6 -> 26.676865 | AH67: 148 | AI67: 304.99 | AJ67: 591 | AK67: 490 | AL67: =(AK67*AJ67*AI67)/10^6 -> 88.322054 | AM67: =AL67*U67 -> 66.241541 | AN67: =AI67*AK67 -> 149445.1 | AO67: =AH67*AI67 -> 45138.52 | AP67: =U67+AB67 -> 0.75 | AQ67: =AL67*AP67/(AG67+AE67) -> 1.7226797 | AR67: A lançar
A68: MAP122 | B68: JARDIM DO CERRADO 8 II - GOIÂNIA | C68: https://earth.google.com/web/search/GOI%c3%82NIA/@-16.67746594,-49.42770992,858.01737984a,4789.30417081d,35y,9.31126662h,0.18897674t,360r/data=CiwiJgokCTImrsNH8yrAEajobj-t-irAGWOHbhWxkEjAIXn8jCOOlEjAQgIIAToDCgEwQgIIAEoICJfn8a8FEAA?authuser=0 | D68: 1 | E68: LandBank | G68: 2770 | J68: 362 | K68: CENTRO-OESTE II | L68: GOIÂNIA | M68: GO | N68: JARDIM DO CERRADO 8 II | O68: Parceria | P68: 0 | Q68: Loteamento | R68: - | S68: 2028 | T68: 47118 | U68: 0.8 | W68: =SUM(U68:V68) -> 0.8 | AA68: 0.198 | AB68: 0.2 | AC68: =AI68*AJ68 -> 139944.68 | AE68: =P68/10^6 -> 0 | AF68: =IF(AL68=0,0,AE68/AL68) -> 0 | AG68: =(AH68*AI68*AJ68)/10^6 -> 20.711813 | AH68: 148 | AI68: 279.88937 | AJ68: 500 | AK68: 500 | AL68: =(AK68*AJ68*AI68)/10^6 -> 69.972342 | AM68: =AL68*U68 -> 55.977874 | AN68: =AI68*AK68 -> 139944.68 | AO68: =AH68*AI68 -> 41423.627 | AP68: =U68+AB68 -> 1 | AQ68: =AL68*AP68/(AG68+AE68) -> 3.3783784 | AR68: A lançar
A69: MAP133 | B69: ANAMARIA SANTOS GUIMARÃES | D69: 1 | E69: LandBank | G69: 2041 | K69: CENTRO-OESTE II | L69: CALDAS NOVAS | M69: GO | N69: A DEFINIR | O69: Parceria | P69: 0 | Q69: Loteamento | S69: 2028 | T69: 46935 | U69: 0.725 | V69: =27.5%-15% -> 0.125 | W69: =SUM(U69:V69) -> 0.85 | AA69: 0.198 | AB69: 0.15 | AC69: =AI69*AJ69 -> 818954.5 | AE69: =P69/10^6 -> 0 | AF69: =IF(AL69=0,0,AE69/AL69) -> 0 | AG69: =(AH69*AI69*AJ69)/10^6 -> 196.54908 | AH69: 240 | AI69: 219.5 | AJ69: 3731 | AK69: 520 | AL69: =(AK69*AJ69*AI69)/10^6 -> 425.85634 | AM69: =AL69*U69 -> 308.74585 | AN69: =AI69*AK69 -> 114140 | AO69: =AH69*AI69 -> 52680 | AP69: =U69+AB69 -> 0.875 | AQ69: =AL69*AP69/(AG69+AE69) -> 1.8958333 | AR69: A lançar
A70: MAP036 | B70: RESIDENCIAL JARDIM EUROPA 2 - ALAGOINHA | C70: https://earth.google.com/web/search/RESIDENCIAL+JARDIM+EUROPA+2+-+ALAGOINHA/@-12.16901753,-38.4079717,117.33325024a,3592.41516492d,35y,0h,0t,0r/data=CiwiJgokCVvsaFFQZxrAESI5vVrxVB7AGWgJCTaDWkHAIWhUtp4sXELAQgIIAToDCgEwQgIIAEoICJfn8a8FEAA?authuser=0 | D70: 1 | E70: LandBank | G70: 2044 | J70: 201 | K70: NORDESTE I | L70: ALAGOINHA | M70: BA | N70: RESIDENCIAL JARDIM EUROPA 2 | O70: Compra e Venda | P70: 2000000 | Q70: Loteamento | R70: Sim | S70: 2028 | T70: 46843 | U70: 0.8 | W70: =SUM(U70:V70) -> 0.8 | AA70: 0.198 | AB70: 0.2 | AC70: =AI70*AJ70 -> 187500 | AE70: =P70/10^6 -> 2 | AF70: =IF(AL70=0,0,AE70/AL70) -> 0.023188406 | AG70: =(AH70*AI70*AJ70)/10^6 -> 22.5 | AH70: 120 | AI70: 180 | AJ70: 1041.6667 | AK70: 460 | AL70: =(AK70*AJ70*AI70)/10^6 -> 86.25 | AM70: =AL70*U70 -> 69 | AN70: =AI70*AK70 -> 82800 | AO70: =AH70*AI70 -> 21600 | AP70: =U70+AB70 -> 1 | AQ70: =AL70*AP70/(AG70+AE70) -> 3.5204082 | AR70: A lançar
A71: MAP039 | B71: JARDIM TROPICAL II - ITAPIPOCA | C71: https://earth.google.com/web/search/ITAPIPOCA/@-3.48318447,-39.60453858,85.75014124a,4591.68380015d,35y,0h,0t,0r/data=CiwiJgokCSj18Ul83hfAEYrTwO0U8hfAGYnj-uRdJETAIcMsoPJeKUTAQgIIAToDCgEwQgIIAEoICJfn8a8FEAA?authuser=0 | D71: 1 | E71: LandBank | G71: 2054 | J71: 206 | K71: NORDESTE II | L71: ITAPIPOCA | M71: CE | N71: JARDIM TROPICAL II | O71: Compra e Venda | P71: 750000 | Q71: Loteamento | R71: Sim | S71: 2028 | T71: 47026 | U71: 0.8 | V71: 0.2 | W71: =SUM(U71:V71) -> 1 | X71: 0.05 | Y71: 0 | Z71: 0.068 | AA71: 0.198 | AC71: =AI71*AJ71 -> 186384 | AE71: =P71/10^6 -> 0.75 | AF71: =IF(AL71=0,0,AE71/AL71) -> 0.0080479011 | AG71: =(AH71*AI71*AJ71)/10^6 -> 24.789072 | AH71: 133 | AI71: 176 | AJ71: 1059 | AK71: 500 | AL71: =(AK71*AJ71*AI71)/10^6 -> 93.192 | AM71: =AL71*U71 -> 74.5536 | AN71: =AI71*AK71 -> 88000 | AO71: =AH71*AI71 -> 23408 | AP71: =U71+AB71 -> 0.8 | AQ71: =AL71*AP71/(AG71+AE71) -> 2.9191977 | AR71: A lançar
A72: MAP040 | B72: JARDIM AMERICA II - TAUÁ | C72: https://earth.google.com/web/search/TAU%c3%81/@-5.97683983,-40.30366275,407.4430109a,2966.57752085d,35y,0h,0t,0r/data=CiwiJgokCVwuodN7uSdAEajZ7_kEaz3AGcctYEv-xi1AIcrxv7LiwVjAQgIIAToDCgEwQgIIAEoICJfn8a8FEAA?authuser=0 | D72: 1 | E72: LandBank | G72: 2056 | J72: 207 | K72: NORDESTE II | L72: TAUÁ | M72: CE | N72: JARDIM AMERICA II | O72: Parceria | P72: 0 | Q72: Loteamento | R72: Sim | S72: 2028 | T72: 46842 | U72: 0.79 | V72: 0.21 | W72: =SUM(U72:V72) -> 1 | X72: 0.05 | Y72: 0 | Z72: 0.068 | AA72: 0.198 | AC72: =AI72*AJ72 -> 201792 | AE72: =P72/10^6 -> 0 | AF72: =IF(AL72=0,0,AE72/AL72) -> 0 | AG72: =(AH72*AI72*AJ72)/10^6 -> 21.793536 | AH72: 108 | AI72: 192 | AJ72: 1051 | AK72: 480 | AL72: =(AK72*AJ72*AI72)/10^6 -> 96.86016 | AM72: =AL72*U72 -> 76.519526 | AN72: =AI72*AK72 -> 92160 | AO72: =AH72*AI72 -> 20736 | AP72: =U72+AB72 -> 0.79 | AQ72: =AL72*AP72/(AG72+AE72) -> 3.5111111 | AR72: A lançar
A73: MAP009 | B73: CIDADE JARDIM IV - SANTARÉM | C73: https://earth.google.com/web/search/CIDADE+JARDIM+12+-+PARAUAPEBAS/@-2.45795692,-54.77217012,46.50042218a,6405.178905d,35y,-0h,0t,0r/data=CiwiJgokCdmVqMeMyQbAESVW3mJaMwnAGYI6tUF7jUfAIaCAQToN3EfAQgIIAToDCgEwQgIIAEoICJfn8a8FEAA | D73: 1 | E73: LandBank | G73: 2121 | J73: 149 | K73: NORTE | L73: SANTARÉM | M73: PA | N73: CIDADE JARDIM IV | O73: Aquisição de Cotas | P73: 4800000 | Q73: Loteamento | R73: Sim | S73: 2028 | T73: 47118 | U73: 1 | W73: =SUM(U73:V73) -> 1 | AA73: 0.198 | AC73: =AI73*AJ73 -> 410455.51 | AE73: =P73/10^6 -> 4.8 | AF73: =IF(AL73=0,0,AE73/AL73) -> 0.023388649 | AG73: =(AH73*AI73*AJ73)/10^6 -> 54.631628 | AH73: 133.1 | AI73: 239.89217 | AJ73: 1711 | AK73: 500 | AL73: =(AK73*AJ73*AI73)/10^6 -> 205.22776 | AM73: =AL73*U73 -> 205.22776 | AN73: =AI73*AK73 -> 119946.09 | AO73: =AH73*AI73 -> 31929.648 | AP73: =U73+AB73 -> 1 | AQ73: =AL73*AP73/(AG73+AE73) -> 3.453174 | AR73: A lançar
A74: MAP013 | B74: RESIDENCIAL CIDADE JARDIM II - SANTANA DO ARAGUAIA | C74: https://earth.google.com/web/search/SANTANA+DO+ARAGUAIA/@-9.33586436,-50.36139721,175.24087708a,6146.88773774d,35y,0.00000002h,0t,0r/data=CoIBGlQSTgolMHg5MzFmMzU2MjJhMTljZmQxOjB4NDBiYzMzMTdkYTkxODA2NxkY0GYwoa0iwCGS2Q9nNCtJwCoTU0FOVEFOQSBETyBBUkFHVUFJQRgCIAEiJgokCSW03oMpdxzAEQai9168gBzAGSqKf2w09UjAIfPbVLWn90jAQgIIAToDCgEwQgIIAEoICJfn8a8FEAA?authuser=0 | D74: 1 | E74: LandBank | G74: 2123 | J74: 153 | K74: NORTE | L74: SANTANA DO ARAGUAIA | M74: PA | N74: RESIDENCIAL CIDADE JARDIM II | O74: Compra e Venda | P74: 114285.71 | Q74: Loteamento | R74: Sim | S74: 2028 | T74: 47118 | U74: 1 | W74: =SUM(U74:V74) -> 1 | AA74: 0.198 | AC74: =AI74*AJ74 -> 121800 | AE74: =P74/10^6 -> 0.11428571 | AF74: =IF(AL74=0,0,AE74/AL74) -> 0.0024059136 | AG74: =(AH74*AI74*AJ74)/10^6 -> 16.21158 | AH74: 133.1 | AI74: 210 | AJ74: 580 | AK74: 390 | AL74: =(AK74*AJ74*AI74)/10^6 -> 47.502 | AM74: =AL74*U74 -> 47.502 | AN74: =AI74*AK74 -> 81900 | AO74: =AH74*AI74 -> 27951 | AP74: =U74+AB74 -> 1 | AQ74: =AL74*AP74/(AG74+AE74) -> 2.909616 | AR74: A lançar
A75: MAP113 | B75: BURITI GARDEN PRIME II - VARZEA GRANDE | C75: https://earth.google.com/web/search/CUIAB%c3%81/@-15.61005921,-56.15084275,175.93804739a,4592.0123658d,35y,0h,0t,0r/data=CiwiJgokCTDbVLh45ybAEXD1A07O7ybAGaZZUBA5uU7AIdT4-d2KvU7AQgIIAToDCgEwQgIIAEoICJfn8a8FEAA?authuser=0 | D75: 1 | E75: LandBank | G75: 1930 | J75: 347 | K75: OESTE | L75: VÁRZEA GRANDE | M75: MT | N75: BURITI GARDEN PRIME II | O75: Parceria | P75: 0 | Q75: Condominio | R75: - | S75: 2028 | T75: 46934 | U75: 0.7 | V75: 0.3 | W75: =SUM(U75:V75) -> 1 | X75: 0.05 | Y75: 0.09 | Z75: 0.068 | AA75: 0.198 | AC75: =AI75*AJ75 -> 154037 | AE75: =P75/10^6 -> 0 | AF75: =IF(AL75=0,0,AE75/AL75) -> 0 | AG75: =(AH75*AI75*AJ75)/10^6 -> 40.04962 | AH75: 260 | AI75: 289 | AJ75: 533 | AK75: 1500 | AL75: =(AK75*AJ75*AI75)/10^6 -> 231.0555 | AM75: =AL75*U75 -> 161.73885 | AN75: =AI75*AK75 -> 433500 | AO75: =AH75*AI75 -> 75140 | AP75: =U75+AB75 -> 0.7 | AQ75: =AL75*AP75/(AG75+AE75) -> 4.0384615 | AR75: A lançar
A76: MAP114 | B76: BURITI GARDEN PRIME III - VARZEA GRANDE | C76: https://earth.google.com/web/search/CUIAB%c3%81/@-15.61005921,-56.15084275,175.93804739a,4592.0123658d,35y,0h,0t,0r/data=CiwiJgokCTDbVLh45ybAEXD1A07O7ybAGaZZUBA5uU7AIdT4-d2KvU7AQgIIAToDCgEwQgIIAEoICJfn8a8FEAA?authuser=0 | D76: 1 | E76: LandBank | G76: 1930 | J76: 348 | K76: OESTE | L76: VÁRZEA GRANDE | M76: MT | N76: BURITI GARDEN PRIME III | O76: Parceria | P76: 0 | Q76: Condominio | R76: - | S76: 2028 | T76: 46934 | U76: 0.7 | V76: 0.3 | W76: =SUM(U76:V76) -> 1 | X76: 0.05 | Y76: 0.09 | Z76: 0.068 | AA76: 0.198 | AC76: =AI76*AJ76 -> 121000 | AE76: =P76/10^6 -> 0 | AF76: =IF(AL76=0,0,AE76/AL76) -> 0 | AG76: =(AH76*AI76*AJ76)/10^6 -> 31.46 | AH76: 260 | AI76: 220 | AJ76: 550 | AK76: 1500 | AL76: =(AK76*AJ76*AI76)/10^6 -> 181.5 | AM76: =AL76*U76 -> 127.05 | AN76: =AI76*AK76 -> 330000 | AO76: =AH76*AI76 -> 57200 | AP76: =U76+AB76 -> 0.7 | AQ76: =AL76*AP76/(AG76+AE76) -> 4.0384615 | AR76: A lançar
A77: MAP127 | B77: SPE BTMV EMPREENDIMENTOS IMOBILIARIOS LTDA | D77: 1 | E77: LandBank | G77: 1929 | K77: OESTE | L77: VÁRZEA GRANDE | M77: MT | N77: SPE BTMV EMPREENDIMENTOS IMOBILIARIOS LTDA | O77: Parceria | P77: 0 | Q77: Condominio | R77: - | S77: 2028 | T77: 46934 | U77: 0.7 | V77: 0.3 | W77: =SUM(U77:V77) -> 1 | AA77: 0.198 | AC77: =AI77*AJ77 -> 139700 | AE77: =P77/10^6 -> 0 | AF77: =IF(AL77=0,0,AE77/AL77) -> 0 | AG77: =(AH77*AI77*AJ77)/10^6 -> 41.91 | AH77: 300 | AI77: 220 | AJ77: 635 | AK77: 1500 | AL77: =(AK77*AJ77*AI77)/10^6 -> 209.55 | AM77: =AL77*U77 -> 146.685 | AN77: =AI77*AK77 -> 330000 | AO77: =AH77*AI77 -> 66000 | AP77: =U77+AB77 -> 0.7 | AQ77: =AL77*AP77/(AG77+AE77) -> 3.5 | AR77: A lançar
A78: MAP115 | B78: BURITI GARDEN PREMIUM - CUIABÁ | C78: https://earth.google.com/web/search/CUIAB%c3%81/@-15.55669308,-56.14650334,159.69800373a,2841.75984399d,35y,0h,0t,0r/data=CiwiJgokCTDbVLh45ybAEXD1A07O7ybAGaZZUBA5uU7AIdT4-d2KvU7AQgIIAToDCgEwQgIIAEoICJfn8a8FEAA?authuser=0 | D78: 1 | E78: LandBank | G78: 2100 | J78: 349 | K78: OESTE | L78: CUIABÁ | M78: MT | N78: BURITI GARDEN PREMIUM | O78: Parceria | P78: 0 | Q78: Condominio | R78: - | S78: 2028 | T78: 47026 | U78: 0.65 | V78: 0.35 | W78: =SUM(U78:V78) -> 1 | X78: 0.05 | Y78: 0 | Z78: 0.068 | AA78: 0.198 | AC78: =AI78*AJ78 -> 271959.14 | AE78: =P78/10^6 -> 0 | AF78: =IF(AL78=0,0,AE78/AL78) -> 0 | AG78: =(AH78*AI78*AJ78)/10^6 -> 87.026924 | AH78: 320 | AI78: 360.21078 | AJ78: 755 | AK78: 2000 | AL78: =(AK78*AJ78*AI78)/10^6 -> 543.91828 | AM78: =AL78*U78 -> 353.54688 | AN78: =AI78*AK78 -> 720421.56 | AO78: =AH78*AI78 -> 115267.45 | AP78: =U78+AB78 -> 0.65 | AQ78: =AL78*AP78/(AG78+AE78) -> 4.0625 | AR78: A lançar
A79: MAP118 | B79: RESIDENCIAL CIDADE JARDIM II - ROLIM DE MOURA | C79: https://earth.google.com/web/search/ROLIM+DE+MOURA/@-11.70003411,-61.7878114,251.9337313a,3182.60368671d,35y,0h,0t,0r/data=CnwaThJICiQweDkzYzg2YmYyMDQ1MWZkNDc6MHg4MjlmMWM5MmZjMTJiNGQZjYZCuo5zJ8AhCpf6HprjTsAqDlJPTElNIERFIE1PVVJBGAEgASImCiQJU-hXLybDI8ARtbsCkK3JI8AZWYZJdKGGT8Ah1B97Of-JT8BCAggBOgMKATBCAggASggIl-fxrwUQAA?authuser=0 | D79: 1 | E79: LandBank | G79: 2000 | J79: 352 | K79: OESTE | L79: ROLIM DE MOURA | M79: RO | N79: RESIDENCIAL CIDADE JARDIM II | O79: Compra e Venda | P79: 250000 | Q79: Loteamento | R79: Sim | S79: 2028 | T79: 46934 | U79: 0.7 | V79: 0.3 | W79: =SUM(U79:V79) -> 1 | X79: 0.05 | Y79: 0.05 | Z79: 0.068 | AA79: 0.198 | AC79: =AI79*AJ79 -> 286880 | AE79: =P79/10^6 -> 0.25 | AF79: =IF(AL79=0,0,AE79/AL79) -> 0.0021302024 | AG79: =(AH79*AI79*AJ79)/10^6 -> 38.15504 | AH79: 133 | AI79: 220 | AJ79: 1304 | AK79: 409.09 | AL79: =(AK79*AJ79*AI79)/10^6 -> 117.35974 | AM79: =AL79*U79 -> 82.151817 | AN79: =AI79*AK79 -> 89999.8 | AO79: =AH79*AI79 -> 29260 | AP79: =U79+AB79 -> 0.7 | AQ79: =AL79*AP79/(AG79+AE79) -> 2.1390895 | AR79: A lançar
A80: MAP119 | B80: RESIDENCIAL CIDADE JARDIM IIII - ROLIM DE MOURA | C80: https://earth.google.com/web/search/ROLIM+DE+MOURA/@-11.70003411,-61.7878114,251.9337313a,3182.60368671d,35y,0h,0t,0r/data=CnwaThJICiQweDkzYzg2YmYyMDQ1MWZkNDc6MHg4MjlmMWM5MmZjMTJiNGQZjYZCuo5zJ8AhCpf6HprjTsAqDlJPTElNIERFIE1PVVJBGAEgASImCiQJU-hXLybDI8ARtbsCkK3JI8AZWYZJdKGGT8Ah1B97Of-JT8BCAggBOgMKATBCAggASggIl-fxrwUQAA?authuser=0 | D80: 1 | E80: LandBank | G80: 2108 | J80: 353 | K80: OESTE | L80: ROLIM DE MOURA | M80: RO | N80: RESIDENCIAL CIDADE JARDIM IIII | O80: Compra e Venda | P80: 250000 | Q80: Loteamento | R80: - | S80: - | T80: - | U80: 0.7 | V80: 0.3 | W80: =SUM(U80:V80) -> 1 | X80: 0.05 | Y80: 0.05 | Z80: 0.068 | AA80: 0.198 | AC80: =AI80*AJ80 -> 69757.27 | AE80: =P80/10^6 -> 0.25 | AF80: =IF(AL80=0,0,AE80/AL80) -> 0.0083345485 | AG80: =(AH80*AI80*AJ80)/10^6 -> 9.2777169 | AH80: 133 | AI80: 255.52114 | AJ80: 273 | AK80: 430 | AL80: =(AK80*AJ80*AI80)/10^6 -> 29.995626 | AM80: =AL80*U80 -> 20.996938 | AN80: =AI80*AK80 -> 109874.09 | AO80: =AH80*AI80 -> 33984.311 | AP80: =U80+AB80 -> 0.7 | AQ80: =AL80*AP80/(AG80+AE80) -> 2.2037744 | AR80: A lançar
A81: MAP120 | B81: RESIDENCIAL CIDADE JARDIM III - ARIQUEMES | C81: https://earth.google.com/web/search/ARIQUEMES/@-9.88752676,-63.06495176,110.43672402a,2137.88748754d,35y,0h,0t,0r/data=CngaShJECiUweDkzY2M4ZmY5NTkwYWU4OTc6MHg0OTM5OGYxNTllOGY5YmEzGQOoTqz4zyPAIejEeZM6hE_AKglBUklRVUVNRVMYASABIiYKJAn0V4MWyvIwwBExfXARXvkwwBmukrOFkXVIwCHsK48mjnxIwEICCAE6AwoBMEICCABKCAiX5_GvBRAA?authuser=0 | D81: 1 | E81: LandBank | G81: 2104 | J81: 354 | K81: OESTE | L81: ARIQUEMES | M81: RO | N81: RESIDENCIAL CIDADE JARDIM III | O81: Compra e Venda | P81: 1057142.9 | Q81: Loteamento | R81: Sim | S81: - | T81: - | U81: 0.7 | V81: 0.3 | W81: =SUM(U81:V81) -> 1 | X81: 0.05 | Y81: 0.09 | Z81: 0.068 | AA81: 0.198 | AC81: =AI81*AJ81 -> 593922 | AE81: =P81/10^6 -> 1.0571429 | AF81: =IF(AL81=0,0,AE81/AL81) -> 0 | AG81: =(AH81*AI81*AJ81)/10^6 -> 78.991626 | AH81: 133 | AI81: 237 | AJ81: 2506 | AK81: 0 | AL81: =(AK81*AJ81*AI81)/10^6 -> 0 | AM81: =AL81*U81 -> 0 | AN81: =AI81*AK81 -> 0 | AO81: =AH81*AI81 -> 31521 | AP81: =U81+AB81 -> 0.7 | AQ81: =AL81*AP81/(AG81+AE81) -> 0 | AR81: A lançar
A82: MAP057 | B82: RESIDENCIAL CIDADE JARDIM I - ITAPETININGA | C82: https://earth.google.com/web/search/ITAPETININGA/@-23.62618263,-48.09089394,643.86218986a,3111.8044646d,35y,0h,0t,0r/data=CiwiJgokCSTz4KZOwTbAEWUEDjqixTbAGTHHXZ3oi0bAId3jN-OskEbAQgIIAToDCgEwQgIIAEoICJfn8a8FEAA?authuser=0 | D82: 1 | E82: LandBank | G82: 2277 | J82: 240 | K82: SUDESTE | L82: ITAPETININGA | M82: SP | N82: RESIDENCIAL CIDADE JARDIM I | O82: Parceria | P82: 0 | Q82: Loteamento | R82: Sim | S82: 2028 | T82: 47117 | U82: 0.55 | V82: 0.40002 | W82: =SUM(U82:V82) -> 0.95002 | X82: 0.05 | Y82: 0.09 | Z82: 0.068 | AA82: 0.198 | AB82: 0.04998 | AC82: =AI82*AJ82 -> 218006.26 | AE82: =P82/10^6 -> 0 | AF82: =IF(AL82=0,0,AE82/AL82) -> 0 | AG82: =(AH82*AI82*AJ82)/10^6 -> 35.53502 | AH82: 163 | AI82: 227.32665 | AJ82: 959 | AK82: 550 | AL82: =(AK82*AJ82*AI82)/10^6 -> 119.90344 | AM82: =AL82*U82 -> 65.946894 | AN82: =AI82*AK82 -> 125029.66 | AO82: =AH82*AI82 -> 37054.244 | AP82: =U82+AB82 -> 0.59998 | AQ82: =AL82*AP82/(AG82+AE82) -> 2.0244724 | AR82: A lançar
A83: MAP046 | B83: JARDIM DO VALE II - COLATINA | C83: https://earth.google.com/web/search/COLATINA/@-19.52647784,-40.60231088,138.19641271a,3370.80950192d,35y,360h,0t,0r/data=CiwiJgokCW0IAtKljDbAEcH4TEmVtzbAGTR6r34gk0XAIZ1xJ4dpwkXAQgIIAToDCgEwQgIIAEoICJfn8a8FEAA?authuser=0 | D83: 1 | E83: LandBank | G83: 2284 | J83: 218 | K83: SUDESTE | L83: COLATINA | M83: ES | N83: JARDIM DO VALE II | O83: Parceria | P83: 0 | Q83: Loteamento | R83: - | S83: 2028 | T83: 46934 | U83: 0.504185 | V83: 0.45 | W83: =SUM(U83:V83) -> 0.954185 | X83: 0.05 | Y83: 0.09 | Z83: 0.068 | AA83: 0.198 | AB83: 0.045815 | AC83: =AI83*AJ83 -> 411540 | AE83: =P83/10^6 -> 0 | AF83: =IF(AL83=0,0,AE83/AL83) -> 0 | AG83: =(AH83*AI83*AJ83)/10^6 -> 69.9618 | AH83: 170 | AI83: 361 | AJ83: 1140 | AK83: 650 | AL83: =(AK83*AJ83*AI83)/10^6 -> 267.501 | AM83: =AL83*U83 -> 134.86999 | AN83: =AI83*AK83 -> 234650 | AO83: =AH83*AI83 -> 61370 | AP83: =U83+AB83 -> 0.55 | AQ83: =AL83*AP83/(AG83+AE83) -> 2.1029412 | AR83: A lançar
A84: MAP048 | B84: RESIDENCIAL CIDADE JARDIM II - DUQUE DE CAXIAS | C84: https://earth.google.com/web/search/Duque+de+Caxias,+RJ/@-22.66541941,-43.35607799,4.11315555a,678.00629462d,35y,-0h,0t,0r/data=CiwiJgokCUvDRSzvbjbAEZpP4J6LfDbAGco2nMkqO0bAIdAPxNEhSkbAQgIIAToDCgEwQgIIAEoICJfn8a8FEAA?authuser=0 | D84: 1 | E84: LandBank | G84: 2273 | J84: 222 | K84: SUDESTE | L84: DUQUE DE CAXIAS | M84: RJ | N84: RESIDENCIAL CIDADE JARDIM II | O84: Permuta | P84: 166666.66 | Q84: Loteamento | R84: Sim | S84: 2028 | T84: 46842 | U84: 0.64169 | V84: 0.3 | W84: =SUM(U84:V84) -> 0.94169 | X84: 0.05 | Y84: 0.09 | Z84: 0.068 | AA84: 0.198 | AB84: 0.05831 | AC84: =AI84*AJ84 -> 262200 | AE84: =P84/10^6 -> 0.16666666 | AF84: =IF(AL84=0,0,AE84/AL84) -> 0.00084752942 | AG84: =(AH84*AI84*AJ84)/10^6 -> 42.7386 | AH84: 163 | AI84: 230 | AJ84: 1140 | AK84: 750 | AL84: =(AK84*AJ84*AI84)/10^6 -> 196.65 | AM84: =AL84*U84 -> 126.18834 | AN84: =AI84*AK84 -> 172500 | AO84: =AH84*AI84 -> 37490 | AP84: =U84+AB84 -> 0.7 | AQ84: =AL84*AP84/(AG84+AE84) -> 3.2083474 | AR84: A lançar
A85: MAP050 | B85: A DEFINIR - DUQUE DE CAXIAS | C85: - | D85: 1 | E85: LandBank | G85: 2285 | J85: 225 | K85: SUDESTE | L85: DUQUE DE CAXIAS | M85: RJ | N85: A DEFINIR - ÁREA DO RICARDO | O85: Parceria | P85: 0 | Q85: Loteamento | R85: - | S85: 2029 | T85: 47299 | U85: 0.595855 | V85: 0.35 | W85: =SUM(U85:V85) -> 0.945855 | X85: 0.05 | Y85: 0.09 | Z85: 0.068 | AA85: 0.198 | AB85: 0.054145 | AC85: =AI85*AJ85 -> 105000 | AE85: =P85/10^6 -> 0 | AF85: =IF(AL85=0,0,AE85/AL85) -> 0 | AG85: =(AH85*AI85*AJ85)/10^6 -> 18.9 | AH85: 180 | AI85: 1000 | AJ85: 105 | AK85: 850 | AL85: =(AK85*AJ85*AI85)/10^6 -> 89.25 | AM85: =AL85*U85 -> 53.180059 | AN85: =AI85*AK85 -> 850000 | AO85: =AH85*AI85 -> 180000 | AP85: =U85+AB85 -> 0.65 | AQ85: =AL85*AP85/(AG85+AE85) -> 3.0694444 | AR85: A lançar
A86: MAP051 | B86: RESIDENCIAL CIDADE JARDIM - INDUSTRIAL - ITATIAIA | C86: https://earth.google.com/web/search/Itatiaia,+RJ/@-22.45992895,-44.52068364,423.46245411a,8948.36825161d,35y,0h,0t,0r/data=CiwiJgokCZ6WBhqISi_AEVBldJnBEzjAGf8jZD_WyULAIQ_8zVvgN0zAQgIIAToDCgEwQgIIAEoICJfn8a8FEAA?authuser=0 | D86: 1 | E86: LandBank | G86: 2278 | J86: 227 | K86: SUDESTE | L86: ITATIAIA | M86: RJ | N86: RESIDENCIAL CIDADE JARDIM - INDUSTRIAL | O86: Parceria | P86: 0 | Q86: Loteamento | R86: Sim | S86: 2028 | T86: 47026 | U86: 0.595855 | V86: 0.35 | W86: =SUM(U86:V86) -> 0.945855 | X86: 0.05 | Y86: 0.09 | Z86: 0.068 | AA86: 0.198 | AB86: 0.054145 | AC86: =AI86*AJ86 -> 91676.92 | AE86: =P86/10^6 -> 0 | AF86: =IF(AL86=0,0,AE86/AL86) -> 0 | AG86: =(AH86*AI86*AJ86)/10^6 -> 14.943338 | AH86: 163 | AI86: 2696.38 | AJ86: 34 | AK86: 1000 | AL86: =(AK86*AJ86*AI86)/10^6 -> 91.67692 | AM86: =AL86*U86 -> 54.626151 | AN86: =AI86*AK86 -> 2696380 | AO86: =AH86*AI86 -> 439509.94 | AP86: =U86+AB86 -> 0.65 | AQ86: =AL86*AP86/(AG86+AE86) -> 3.9877301 | AR86: A lançar
A87: MAP054 | B87: RESIDENCIAL CIDADE JARDIM I - MACAE | C87: https://earth.google.com/web/search/MACAE/@-22.36624118,-41.8234272,34.24557963a,6150.26313789d,35y,0h,0t,0r/data=CiwiJgokCcmdsN-e6TbAEVdlXJdI9TbAGUMWAjLoEkXAIbglujnGH0XAQgIIAToDCgEwQgIIAEoICJfn8a8FEAA?authuser=0 | D87: 1 | E87: LandBank | G87: 2287 | J87: 233 | K87: SUDESTE | L87: MACAÉ | M87: RJ | N87: RESIDENCIAL CIDADE JARDIM I | O87: Parceria | P87: 0 | Q87: Loteamento | R87: Sim | S87: 2028 | T87: 47118 | U87: 0.46669 | V87: 0.3 | W87: =SUM(U87:V87) -> 0.76669 | X87: 0.05 | Y87: 0.09 | Z87: 0.068 | AA87: 0.198 | AB87: 0.23331 | AC87: =AI87*AJ87 -> 94208 | AE87: =P87/10^6 -> 0 | AF87: =IF(AL87=0,0,AE87/AL87) -> 0 | AG87: =(AH87*AI87*AJ87)/10^6 -> 16.95744 | AH87: 180 | AI87: 256 | AJ87: 368 | AK87: 900 | AL87: =(AK87*AJ87*AI87)/10^6 -> 84.7872 | AM87: =AL87*U87 -> 39.569338 | AN87: =AI87*AK87 -> 230400 | AO87: =AH87*AI87 -> 46080 | AP87: =U87+AB87 -> 0.7 | AQ87: =AL87*AP87/(AG87+AE87) -> 3.5 | AR87: A lançar
A88: MAP054 | B88: RESIDENCIAL CIDADE JARDIM II - MACAE | C88: https://earth.google.com/web/search/MACAE/@-22.36624118,-41.8234272,34.24557963a,6150.26313789d,35y,0h,0t,0r/data=CiwiJgokCcmdsN-e6TbAEVdlXJdI9TbAGUMWAjLoEkXAIbglujnGH0XAQgIIAToDCgEwQgIIAEoICJfn8a8FEAA?authuser=0 | D88: 1 | E88: LandBank | G88: 2287 | J88: 234 | K88: SUDESTE | L88: MACAÉ | M88: RJ | N88: RESIDENCIAL CIDADE JARDIM II | O88: Parceria | P88: 0 | Q88: Loteamento | R88: - | S88: 2028 | T88: 47118 | U88: 0.46669 | V88: 0.3 | W88: =SUM(U88:V88) -> 0.76669 | X88: 0.05 | Y88: 0.09 | Z88: 0.068 | AA88: 0.198 | AB88: 0.23331 | AC88: =AI88*AJ88 -> 183738 | AE88: =P88/10^6 -> 0 | AF88: =IF(AL88=0,0,AE88/AL88) -> 0 | AG88: =(AH88*AI88*AJ88)/10^6 -> 33.07284 | AH88: 180 | AI88: 271 | AJ88: 678 | AK88: 600 | AL88: =(AK88*AJ88*AI88)/10^6 -> 110.2428 | AM88: =AL88*U88 -> 51.449212 | AN88: =AI88*AK88 -> 162600 | AO88: =AH88*AI88 -> 48780 | AP88: =U88+AB88 -> 0.7 | AQ88: =AL88*AP88/(AG88+AE88) -> 2.3333333 | AR88: A lançar
A89: MAP062 | B89: JARDIM IPIRANGA I - PRESIDENTE PRUDENTE | C89: https://earth.google.com/web/search/PRESIDENTE+PRUDENTE/@-22.07352232,-51.4013622,413.34837945a,3248.43771077d,35y,0.00000083h,0t,0r/data=CiwiJgokCQO2VLUNETfAEV-ipG2MFTfAGcVo9EuN20bAIW53qAeE4EbAQgIIAToDCgEwQgIIAEoICJfn8a8FEAA?authuser=0 | D89: 1 | E89: LandBank | G89: 2281 | J89: 255 | K89: SUDESTE | L89: PRESIDENTE PRUDENTE | M89: SP | N89: JARDIM IPIRANGA I | O89: Parceria | P89: 0 | Q89: Loteamento | R89: Sim | S89: 2028 | T89: 47026 | U89: 0.6371065 | V89: 0.305 | W89: =SUM(U89:V89) -> 0.9421065 | X89: 0.05 | Y89: 0.09 | Z89: 0.068 | AA89: 0.198 | AB89: 0.0578935 | AC89: =AI89*AJ89 -> 183688.94 | AE89: =P89/10^6 -> 0 | AF89: =IF(AL89=0,0,AE89/AL89) -> 0 | AG89: =(AH89*AI89*AJ89)/10^6 -> 29.941297 | AH89: 163 | AI89: 174.94185 | AJ89: 1050 | AK89: 550 | AL89: =(AK89*AJ89*AI89)/10^6 -> 101.02892 | AM89: =AL89*U89 -> 64.36618 | AN89: =AI89*AK89 -> 96218.016 | AO89: =AH89*AI89 -> 28515.521 | AP89: =U89+AB89 -> 0.695 | AQ89: =AL89*AP89/(AG89+AE89) -> 2.345092 | AR89: A lançar
A90: MAP063 | B90: JARDIM IPIRANGA II - PRESIDENTE PRUDENTE | C90: https://earth.google.com/web/search/PRESIDENTE+PRUDENTE/@-22.07352232,-51.4013622,413.34837945a,3248.43771077d,35y,0.00000083h,0t,0r/data=CiwiJgokCQO2VLUNETfAEV-ipG2MFTfAGcVo9EuN20bAIW53qAeE4EbAQgIIAToDCgEwQgIIAEoICJfn8a8FEAA?authuser=0 | D90: 1 | E90: LandBank | G90: 2281 | J90: 256 | K90: SUDESTE | L90: PRESIDENTE PRUDENTE | M90: SP | N90: JARDIM IPIRANGA II | O90: Parceria | P90: 0 | Q90: Loteamento | R90: - | S90: 2028 | T90: 47026 | U90: 0.6371065 | V90: 0.305 | W90: =SUM(U90:V90) -> 0.9421065 | X90: 0.05 | Y90: 0.09 | Z90: 0.068 | AA90: 0.198 | AB90: 0.0578935 | AC90: =AI90*AJ90 -> 94010 | AE90: =P90/10^6 -> 0 | AF90: =IF(AL90=0,0,AE90/AL90) -> 0 | AG90: =(AH90*AI90*AJ90)/10^6 -> 15.32363 | AH90: 163 | AI90: 170 | AJ90: 553 | AK90: 550 | AL90: =(AK90*AJ90*AI90)/10^6 -> 51.7055 | AM90: =AL90*U90 -> 32.94191 | AN90: =AI90*AK90 -> 93500 | AO90: =AH90*AI90 -> 27710 | AP90: =U90+AB90 -> 0.695 | AQ90: =AL90*AP90/(AG90+AE90) -> 2.345092 | AR90: A lançar
A91: MAP064 | B91: JARDIM NOVA AMERICA I E II - PRESIDENTE PRUDENTE | C91: https://earth.google.com/web/search/PRESIDENTE+PRUDENTE/@-22.06712728,-51.37175302,456.77615334a,2330.45847911d,35y,0h,0t,0r/data=CiwiJgokCQO2VLUNETfAEV-ipG2MFTfAGcVo9EuN20bAIW53qAeE4EbAQgIIAToDCgEwQgIIAEoICJfn8a8FEAA?authuser=0 | D91: 1 | E91: LandBank | G91: 2281 | J91: 257 | K91: SUDESTE | L91: PRESIDENTE PRUDENTE | M91: SP | N91: JARDIM NOVA AMERICA I E II | O91: Parceria | P91: 0 | Q91: Loteamento | R91: - | S91: 2028 | T91: 47026 | U91: 0.650857 | V91: 0.29 | W91: =SUM(U91:V91) -> 0.940857 | X91: 0.05 | Y91: 0.09 | Z91: 0.068 | AA91: 0.198 | AB91: 0.059143 | AC91: =AI91*AJ91 -> 101120 | AE91: =P91/10^6 -> 0 | AF91: =IF(AL91=0,0,AE91/AL91) -> 0 | AG91: =(AH91*AI91*AJ91)/10^6 -> 16.48256 | AH91: 163 | AI91: 160 | AJ91: 632 | AK91: 600 | AL91: =(AK91*AJ91*AI91)/10^6 -> 60.672 | AM91: =AL91*U91 -> 39.488796 | AN91: =AI91*AK91 -> 96000 | AO91: =AH91*AI91 -> 26080 | AP91: =U91+AB91 -> 0.71 | AQ91: =AL91*AP91/(AG91+AE91) -> 2.6134969 | AR91: A lançar
A92: MAP065 | B92: RESIDENCIAL MADRI - PRESIDENTE PRUDENTE | C92: https://earth.google.com/web/search/PRESIDENTE+PRUDENTE/@-22.14116354,-51.35308002,408.23858461a,3078.88745257d,35y,0h,0t,0r/data=CiwiJgokCQO2VLUNETfAEV-ipG2MFTfAGcVo9EuN20bAIW53qAeE4EbAQgIIAToDCgEwQgIIAEoICJfn8a8FEAA?authuser=0 | D92: 1 | E92: LandBank | G92: 2281 | J92: 258 | K92: SUDESTE | L92: PRESIDENTE PRUDENTE | M92: SP | N92: RESIDENCIAL MADRI | O92: Parceria | P92: 0 | Q92: Loteamento | R92: - | S92: 2028 | T92: 47026 | U92: 0.650857 | V92: 0.29 | W92: =SUM(U92:V92) -> 0.940857 | X92: 0.05 | Y92: 0.09 | Z92: 0.068 | AA92: 0.198 | AB92: 0.059143 | AC92: =AI92*AJ92 -> 88800 | AE92: =P92/10^6 -> 0 | AF92: =IF(AL92=0,0,AE92/AL92) -> 0 | AG92: =(AH92*AI92*AJ92)/10^6 -> 14.4744 | AH92: 163 | AI92: 160 | AJ92: 555 | AK92: 600 | AL92: =(AK92*AJ92*AI92)/10^6 -> 53.28 | AM92: =AL92*U92 -> 34.677661 | AN92: =AI92*AK92 -> 96000 | AO92: =AH92*AI92 -> 26080 | AP92: =U92+AB92 -> 0.71 | AQ92: =AL92*AP92/(AG92+AE92) -> 2.6134969 | AR92: A lançar
A93: MAP134 | B93: MIRAMONTES EMPREENDIMENTOS IMOBILIÁRIOS LTDA | D93: 1 | E93: LandBank | G93: 2727 | K93: SUDESTE | L93: UBERLÃNDIA | M93: MG | N93: CONDOMINÍO PORSCHE | O93: Parceria | P93: 0 | Q93: Condominio | R93: Sim | S93: 2028 | T93: 46856 | U93: 0.57 | V93: 0.43 | W93: =SUM(U93:V93) -> 1 | AA93: 0.198 | AC93: =AI93*AJ93 -> 144500 | AE93: =P93/10^6 -> 0 | AF93: =IF(AL93=0,0,AE93/AL93) -> 0 | AG93: =(AH93*AI93*AJ93)/10^6 -> 72.25 | AH93: 500 | AI93: 850 | AJ93: 170 | AK93: 3500 | AL93: =(AK93*AJ93*AI93)/10^6 -> 505.75 | AM93: =AL93*U93 -> 288.2775 | AN93: =AI93*AK93 -> 2975000 | AO93: =AH93*AI93 -> 425000 | AP93: =U93+AB93 -> 0.57 | AQ93: =AL93*AP93/(AG93+AE93) -> 3.99 | AR93: A lançar
A94: MAP098 | B94: 10A - RIO GRANDE - AQUARIO/IBOTY - RIO GRANDE DO SUL | C94: https://earth.google.com/web/search/RIO+GRANDE+DO+SUL/@-32.11183503,-52.18658908,5.40403187a,4423.26572132d,35y,-0h,0t,0r/data=CoABGlISTAolMHg5NTA0NzIwYzQwYjQ1ODAzOjB4YWQ5ZmIzZGJhZjlmNzNkZRnYHgdvWV09wCGQV9bsN9VJwCoRUklPIEdSQU5ERSBETyBTVUwYASABIiYKJAkw_JT_K_M9wBEf1nHWmAI-wBmH-JguXXlJwCFODtDCdYtJwEICCAE6AwoBMEICCABKCAiX5_GvBRAA?authuser=0 | D94: 1 | E94: LandBank | G94: 2383 | J94: 314 | K94: SUL | L94: RIO GRANDE | M94: RS | N94: 10A - RIO GRANDE - AQUARIO/IBOTY | O94: Parceria | P94: 0 | Q94: Loteamento | R94: - | S94: 2027 | T94: 46568 | U94: 0.648 | V94: 0.19 | W94: =SUM(U94:V94) -> 0.838 | X94: 0.07 | Y94: 0.095 | Z94: 0.068 | AA94: 0.198 | AB94: 0.162 | AC94: =AI94*AJ94 -> 166930 | AE94: =P94/10^6 -> 0 | AF94: =IF(AL94=0,0,AE94/AL94) -> 0 | AG94: =(AH94*AI94*AJ94)/10^6 -> 29.21275 | AH94: 175 | AI94: 160.04794 | AJ94: 1043 | AK94: 550 | AL94: =(AK94*AJ94*AI94)/10^6 -> 91.8115 | AM94: =AL94*U94 -> 59.493852 | AN94: =AI94*AK94 -> 88026.366 | AO94: =AH94*AI94 -> 28008.389 | AP94: =U94+AB94 -> 0.81 | AQ94: =AL94*AP94/(AG94+AE94) -> 2.5457143 | AR94: A lançar
A95: MAP074 | B95: 1A - CACHOEIRA (COMPRA 23,21HA) - CACHOEIRA DO SUL | C95: https://earth.google.com/web/search/PORTO+ALEGRE/@-30.02393013,-52.88446203,56.86896845a,3471.83898874d,35y,0h,0t,0r/data=CiwiJgokCdF8eOBcqz3AEVk4mQ0orz3AGW7M2FWxNkrAIVpN-_QgO0rAQgIIAToDCgEwQgIIAEoICJfn8a8FEAA?authuser=0 | D95: 1 | E95: LandBank | G95: 2372 | J95: 273 | K95: SUL | L95: CACHOEIRA DO SUL | M95: RS | N95: 1A - CACHOEIRA (COMPRA 23,21HA) | O95: Parceria | P95: 0 | Q95: Loteamento | R95: - | S95: 2027 | T95: 46752 | U95: 0.8 | W95: =SUM(U95:V95) -> 0.8 | AA95: 0.198 | AB95: 0.2 | AC95: =AI95*AJ95 -> 46181.9 | AE95: =P95/10^6 -> 0 | AF95: =IF(AL95=0,0,AE95/AL95) -> 0 | AG95: =(AH95*AI95*AJ95)/10^6 -> 8.0818325 | AH95: 175 | AI95: 219.91381 | AJ95: 210 | AK95: 600 | AL95: =(AK95*AJ95*AI95)/10^6 -> 27.70914 | AM95: =AL95*U95 -> 22.167312 | AN95: =AI95*AK95 -> 131948.29 | AO95: =AH95*AI95 -> 38484.917 | AP95: =U95+AB95 -> 1 | AQ95: =AL95*AP95/(AG95+AE95) -> 3.4285714 | AR95: A lançar
A96: MAP074 | B96: 1B - CACHOEIRA (COMPRA 23,21HA) - CACHOEIRA DO SUL | C96: https://earth.google.com/web/search/PORTO+ALEGRE/@-30.02393013,-52.88446203,56.86896845a,3471.83898874d,35y,0h,0t,0r/data=CiwiJgokCdF8eOBcqz3AEVk4mQ0orz3AGW7M2FWxNkrAIVpN-_QgO0rAQgIIAToDCgEwQgIIAEoICJfn8a8FEAA?authuser=0 | D96: 1 | E96: LandBank | G96: 2372 | J96: 275 | K96: SUL | L96: CACHOEIRA DO SUL | M96: RS | N96: 1B - CACHOEIRA (COMPRA 23,21HA) | O96: Parceria | P96: 0 | Q96: Loteamento | R96: - | S96: 2027 | T96: 46752 | U96: 0.8 | W96: =SUM(U96:V96) -> 0.8 | AA96: 0.198 | AB96: 0.2 | AC96: =AI96*AJ96 -> 20280 | AE96: =P96/10^6 -> 0 | AF96: =IF(AL96=0,0,AE96/AL96) -> 0 | AG96: =(AH96*AI96*AJ96)/10^6 -> 3.549 | AH96: 175 | AI96: 260 | AJ96: 78 | AK96: 600 | AL96: =(AK96*AJ96*AI96)/10^6 -> 12.168 | AM96: =AL96*U96 -> 9.7344 | AN96: =AI96*AK96 -> 156000 | AO96: =AH96*AI96 -> 45500 | AP96: =U96+AB96 -> 1 | AQ96: =AL96*AP96/(AG96+AE96) -> 3.4285714 | AR96: A lançar
A97: MAP075 | B97: 2B - GUAÍBA - GUAÍBA | C97: https://earth.google.com/web/search/PORTO+ALEGRE/@-30.15639376,-51.37950813,15.7953786a,5231.5657715d,35y,360h,0t,0r/data=CiwiJgokCdF8eOBcqz3AEVk4mQ0orz3AGW7M2FWxNkrAIVpN-_QgO0rAQgIIAToDCgEwQgIIAEoICJfn8a8FEAA?authuser=0 | D97: 1 | E97: LandBank | G97: 2377 | J97: 276 | K97: SUL | L97: GUAÍBA | M97: RS | N97: 2B - GUIAÍBA | O97: Parceria | P97: 0 | Q97: Loteamento | R97: Sim | S97: 2027 | T97: 46752 | U97: 0.56 | V97: 0.3 | W97: =SUM(U97:V97) -> 0.86 | X97: 0.07 | Y97: 0.095 | Z97: 0.068 | AA97: 0.198 | AB97: 0.14 | AC97: =AI97*AJ97 -> 249900 | AE97: =P97/10^6 -> 0 | AF97: =IF(AL97=0,0,AE97/AL97) -> 0 | AG97: =(AH97*AI97*AJ97)/10^6 -> 43.7325 | AH97: 175 | AI97: 210 | AJ97: 1190 | AK97: 650 | AL97: =(AK97*AJ97*AI97)/10^6 -> 162.435 | AM97: =AL97*U97 -> 90.9636 | AN97: =AI97*AK97 -> 136500 | AO97: =AH97*AI97 -> 36750 | AP97: =U97+AB97 -> 0.7 | AQ97: =AL97*AP97/(AG97+AE97) -> 2.6 | AR97: A lançar
A98: MAP078 | B98: 3AC - POA CIDADE NOVA /ARILDO - PORTO ALEGRE | C98: https://earth.google.com/web/search/PORTO+ALEGRE/@-30.12584024,-51.13053681,31.39242651a,5997.00691746d,35y,0h,0t,0r/data=CiwiJgokCdF8eOBcqz3AEVk4mQ0orz3AGW7M2FWxNkrAIVpN-_QgO0rAQgIIAToDCgEwQgIIAEoICJfn8a8FEAA?authuser=0 | D98: 1 | E98: LandBank | G98: 2381 | J98: 284 | K98: SUL | L98: PORTO ALEGRE | M98: RS | N98: 3AC - POA CIDADE NOVA/ ARILDO I | O98: Parceria | P98: 0 | Q98: Loteamento | R98: - | S98: 2028 | T98: 47118 | U98: 0.4341 | V98: 0.4574 | W98: =SUM(U98:V98) -> 0.8915 | X98: 0.07 | Y98: 0.06 | Z98: 0.068 | AA98: 0.198 | AB98: 0.1085 | AC98: =AI98*AJ98 -> 168000 | AE98: =P98/10^6 -> 0 | AF98: =IF(AL98=0,0,AE98/AL98) -> 0 | AG98: =(AH98*AI98*AJ98)/10^6 -> 29.4 | AH98: 175 | AI98: 200 | AJ98: 840 | AK98: 700 | AL98: =(AK98*AJ98*AI98)/10^6 -> 117.6 | AM98: =AL98*U98 -> 51.05016 | AN98: =AI98*AK98 -> 140000 | AO98: =AH98*AI98 -> 35000 | AP98: =U98+AB98 -> 0.5426 | AQ98: =AL98*AP98/(AG98+AE98) -> 2.1704 | AR98: A lançar
A99: MAP089 | B99: 6D - CX. SUL - SIVIERO / ZANANDREA - CAXIAS DO SUL | C99: https://earth.google.com/web/search/CAXIAS+DO+SUL/@-29.09930815,-51.19548586,755.21882371a,2587.3651093d,35y,0h,0t,0r/data=CnwaThJICiUweDk1MWViY2QxNjQzNWYwNzM6MHhmNTE0ZjcwN2I1NzczYmY0GVOObimMLD3AIRz3nKoxl0nAKg1DQVhJQVMgRE8gU1VMGAEgASImCiQJ1tRH0utLPcARa0Tc7klTPcAZjiIdAINaScAhKwpGrRhjScBCAggBOgMKATBCAggASggIl-fxrwUQAA?authuser=0 | D99: 1 | E99: LandBank | G99: 2374 | J99: 302 | K99: SUL | L99: CAXIAS DO SUL | M99: RS | N99: 6D - CX. SUL - SIVIERO / ZANANDREA | O99: Parceria | P99: 0 | Q99: Loteamento | R99: - | S99: 2027 | T99: 46660 | U99: 0.4 | V99: 0.5 | W99: =SUM(U99:V99) -> 0.9 | X99: 0.07 | Y99: 0.095 | Z99: 0.068 | AA99: 0.198 | AB99: 0.1 | AC99: =AI99*AJ99 -> 79997.34 | AE99: =P99/10^6 -> 0 | AF99: =IF(AL99=0,0,AE99/AL99) -> 0 | AG99: =(AH99*AI99*AJ99)/10^6 -> 13.999534 | AH99: 175 | AI99: 330.56752 | AJ99: 242 | AK99: 750 | AL99: =(AK99*AJ99*AI99)/10^6 -> 59.998005 | AM99: =AL99*U99 -> 23.999202 | AN99: =AI99*AK99 -> 247925.64 | AO99: =AH99*AI99 -> 57849.316 | AP99: =U99+AB99 -> 0.5 | AQ99: =AL99*AP99/(AG99+AE99) -> 2.1428571 | AR99: A lançar
A100: MAP095 | B100: 8C - VIAMÃO - VIANÓPOLIS - VIAMÃO | C100: https://earth.google.com/web/search/VIAM%c3%83O/@-30.06497491,-51.03875844,59.46189546a,2897.51328111d,35y,360h,0t,0r/data=CnYaSBJCCiUweDk1MTk5OGE2ZDhmMjY0NDE6MHgxNWY0MmRhYTgyYjY2ZDQwGXCFZo0wFT7AIQB4nz5dhEnAKgdWSUFNw4NPGAEgASImCiQJsTk0ZNOlP8ARLqkiuNytP8AZ9eUZULQnSsAh8JLJOEwxSsBCAggBOgMKATBCAggASggIl-fxrwUQAA?authuser=0 | D100: 1 | E100: LandBank | G100: 2389 | J100: 311 | K100: SUL | L100: VIAMÃO | M100: RS | N100: 8C - VIAMÃO - VIANÓPOLIS | O100: Parceria | P100: 0 | Q100: Loteamento | R100: - | S100: 2027 | T100: 46477 | U100: 0.624 | V100: 0.22 | W100: =SUM(U100:V100) -> 0.844 | X100: 0.07 | Y100: 0.095 | Z100: 0.068 | AA100: 0.198 | AB100: 0.156 | AC100: =AI100*AJ100 -> 114390 | AE100: =P100/10^6 -> 0 | AF100: =IF(AL100=0,0,AE100/AL100) -> 0 | AG100: =(AH100*AI100*AJ100)/10^6 -> 20.01825 | AH100: 175 | AI100: 220.40462 | AJ100: 519 | AK100: 600 | AL100: =(AK100*AJ100*AI100)/10^6 -> 68.634 | AM100: =AL100*U100 -> 42.827616 | AN100: =AI100*AK100 -> 132242.77 | AO100: =AH100*AI100 -> 38570.809 | AP100: =U100+AB100 -> 0.78 | AQ100: =AL100*AP100/(AG100+AE100) -> 2.6742857 | AR100: A lançar
...

Sheet Painel
D2: EMPREENDIMENTOS | F2: =COUNTA(AREAS!N4:N233) -> 230
D3: CIDADE | F3: =COUNTA(_xlfn.UNIQUE(AREAS!L4:L233)) -> 74
D4: ESTADOS | F4: =COUNTA(_xlfn.UNIQUE(AREAS!M4:M233)) -> 17
D5: UNIDADES (LOTES) | F5: =SUM(AREAS!AJ4:AJ233) -> 209316.38
D6: ÁREA HECTARE | F6: =G6/10000 -> 5467.7119 | G6: =SUM(AREAS!AC4:AC233) -> 54677119
D7: VGV TOTAL | F7: =SUM(AREAS!AL4:AL233) -> 36570.203
D8: VGV BT | F8: =SUM(AREAS!AM4:AM233) -> 23444.781
B10: Regional | C10: Empreendimentos | D10: Loteamento | E10: Condominio | F10: Qtde lotes | G10: Loteamento | H10: Condominio | I10: % Cond
B11: {=_xlfn._xlws.SORT(_xlfn.UNIQUE(AREAS!K4:K167))} -> CENTRO-OESTE I | C11: =COUNTIF(AREAS!K:K,Painel!B11) -> 2 | D11: =COUNTIFS(AREAS!$K:$K,Painel!$B11,AREAS!$Q:$Q,Painel!D$10) -> 2 | E11: =COUNTIFS(AREAS!$K:$K,Painel!$B11,AREAS!$Q:$Q,Painel!E$10) -> 0 | F11: =SUMIFS(AREAS!$AJ$4:$AJ$1048576,AREAS!$K$4:$K$1048576,Painel!B11) -> 1461 | G11: =SUMIFS(AREAS!$AJ$4:$AJ$167,AREAS!$K$4:$K$167,Painel!$B11,AREAS!$Q$4:$Q$167,Painel!G$10) -> 1461 | H11: =SUMIFS(AREAS!$AJ$4:$AJ$167,AREAS!$K$4:$K$167,Painel!$B11,AREAS!$Q$4:$Q$167,Painel!H$10) -> 0 | I11: =H11/F11 -> 0
B12: CENTRO-OESTE II | C12: =COUNTIF(AREAS!K:K,Painel!B12) -> 10 | D12: =COUNTIFS(AREAS!$K:$K,Painel!$B12,AREAS!$Q:$Q,Painel!D$10) -> 10 | E12: =COUNTIFS(AREAS!$K:$K,Painel!$B12,AREAS!$Q:$Q,Painel!E$10) -> 0 | F12: =SUMIFS(AREAS!$AJ$4:$AJ$1048576,AREAS!$K$4:$K$1048576,Painel!B12) -> 9416 | G12: =SUMIFS(AREAS!$AJ$4:$AJ$167,AREAS!$K$4:$K$167,Painel!$B12,AREAS!$Q$4:$Q$167,Painel!G$10) -> 8916 | H12: =SUMIFS(AREAS!$AJ$4:$AJ$167,AREAS!$K$4:$K$167,Painel!$B12,AREAS!$Q$4:$Q$167,Painel!H$10) -> 0 | I12: =H12/F12 -> 0
B13: NORDESTE I | C13: =COUNTIF(AREAS!K:K,Painel!B13) -> 7 | D13: =COUNTIFS(AREAS!$K:$K,Painel!$B13,AREAS!$Q:$Q,Painel!D$10) -> 5 | E13: =COUNTIFS(AREAS!$K:$K,Painel!$B13,AREAS!$Q:$Q,Painel!E$10) -> 2 | F13: =SUMIFS(AREAS!$AJ$4:$AJ$1048576,AREAS!$K$4:$K$1048576,Painel!B13) -> 8189.6667 | G13: =SUMIFS(AREAS!$AJ$4:$AJ$167,AREAS!$K$4:$K$167,Painel!$B13,AREAS!$Q$4:$Q$167,Painel!G$10) -> 7504.6667 | H13: =SUMIFS(AREAS!$AJ$4:$AJ$167,AREAS!$K$4:$K$167,Painel!$B13,AREAS!$Q$4:$Q$167,Painel!H$10) -> 685 | I13: =H13/F13 -> 0.083641988
B14: NORDESTE II | C14: =COUNTIF(AREAS!K:K,Painel!B14) -> 7 | D14: =COUNTIFS(AREAS!$K:$K,Painel!$B14,AREAS!$Q:$Q,Painel!D$10) -> 7 | E14: =COUNTIFS(AREAS!$K:$K,Painel!$B14,AREAS!$Q:$Q,Painel!E$10) -> 0 | F14: =SUMIFS(AREAS!$AJ$4:$AJ$1048576,AREAS!$K$4:$K$1048576,Painel!B14) -> 7420 | G14: =SUMIFS(AREAS!$AJ$4:$AJ$167,AREAS!$K$4:$K$167,Painel!$B14,AREAS!$Q$4:$Q$167,Painel!G$10) -> 7420 | H14: =SUMIFS(AREAS!$AJ$4:$AJ$167,AREAS!$K$4:$K$167,Painel!$B14,AREAS!$Q$4:$Q$167,Painel!H$10) -> 0 | I14: =H14/F14 -> 0
B15: NORTE | C15: =COUNTIF(AREAS!K:K,Painel!B15) -> 26 | D15: =COUNTIFS(AREAS!$K:$K,Painel!$B15,AREAS!$Q:$Q,Painel!D$10) -> 25 | E15: =COUNTIFS(AREAS!$K:$K,Painel!$B15,AREAS!$Q:$Q,Painel!E$10) -> 1 | F15: =SUMIFS(AREAS!$AJ$4:$AJ$1048576,AREAS!$K$4:$K$1048576,Painel!B15) -> 23843 | G15: =SUMIFS(AREAS!$AJ$4:$AJ$167,AREAS!$K$4:$K$167,Painel!$B15,AREAS!$Q$4:$Q$167,Painel!G$10) -> 22093 | H15: =SUMIFS(AREAS!$AJ$4:$AJ$167,AREAS!$K$4:$K$167,Painel!$B15,AREAS!$Q$4:$Q$167,Painel!H$10) -> 250 | I15: =H15/F15 -> 0.010485258
B16: OESTE | C16: =COUNTIF(AREAS!K:K,Painel!B16) -> 32 | D16: =COUNTIFS(AREAS!$K:$K,Painel!$B16,AREAS!$Q:$Q,Painel!D$10) -> 24 | E16: =COUNTIFS(AREAS!$K:$K,Painel!$B16,AREAS!$Q:$Q,Painel!E$10) -> 8 | F16: =SUMIFS(AREAS!$AJ$4:$AJ$1048576,AREAS!$K$4:$K$1048576,Painel!B16) -> 44711.364 | G16: =SUMIFS(AREAS!$AJ$4:$AJ$167,AREAS!$K$4:$K$167,Painel!$B16,AREAS!$Q$4:$Q$167,Painel!G$10) -> 33674.697 | H16: =SUMIFS(AREAS!$AJ$4:$AJ$167,AREAS!$K$4:$K$167,Painel!$B16,AREAS!$Q$4:$Q$167,Painel!H$10) -> 6639.6667 | I16: =H16/F16 -> 0.14850065
B17: SUDESTE | C17: =COUNTIF(AREAS!K:K,Painel!B17) -> 63 | D17: =COUNTIFS(AREAS!$K:$K,Painel!$B17,AREAS!$Q:$Q,Painel!D$10) -> 54 | E17: =COUNTIFS(AREAS!$K:$K,Painel!$B17,AREAS!$Q:$Q,Painel!E$10) -> 9 | F17: =SUMIFS(AREAS!$AJ$4:$AJ$1048576,AREAS!$K$4:$K$1048576,Painel!B17) -> 53031 | G17: =SUMIFS(AREAS!$AJ$4:$AJ$167,AREAS!$K$4:$K$167,Painel!$B17,AREAS!$Q$4:$Q$167,Painel!G$10) -> 27857 | H17: =SUMIFS(AREAS!$AJ$4:$AJ$167,AREAS!$K$4:$K$167,Painel!$B17,AREAS!$Q$4:$Q$167,Painel!H$10) -> 1460 | I17: =H17/F17 -> 0.027531067
B18: SUL | C18: =COUNTIF(AREAS!K:K,Painel!B18) -> 58 | D18: =COUNTIFS(AREAS!$K:$K,Painel!$B18,AREAS!$Q:$Q,Painel!D$10) -> 51 | E18: =COUNTIFS(AREAS!$K:$K,Painel!$B18,AREAS!$Q:$Q,Painel!E$10) -> 7 | F18: =SUMIFS(AREAS!$AJ$4:$AJ$1048576,AREAS!$K$4:$K$1048576,Painel!B18) -> 40619.667 | G18: =SUMIFS(AREAS!$AJ$4:$AJ$167,AREAS!$K$4:$K$167,Painel!$B18,AREAS!$Q$4:$Q$167,Painel!G$10) -> 19134.5 | H18: =SUMIFS(AREAS!$AJ$4:$AJ$167,AREAS!$K$4:$K$167,Painel!$B18,AREAS!$Q$4:$Q$167,Painel!H$10) -> 444 | I18: =H18/F18 -> 0.010930666
B19: TOCANTINS | C19: =COUNTIF(AREAS!K:K,Painel!B19) -> 34 | D19: =COUNTIFS(AREAS!$K:$K,Painel!$B19,AREAS!$Q:$Q,Painel!D$10) -> 29 | E19: =COUNTIFS(AREAS!$K:$K,Painel!$B19,AREAS!$Q:$Q,Painel!E$10) -> 5 | F19: =SUMIFS(AREAS!$AJ$4:$AJ$1048576,AREAS!$K$4:$K$1048576,Painel!B19) -> 24917.685 | G19: =SUMIFS(AREAS!$AJ$4:$AJ$167,AREAS!$K$4:$K$167,Painel!$B19,AREAS!$Q$4:$Q$167,Painel!G$10) -> 19544.556 | H19: =SUMIFS(AREAS!$AJ$4:$AJ$167,AREAS!$K$4:$K$167,Painel!$B19,AREAS!$Q$4:$Q$167,Painel!H$10) -> 427 | I19: =H19/F19 -> 0.017136423
B20: Total | C20: =SUM(C11:C19) -> 239 | D20: =SUM(D11:D19) -> 207 | E20: =SUM(E11:E19) -> 32 | F20: =SUM(F11:F19) -> 213609.38 | G20: =SUM(G11:G19) -> 147605.42 | H20: =SUM(H11:H19) -> 9905.6667

Sheet Excluído da base
A2: MAP034 | B2: RESIDENCIAL CIDADE JARDIM III - STP 3 - RIO LARGO | C2: https://earth.google.com/web/search/RIO+LARGO/@-9.52900304,-35.81653115,112.35298923a,4987.59724811d,35y,0.00000121h,0t,0r/data=CiwiJgokCbfopBmzfCPAEeMgyVIMhiPAGTrKKDMX6kHAIcF9G6ro7kHAQgIIAToDCgEwQgIIAEoICJfn8a8FEAA?authuser=0 | D2: 1 | E2: LandBank | G2: 2049 | J2: 199 | K2: NORDESTE I | L2: RIO LARGO | M2: AL | N2: RESIDENCIAL CIDADE JARDIM III - STP 3 | O2: Compra e Venda | P2: 1923792 | Q2: Loteamento | R2: Sim | S2: 2028 | T2: 46934 | U2: 0.8 | W2: =SUM(U2:V2) -> 0.8 | AA2: 0.198 | AB2: 0.2 | AC2: =AI2*AJ2 -> 114840 | AE2: =P2/10^6 -> 1.923792 | AF2: =IF(AL2=0,0,AE2/AL2) -> 0.035444897 | AG2: =(AH2*AI2*AJ2)/10^6 -> 13.7808 | AH2: 120 | AI2: 165 | AJ2: 696 | AK2: 472.61904 | AL2: =(AK2*AJ2*AI2)/10^6 -> 54.275571 | AM2: =AL2*U2 -> 43.420457 | AN2: 79872.618 | AO2: =AH2*AI2 -> 19800 | AP2: =U2+AB2 -> 1 | AQ2: =AL2*AP2/(AG2+AE2) -> 3.4560319 | AR2: A lançar
A3: MAP034 | B3: RESIDENCIAL CIDADE JARDIM III - STP 2 - RIO LARGO | C3: https://earth.google.com/web/search/RIO+LARGO/@-9.52900304,-35.81653115,112.35298923a,4987.59724811d,35y,0.00000121h,0t,0r/data=CiwiJgokCbfopBmzfCPAEeMgyVIMhiPAGTrKKDMX6kHAIcF9G6ro7kHAQgIIAToDCgEwQgIIAEoICJfn8a8FEAA?authuser=0 | D3: 1 | E3: LandBank | G3: 2049 | J3: 198 | K3: NORDESTE I | L3: RIO LARGO | M3: AL | N3: RESIDENCIAL CIDADE JARDIM III | O3: Compra e Venda | P3: 1923792 | Q3: Loteamento | R3: Sim | S3: 2027 | T3: 46477 | U3: 0.8 | W3: =SUM(U3:V3) -> 0.8 | AA3: 0.198 | AB3: 0.2 | AC3: =AI3*AJ3 -> 165000 | AE3: =P3/10^6 -> 1.923792 | AF3: =IF(AL3=0,0,AE3/AL3) -> 0.024669648 | AG3: =(AH3*AI3*AJ3)/10^6 -> 19.8 | AH3: 120 | AI3: 165 | AJ3: 1000 | AK3: 472.61904 | AL3: =(AK3*AJ3*AI3)/10^6 -> 77.982142 | AM3: =AL3*U3 -> 62.385714 | AN3: 79872.618 | AO3: =AH3*AI3 -> 19800 | AP3: =U3+AB3 -> 1 | AQ3: =AL3*AP3/(AG3+AE3) -> 3.5897113 | AR3: A lançar
A4: MAP037 | B4: RESIDENCIAL JARDIM EUROPA - BARRA DOS COQUEIROS | C4: https://earth.google.com/web/search/BARRA+DOS+COQUEIROS/@-10.86709266,-36.98473154,9.11625276a,6838.59037115d,35y,0h,0t,0r/data=CiwiJgokCez0LUwI4RzAEc6AbPlB_xzAGXUWKXAsqkPAIYL6q2XpsUPAQgIIAToDCgEwQgIIAEoICJfn8a8FEAA?authuser=0 | D4: 1 | E4: LandBank | G4: 2046 | J4: 203 | K4: NORDESTE I | L4: BARRA DOS COQUEIROS | M4: SE | N4: RESIDENCIAL JARDIM EUROPA | O4: Compra e Venda | P4: 4000000 | Q4: Loteamento | R4: - | S4: 2028 | T4: 46934 | U4: 0.8 | W4: =SUM(U4:V4) -> 0.8 | AA4: 0.198 | AB4: 0.2 | AC4: =AI4*AJ4 -> 204159.05 | AE4: =P4/10^6 -> 4 | AF4: =IF(AL4=0,0,AE4/AL4) -> 0.045564111 | AG4: =(AH4*AI4*AJ4)/10^6 -> 24.499086 | AH4: 120 | AI4: 216.49952 | AJ4: 943 | AK4: 430 | AL4: =(AK4*AJ4*AI4)/10^6 -> 87.788391 | AM4: =AL4*U4 -> 70.230713 | AN4: 93094.795 | AO4: =AH4*AI4 -> 25979.943 | AP4: =U4+AB4 -> 1 | AQ4: =AL4*AP4/(AG4+AE4) -> 3.0803932 | AR4: A lançar
A5: MAP106 | B5: RESIDENCIAL CIDADE JARDIM II - STP 2 - RIO BRANCO | C5: https://earth.google.com/web/search/RIO+BRANCO/@-9.9098996,-67.78102104,162.15508008a,8113.58158257d,35y,360h,0t,0r/data=CnkaSxJFCiUweDkxN2Y3YmI2OGFjYzk2ZjM6MHg4YWI4OGYxZDdmMWQ5YjNjGbb6RWSz8iPAIUaLfRPU81DAKgpSSU8gQlJBTkNPGAEgASImCiQJfzD99xEWMMAR4w_EqB0hMMAZ8L7dRwvPTMAhtzjkj7naTMBCAggBOgMKATBCAggASggIl-fxrwUQAA?authuser=0 | D5: 1 | E5: LandBank | G5: 2106 | J5: 327 | K5: OESTE | L5: RIO BRANCO | M5: AC | N5: RESIDENCIAL CIDADE JARDIM II - STP 2 | O5: Compra e Venda | P5: 1436252.3 | Q5: Loteamento | R5: Sim | S5: 2027 | T5: 46568 | U5: 0.7 | V5: 0.3 | W5: =SUM(U5:V5) -> 1 | X5: 0.05 | Y5: 0.09 | Z5: 0.068 | AA5: 0.198 | AC5: =AI5*AJ5 -> 248211 | AE5: =P5/10^6 -> 1.4362523 | AF5: =IF(AL5=0,0,AE5/AL5) -> 0.011572834 | AG5: =(AH5*AI5*AJ5)/10^6 -> 39.71376 | AH5: 160 | AI5: 261 | AJ5: 951 | AK5: 500 | AL5: =(AK5*AJ5*AI5)/10^6 -> 124.1055 | AM5: =AL5*U5 -> 86.87385 | AN5: 110000 | AO5: =AH5*AI5 -> 41760 | AP5: =U5+AB5 -> 0.7 | AQ5: =AL5*AP5/(AG5+AE5) -> 2.11115 | AR5: A lançar
A6: MAP108 | B6: RESIDENCIAL CIDADE JARDIM I - STP2 - CÁCERES | C6: https://earth.google.com/web/search/C%c3%81CERES/@-16.11433068,-57.66517767,145.36941085a,5953.03993857d,35y,-0h,0t,0r/data=CiwiJgokCQX_JH53NS3AETlJC9e-RS3AGdinZMrzwEzAIeq1E4h_yUzAQgIIAToDCgEwQgIIAEoICJfn8a8FEAA?authuser=0 | D6: 1 | E6: LandBank | G6: 1865 | J6: 337 | K6: OESTE | L6: CÁCERES | M6: MT | N6: RESIDENCIAL CIDADE JARDIM I - STP2 | O6: Parceria | P6: 0 | Q6: Loteamento | R6: Sim | S6: 2026 | T6: 46295 | U6: 0.81 | V6: 0.19 | W6: =SUM(U6:V6) -> 1 | X6: 0.05 | Y6: 0 | Z6: 0.068 | AA6: 0.198 | AC6: 169349 | AE6: =P6/10^6 -> 0 | AF6: =IF(AL6=0,0,AE6/AL6) -> 0 | AG6: =(AH6*AI6*AJ6)/10^6 -> 22.567972 | AH6: 133 | AI6: 236 | AJ6: 719 | AK6: 450 | AL6: =(AK6*AJ6*AI6)/10^6 -> 76.3578 | AM6: =AL6*U6 -> 61.849818 | AN6: 90000 | AO6: =AH6*AI6 -> 31388 | AP6: =U6+AB6 -> 0.81 | AQ6: =AL6*AP6/(AG6+AE6) -> 2.7406015 | AR6: A lançar
A7: MAP126 | B7: RESIDENCIAL PARQUE JARDIM | D7: 1 | E7: LandBank | G7: 2588 | K7: OESTE | L7: TANGARÁ DA SERRA | M7: MT | N7: RESIDENCIAL PARQUE JARDIM | O7: Compra e Venda | P7: 10682.93 | Q7: Loteamento | R7: - | S7: 2027 | T7: - | U7: 0.7 | V7: 0.3 | W7: =SUM(U7:V7) -> 1 | AA7: 0.198 | AC7: 998700 | AE7: =P7/10^6 -> 0.01068293 | AF7: =IF(AL7=0,0,AE7/AL7) -> 4.760664e-05 | AG7: =(AH7*AI7*AJ7)/10^6 -> 74.613 | AH7: 133 | AI7: 250 | AJ7: 2244 | AK7: 400 | AL7: =(AK7*AJ7*AI7)/10^6 -> 224.4 | AM7: =AL7*U7 -> 157.08 | AN7: =AI7*AK7 -> 100000 | AO7: =AH7*AI7 -> 33250 | AP7: =U7+AB7 -> 0.7 | AQ7: =AL7*AP7/(AG7+AE7) -> 2.1049618 | AR7: A lançar
A8: MAP111 | B8: RESIDENCIAL CIDADE JARDIM I - STP2 - TANGARÁ DA SERRA | C8: https://earth.google.com/web/search/TANGAR%c3%81+DA+SERRA/@-14.62032689,-57.54082084,346.92096178a,5258.20888551d,35y,0h,0t,0r/data=CiwiJgokCXA9rQptMS_AEXKWStZFPy_AGehdnQKoD0zAIeamtZ71FkzAQgIIAToDCgEwQgIIAEoICJfn8a8FEAA?authuser=0 | D8: 1 | E8: LandBank | G8: 2107 | J8: 341 | K8: OESTE | L8: TANGARÁ DA SERRA | M8: MT | N8: RESIDENCIAL CIDADE JARDIM I - STP2 | O8: Compra e Venda | P8: 10682.93 | Q8: Loteamento | R8: Sim | S8: 2029 | T8: 47483 | U8: 0.7 | V8: 0.3 | W8: =SUM(U8:V8) -> 1 | X8: 0.05 | Y8: 0.09 | Z8: 0.068 | AA8: 0.198 | AC8: =AI8*AJ8 -> 279716.51 | AE8: =P8/10^6 -> 0.01068293 | AF8: =IF(AL8=0,0,AE8/AL8) -> 7.6383979e-05 | AG8: =(AH8*AI8*AJ8)/10^6 -> 37.202296 | AH8: 133 | AI8: 324.1211 | AJ8: 863 | AK8: 500 | AL8: =(AK8*AJ8*AI8)/10^6 -> 139.85825 | AM8: =AL8*U8 -> 97.900778 | AN8: =AI8*AK8 -> 162060.55 | AO8: =AH8*AI8 -> 43108.106 | AP8: =U8+AB8 -> 0.7 | AQ8: =AL8*AP8/(AG8+AE8) -> 2.6308235 | AR8: A lançar
A9: MAP058 | B9: RESIDENCIAL CIDADE JARDIM II - ITAPETININGA | C9: https://earth.google.com/web/search/ITAPETININGA/@-23.62618263,-48.09089394,643.86218986a,3111.8044646d,35y,0h,0t,0r/data=CiwiJgokCSTz4KZOwTbAEWUEDjqixTbAGTHHXZ3oi0bAId3jN-OskEbAQgIIAToDCgEwQgIIAEoICJfn8a8FEAA?authuser=0 | D9: 1 | E9: LandBank | G9: 2277 | J9: 241 | K9: SUDESTE | L9: ITAPETININGA | M9: SP | N9: RESIDENCIAL CIDADE JARDIM II | O9: Parceria | P9: 0 | Q9: Loteamento | R9: Sim | S9: 2029 | T9: 47482 | U9: 0.55 | V9: 0.40002 | W9: =SUM(U9:V9) -> 0.95002 | X9: 0.05 | Y9: 0.09 | Z9: 0.068 | AA9: 0.198 | AB9: 0.04998 | AC9: =AI9*AJ9 -> 268822.81 | AE9: =P9/10^6 -> 0 | AF9: =IF(AL9=0,0,AE9/AL9) -> 0 | AG9: =(AH9*AI9*AJ9)/10^6 -> 43.818118 | AH9: 163 | AI9: 218.73296 | AJ9: 1229 | AK9: 550 | AL9: =(AK9*AJ9*AI9)/10^6 -> 147.85255 | AM9: =AL9*U9 -> 81.3189 | AN9: =AI9*AK9 -> 120303.13 | AO9: =AH9*AI9 -> 35653.473 | AP9: =U9+AB9 -> 0.59998 | AQ9: =AL9*AP9/(AG9+AE9) -> 2.0244724 | AR9: A lançar
A10: MAP043 | B10: RESIDENCIAL CIDADE JARDIM II - MONTES CLAROS | C10: https://earth.google.com/web/search/MONTES+CLAROS/@-16.78340211,-43.85914746,708.18079241a,4857.74891966d,35y,0h,0t,0r/data=CiwiJgokCaYkZ-ZvtTPAEWpwuK9tuzPAGWYZIm4r8UfAIR546sKi90fAQgIIAToDCgEwQgIIAEoICJfn8a8FEAA?authuser=0 | D10: 1 | E10: LandBank | G10: 2288 | J10: 214 | K10: SUDESTE | L10: MONTES CLAROS | M10: MG | N10: RESIDENCIAL CIDADE JARDIM II | O10: Parceria | P10: 0 | Q10: Loteamento | R10: - | S10: 2029 | T10: 47391 | U10: 0.45835 | V10: 0.5 | W10: =SUM(U10:V10) -> 0.95835 | X10: 0.05 | Y10: 0 | Z10: 0.068 | AA10: 0.198 | AB10: 0.04165 | AC10: =AI10*AJ10 -> 232564 | AE10: =P10/10^6 -> 0 | AF10: =IF(AL10=0,0,AE10/AL10) -> 0 | AG10: =(AH10*AI10*AJ10)/10^6 -> 37.907932 | AH10: 163 | AI10: 212 | AJ10: 1097 | AK10: 550 | AL10: =(AK10*AJ10*AI10)/10^6 -> 127.9102 | AM10: =AL10*U10 -> 58.62764 | AN10: =AI10*AK10 -> 116600 | AO10: =AH10*AI10 -> 34556 | AP10: =U10+AB10 -> 0.5 | AQ10: =AL10*AP10/(AG10+AE10) -> 1.6871166 | AR10: A lançar
A11: MAP051 | B11: RESIDENCIAL CIDADE JARDIM - ITATIAIA | C11: https://earth.google.com/web/search/Itatiaia,+RJ/@-22.45992895,-44.52068364,423.46245411a,8948.36825161d,35y,0h,0t,0r/data=CiwiJgokCZ6WBhqISi_AEVBldJnBEzjAGf8jZD_WyULAIQ_8zVvgN0zAQgIIAToDCgEwQgIIAEoICJfn8a8FEAA?authuser=0 | D11: 1 | E11: LandBank | G11: 2278 | J11: 226 | K11: SUDESTE | L11: ITATIAIA | M11: RJ | N11: RESIDENCIAL CIDADE JARDIM | O11: Parceria | P11: 0 | Q11: Loteamento | R11: Sim | S11: 2029 | T11: 47483 | U11: 0.595855 | V11: 0.35 | W11: =SUM(U11:V11) -> 0.945855 | X11: 0.05 | Y11: 0.09 | Z11: 0.068 | AA11: 0.198 | AB11: 0.054145 | AC11: =AI11*AJ11 -> 202308 | AE11: =P11/10^6 -> 0 | AF11: =IF(AL11=0,0,AE11/AL11) -> 0 | AG11: =(AH11*AI11*AJ11)/10^6 -> 32.976204 | AH11: 163 | AI11: 276 | AJ11: 733 | AK11: 715 | AL11: =(AK11*AJ11*AI11)/10^6 -> 144.65022 | AM11: =AL11*U11 -> 86.190557 | AN11: =AI11*AK11 -> 197340 | AO11: =AH11*AI11 -> 44988 | AP11: =U11+AB11 -> 0.65 | AQ11: =AL11*AP11/(AG11+AE11) -> 2.851227 | AR11: A lançar
A12: MAP046 | B12: JARDIM DO VALE III - COLATINA | C12: https://earth.google.com/web/search/COLATINA/@-19.52647784,-40.60231088,138.19641271a,3370.80950192d,35y,360h,0t,0r/data=CiwiJgokCW0IAtKljDbAEcH4TEmVtzbAGTR6r34gk0XAIZ1xJ4dpwkXAQgIIAToDCgEwQgIIAEoICJfn8a8FEAA?authuser=0 | D12: 1 | E12: LandBank | G12: 2284 | J12: 219 | K12: SUDESTE | L12: COLATINA | M12: ES | N12: JARDIM DO VALE III | O12: Parceria | P12: 0 | Q12: Loteamento | R12: - | S12: 2029 | T12: 47299 | U12: 0.504185 | V12: 0.45 | W12: =SUM(U12:V12) -> 0.954185 | X12: 0.05 | Y12: 0.09 | Z12: 0.068 | AA12: 0.198 | AB12: 0.045815 | AC12: =AI12*AJ12 -> 411540 | AE12: =P12/10^6 -> 0 | AF12: =IF(AL12=0,0,AE12/AL12) -> 0 | AG12: =(AH12*AI12*AJ12)/10^6 -> 69.9618 | AH12: 170 | AI12: 361 | AJ12: 1140 | AK12: 650 | AL12: =(AK12*AJ12*AI12)/10^6 -> 267.501 | AM12: =AL12*U12 -> 134.86999 | AN12: =AI12*AK12 -> 234650 | AO12: =AH12*AI12 -> 61370 | AP12: =U12+AB12 -> 0.55 | AQ12: =AL12*AP12/(AG12+AE12) -> 2.1029412 | AR12: A lançar
A13: MAP048 | B13: RESIDENCIAL CIDADE JARDIM III - DUQUE DE CAXIAS | C13: - | D13: 1 | E13: LandBank | G13: 2273 | J13: 223 | K13: SUDESTE | L13: DUQUE DE CAXIAS | M13: RJ | N13: RESIDENCIAL CIDADE JARDIM III | O13: Permuta | P13: 166667 | Q13: Loteamento | R13: - | S13: 2029 | T13: 47207 | U13: 0.64169 | V13: 0.3 | W13: =SUM(U13:V13) -> 0.94169 | X13: 0.05 | Y13: 0.09 | Z13: 0.068 | AA13: 0.198 | AB13: 0.05831 | AC13: =AI13*AJ13 -> 262200 | AE13: =P13/10^6 -> 0.166667 | AF13: =IF(AL13=0,0,AE13/AL13) -> 0.00079456045 | AG13: =(AH13*AI13*AJ13)/10^6 -> 42.7386 | AH13: 163 | AI13: 230 | AJ13: 1140 | AK13: 800 | AL13: =(AK13*AJ13*AI13)/10^6 -> 209.76 | AM13: =AL13*U13 -> 134.60089 | AN13: =AI13*AK13 -> 184000 | AO13: =AH13*AI13 -> 37490 | AP13: =U13+AB13 -> 0.7 | AQ13: =AL13*AP13/(AG13+AE13) -> 3.4222372 | AR13: A lançar
A14: MAP051 | B14: RESIDENCIAL CIDADE JARDIM II - ITATIAIA | C14: https://earth.google.com/web/search/Itatiaia,+RJ/@-22.45992895,-44.52068364,423.46245411a,8948.36825161d,35y,0h,0t,0r/data=CiwiJgokCZ6WBhqISi_AEVBldJnBEzjAGf8jZD_WyULAIQ_8zVvgN0zAQgIIAToDCgEwQgIIAEoICJfn8a8FEAA?authuser=0 | D14: 1 | E14: LandBank | G14: 2278 | J14: 228 | K14: SUDESTE | L14: ITATIAIA | M14: RJ | N14: RESIDENCIAL CIDADE JARDIM II | O14: Parceria | P14: 0 | Q14: Loteamento | R14: - | S14: 2029 | T14: 47483 | U14: 0.595855 | V14: 0.35 | W14: =SUM(U14:V14) -> 0.945855 | X14: 0.05 | Y14: 0.09 | Z14: 0.068 | AA14: 0.198 | AB14: 0.054145 | AC14: =AI14*AJ14 -> 220800 | AE14: =P14/10^6 -> 0 | AF14: =IF(AL14=0,0,AE14/AL14) -> 0 | AG14: =(AH14*AI14*AJ14)/10^6 -> 35.9904 | AH14: 163 | AI14: 276 | AJ14: 800 | AK14: 650 | AL14: =(AK14*AJ14*AI14)/10^6 -> 143.52 | AM14: =AL14*U14 -> 85.51711 | AN14: =AI14*AK14 -> 179400 | AO14: =AH14*AI14 -> 44988 | AP14: =U14+AB14 -> 0.65 | AQ14: =AL14*AP14/(AG14+AE14) -> 2.5920245 | AR14: A lançar
A15: MAP053 | B15: A DENIFIR - ITABORAÍ | C15: https://earth.google.com/web/search/ITABORA%c3%8d/@-22.7705662,-42.90251485,16.01615323a,2212.94452737d,35y,0h,0t,0r/data=CiwiJgokCWeuUiREWTbAEf3J2D8_YjbAGShqrBV35ETAIYuIHwFV7kTAQgIIAToDCgEwQgIIAEoICJfn8a8FEAA?authuser=0 | D15: 1 | E15: LandBank | G15: 2276 | J15: 232 | K15: SUDESTE | L15: ITABORAÍ | M15: RJ | N15: A DEFINIR | O15: Compra e Venda | P15: 6273440.6 | Q15: Loteamento | R15: - | S15: 2029 | T15: 47391 | U15: 0.573362 | V15: 0.14 | W15: =SUM(U15:V15) -> 0.713362 | X15: 0.05 | Y15: 0 | Z15: 0.068 | AA15: 0.198 | AB15: 0.286638 | AC15: =AI15*AJ15 -> 95400 | AE15: =P15/10^6 -> 6.2734406 | AF15: =IF(AL15=0,0,AE15/AL15) -> 0.10959889 | AG15: =(AH15*AI15*AJ15)/10^6 -> 15.5502 | AH15: 163 | AI15: 180 | AJ15: 530 | AK15: 600 | AL15: =(AK15*AJ15*AI15)/10^6 -> 57.24 | AM15: =AL15*U15 -> 32.819241 | AN15: =AI15*AK15 -> 108000 | AO15: =AH15*AI15 -> 29340 | AP15: =U15+AB15 -> 0.86 | AQ15: =AL15*AP15/(AG15+AE15) -> 2.2556457 | AR15: A lançar
A16: MAP054 | B16: RESIDENCIAL CIDADE JARDIM III - MACAE | C16: https://earth.google.com/web/search/MACAE/@-22.36624118,-41.8234272,34.24557963a,6150.26313789d,35y,0h,0t,0r/data=CiwiJgokCcmdsN-e6TbAEVdlXJdI9TbAGUMWAjLoEkXAIbglujnGH0XAQgIIAToDCgEwQgIIAEoICJfn8a8FEAA?authuser=0 | D16: 1 | E16: LandBank | G16: 2287 | J16: 235 | K16: SUDESTE | L16: MACAE | M16: RJ | N16: RESIDENCIAL CIDADE JARDIM III | O16: Parceria | P16: 0 | Q16: Loteamento | R16: - | S16: 2029 | T16: 47483 | U16: 0.46669 | V16: 0.3 | W16: =SUM(U16:V16) -> 0.76669 | X16: 0.05 | Y16: 0.09 | Z16: 0.068 | AA16: 0.198 | AB16: 0.23331 | AC16: 171270.39 | AE16: =P16/10^6 -> 0 | AF16: =IF(AL16=0,0,AE16/AL16) -> 0 | AG16: =(AH16*AI16*AJ16)/10^6 -> 30.82752 | AH16: 180 | AI16: 256 | AJ16: 669 | AK16: 950 | AL16: =(AK16*AJ16*AI16)/10^6 -> 162.7008 | AM16: =AL16*U16 -> 75.930836 | AN16: =AI16*AK16 -> 243200 | AO16: =AH16*AI16 -> 46080 | AP16: =U16+AB16 -> 0.7 | AQ16: =AL16*AP16/(AG16+AE16) -> 3.6944444 | AR16: A lançar
A17: MAP056 | B17: A DEFINIR I - ARRAIAL DO CABO | C17: https://earth.google.com/web/search/ARRAIAL+DO+CABO/@-22.93536918,-42.19797612,2.57990512a,8028.28875861d,35y,0h,0t,0r/data=CnwaThJICiMweDk3MTk3YmEwMTFkM2E5OjB4M2M0YTJiN2IxNGUwMDMwORnXiSarffc2wCH54BAFjgNFwCoPQVJSQUlBTCBETyBDQUJPGAEgASImCiQJ3jIbZ5OdN8AR8LcycgejN8AZIoh5YJwISMAhtPiWdKgOSMBCAggBOgMKATBCAggASggIl-fxrwUQAA?authuser=0 | D17: 1 | E17: LandBank | G17: 2269 | J17: 238 | K17: SUDESTE | L17: ARRAIAL DO CABO | M17: RJ | N17: A DEFINIR | O17: Parceria | P17: 0 | Q17: Loteamento | R17: Sim | S17: 2029 | T17: 47299 | U17: 0.6875 | V17: 0.25 | W17: =SUM(U17:V17) -> 0.9375 | X17: 0.05 | Y17: 0 | Z17: 0.068 | AA17: 0.198 | AB17: 0.0625 | AC17: =AI17*AJ17 -> 241875 | AE17: =P17/10^6 -> 0 | AF17: =IF(AL17=0,0,AE17/AL17) -> 0 | AG17: =(AH17*AI17*AJ17)/10^6 -> 39.425625 | AH17: 163 | AI17: 250.12927 | AJ17: 967 | AK17: 800 | AL17: =(AK17*AJ17*AI17)/10^6 -> 193.5 | AM17: =AL17*U17 -> 133.03125 | AN17: =AI17*AK17 -> 200103.41 | AO17: =AH17*AI17 -> 40771.07 | AP17: =U17+AB17 -> 0.75 | AQ17: =AL17*AP17/(AG17+AE17) -> 3.6809816 | AR17: A lançar
A18: MAP055 | B18: A DEFINIR I - MACAE | C18: https://earth.google.com/web/search/MACAE/@-22.36624118,-41.8234272,34.24557963a,6150.26313789d,35y,0h,0t,0r/data=CiwiJgokCcmdsN-e6TbAEVdlXJdI9TbAGUMWAjLoEkXAIbglujnGH0XAQgIIAToDCgEwQgIIAEoICJfn8a8FEAA?authuser=0 | D18: 1 | E18: Estudo de viabilidade | G18: 2642 | J18: 236 | K18: SUDESTE | L18: MACAE | M18: RJ | N18: A DEFINIR | O18: Parceria | P18: 0 | Q18: Loteamento | R18: - | S18: 2029 | T18: 47483 | U18: 0.595855 | V18: 0.35 | W18: =SUM(U18:V18) -> 0.945855 | X18: 0.05 | Y18: 0.09 | Z18: 0.068 | AA18: 0.198 | AB18: 0.054145 | AC18: =AI18*AJ18 -> 183738 | AE18: =P18/10^6 -> 0 | AF18: =IF(AL18=0,0,AE18/AL18) -> 0 | AG18: =(AH18*AI18*AJ18)/10^6 -> 29.949294 | AH18: 163 | AI18: 271 | AJ18: 678 | AK18: 600 | AL18: =(AK18*AJ18*AI18)/10^6 -> 110.2428 | AM18: =AL18*U18 -> 65.688724 | AN18: =AI18*AK18 -> 162600 | AO18: =AH18*AI18 -> 44173 | AP18: =U18+AB18 -> 0.65 | AQ18: =AL18*AP18/(AG18+AE18) -> 2.392638 | AR18: A lançar
A19: MAP055 | B19: A DEFINIR II - MACAE | C19: https://earth.google.com/web/search/MACAE/@-22.36624118,-41.8234272,34.24557963a,6150.26313789d,35y,0h,0t,0r/data=CiwiJgokCcmdsN-e6TbAEVdlXJdI9TbAGUMWAjLoEkXAIbglujnGH0XAQgIIAToDCgEwQgIIAEoICJfn8a8FEAA?authuser=0 | D19: 1 | E19: Estudo de viabilidade | G19: 2642 | J19: 237 | K19: SUDESTE | L19: MACAE | M19: RJ | N19: A DEFINIR | O19: Parceria | P19: 0 | Q19: Loteamento | R19: - | S19: 2029 | T19: 47483 | U19: 0.595855 | V19: 0.35 | W19: =SUM(U19:V19) -> 0.945855 | X19: 0.05 | Y19: 0.09 | Z19: 0.068 | AA19: 0.198 | AB19: 0.054145 | AC19: =AI19*AJ19 -> 260596 | AE19: =P19/10^6 -> 0 | AF19: =IF(AL19=0,0,AE19/AL19) -> 0 | AG19: =(AH19*AI19*AJ19)/10^6 -> 42.477148 | AH19: 163 | AI19: 227 | AJ19: 1148 | AK19: 650 | AL19: =(AK19*AJ19*AI19)/10^6 -> 169.3874 | AM19: =AL19*U19 -> 100.93033 | AN19: =AI19*AK19 -> 147550 | AO19: =AH19*AI19 -> 37001 | AP19: =U19+AB19 -> 0.65 | AQ19: =AL19*AP19/(AG19+AE19) -> 2.5920245 | AR19: A lançar
A20: MAP061 | B20: RESIDENCIAL CIDADE JARDIM II - LORENA | C20: https://earth.google.com/web/search/LORENA/@-22.76355759,-45.11165622,554.79907101a,2424.9160967d,35y,0h,0t,0r/data=CiwiJgokCdDYYcMpEDbAEb-si-d6FTbAGdP8OMJ1sEnAIeq0yPtJtknAQgIIAToDCgEwQgIIAEoICJfn8a8FEAA?authuser=0 | D20: 1 | E20: LandBank | G20: 2286 | J20: 250 | K20: SUDESTE | L20: LORENA | M20: SP | N20: RESIDENCIAL CIDADE JARDIM II | O20: Parceria | P20: 0 | Q20: Loteamento | R20: - | S20: 2029 | T20: 47299 | U20: 0.45 | V20: 0.5 | W20: =SUM(U20:V20) -> 0.95 | X20: 0.05 | Y20: 0.09 | Z20: 0.068 | AA20: 0.198 | AB20: 0.05 | AC20: =AI20*AJ20 -> 308574.72 | AE20: =P20/10^6 -> 0 | AF20: =IF(AL20=0,0,AE20/AL20) -> 0 | AG20: =(AH20*AI20*AJ20)/10^6 -> 50.29768 | AH20: 163 | AI20: 299.00651 | AJ20: 1032 | AK20: 550 | AL20: =(AK20*AJ20*AI20)/10^6 -> 169.7161 | AM20: =AL20*U20 -> 76.372244 | AN20: =AI20*AK20 -> 164453.58 | AO20: =AH20*AI20 -> 48738.062 | AP20: =U20+AB20 -> 0.5 | AQ20: =AL20*AP20/(AG20+AE20) -> 1.6871166 | AR20: A lançar
A21: MAP066 | B21: ROBERTO NEGRAO I - PRESIDENTE PRUDENTE | C21: https://earth.google.com/web/search/PRESIDENTE+PRUDENTE/@-22.14871306,-51.33335737,421.19686992a,3065.92913489d,35y,0h,0t,0r/data=CiwiJgokCQO2VLUNETfAEV-ipG2MFTfAGcVo9EuN20bAIW53qAeE4EbAQgIIAToDCgEwQgIIAEoICJfn8a8FEAA?authuser=0 | D21: 1 | E21: LandBank | G21: 2281 | J21: 259 | K21: SUDESTE | L21: PRESIDENTE PRUDENTE | M21: SP | N21: ROBERTO NEGRAO I | O21: Parceria | P21: 0 | Q21: Loteamento | R21: - | S21: 2029 | T21: 47391 | U21: 0.650857 | V21: 0.29 | W21: =SUM(U21:V21) -> 0.940857 | X21: 0.05 | Y21: 0.09 | Z21: 0.068 | AA21: 0.198 | AB21: 0.059143 | AC21: =AI21*AJ21 -> 142117.4 | AE21: =P21/10^6 -> 0 | AF21: =IF(AL21=0,0,AE21/AL21) -> 0 | AG21: =(AH21*AI21*AJ21)/10^6 -> 23.165136 | AH21: 163 | AI21: 159.86209 | AJ21: 889 | AK21: 550 | AL21: =(AK21*AJ21*AI21)/10^6 -> 78.16457 | AM21: =AL21*U21 -> 50.873958 | AN21: =AI21*AK21 -> 87924.151 | AO21: =AH21*AI21 -> 26057.521 | AP21: =U21+AB21 -> 0.71 | AQ21: =AL21*AP21/(AG21+AE21) -> 2.3957055 | AR21: A lançar
A22: MAP137 | B22: RESIDENCIAL SÃO FRANCISCO DE AVARÉ II - AVARÉ | C22: https://earth.google.com/web/search/Avar%c3%a9,+SP/@-23.13817295,-48.93466362,759.5009067a,2026.71010604d,35y,0h,0t,0r/data=CiwiJgokCbdqOrTERTTAEdFka3GySTTAGdvcUdEVIUnAIfMq4hhXJUnAQgIIAToDCgEwQgIIAEoICJfn8a8FEAA?authuser=0 | D22: 1 | E22: LandBank | G22: 2270 | J22: 263 | K22: SUDESTE | L22: AVARÉ | M22: SP | N22: RESIDENCIAL SÃO FRANCISCO DE AVARÉ II | O22: Parceria | P22: 0 | Q22: Loteamento | R22: - | S22: 2029 | T22: 46660 | U22: 0.6417 | V22: 0.3 | W22: =SUM(U22:V22) -> 0.9417 | X22: 0.05 | Y22: 0.09 | Z22: 0.068 | AA22: 0.198 | AB22: 0.0583 | AC22: 225552.72 | AE22: =P22/10^6 -> 0 | AF22: =IF(AL22=0,0,AE22/AL22) -> 0 | AG22: =(AH22*AI22*AJ22)/10^6 -> 32.2088 | AH22: 163 | AI22: 200 | AJ22: 988 | AK22: 600 | AL22: =(AK22*AJ22*AI22)/10^6 -> 118.56 | AM22: =AL22*U22 -> 76.079952 | AN22: =AI22*AK22 -> 120000 | AO22: =AH22*AI22 -> 32600 | AP22: =U22+AB22 -> 0.7 | AQ22: =AL22*AP22/(AG22+AE22) -> 2.5766871 | AR22: A lançar
A23: MAP073 | B23: A DEFINIR - CABO FRIO | C23: https://earth.google.com/web/search/CABO+FRIO/@-22.8250059,-42.03103576,12.7124684a,2857.57864826d,35y,0h,0t,0r/data=CiwiJgokCVC2q1CQAz7AERjRb_uvCD7AGY9__Xk0bkrAIVnsd6A3dErAQgIIAToDCgEwQgIIAEoICJfn8a8FEAA?authuser=0 | D23: 1 | E23: Estudo de viabilidade | G23: 2395 | J23: 269 | K23: SUDESTE | L23: CABO FRIO | M23: RJ | N23: A DEFINIR | O23: Parceria | P23: 0 | Q23: Loteamento | R23: - | S23: 2029 | T23: 47391 | U23: 0.7 | V23: 0.3 | W23: =SUM(U23:V23) -> 1 | X23: 0.05 | Y23: 0 | Z23: 0.068 | AA23: 0.198 | AC23: 325041 | AE23: =P23/10^6 -> 0 | AF23: =IF(AL23=0,0,AE23/AL23) -> 0 | AG23: =(AH23*AI23*AJ23)/10^6 -> 26.3408 | AH23: 163 | AI23: 200 | AJ23: 808 | AK23: 800 | AL23: =(AK23*AJ23*AI23)/10^6 -> 129.28 | AM23: =AL23*U23 -> 90.496 | AN23: =AI23*AK23 -> 160000 | AO23: =AH23*AI23 -> 32600 | AP23: =U23+AB23 -> 0.7 | AQ23: =AL23*AP23/(AG23+AE23) -> 3.4355828 | AR23: A lançar
A24: MAP073 | B24: A DEFINIR - CABO FRIO | C24: https://earth.google.com/web/search/CABO+FRIO/@-22.8250059,-42.03103576,12.7124684a,2857.57864826d,35y,0h,0t,0r/data=CiwiJgokCVC2q1CQAz7AERjRb_uvCD7AGY9__Xk0bkrAIVnsd6A3dErAQgIIAToDCgEwQgIIAEoICJfn8a8FEAA?authuser=0 | D24: 1 | E24: Estudo de viabilidade | G24: 2395 | J24: 270 | K24: SUDESTE | L24: CABO FRIO | M24: RJ | N24: A DEFINIR | O24: Parceria | P24: 0 | Q24: Loteamento | R24: - | S24: 2029 | T24: 47391 | U24: 0.7 | V24: 0.3 | W24: =SUM(U24:V24) -> 1 | X24: 0.05 | Y24: 0 | Z24: 0.068 | AA24: 0.198 | AC24: 325041 | AE24: =P24/10^6 -> 0 | AF24: =IF(AL24=0,0,AE24/AL24) -> 0 | AG24: =(AH24*AI24*AJ24)/10^6 -> 26.3408 | AH24: 163 | AI24: 200 | AJ24: 808 | AK24: 500 | AL24: =(AK24*AJ24*AI24)/10^6 -> 80.8 | AM24: =AL24*U24 -> 56.56 | AN24: =AI24*AK24 -> 100000 | AO24: =AH24*AI24 -> 32600 | AP24: =U24+AB24 -> 0.7 | AQ24: =AL24*AP24/(AG24+AE24) -> 2.1472393 | AR24: A lançar
A25: MAP073 | B25: A DEFINIR - CABO FRIO | C25: https://earth.google.com/web/search/CABO+FRIO/@-22.8250059,-42.03103576,12.7124684a,2857.57864826d,35y,0h,0t,0r/data=CiwiJgokCVC2q1CQAz7AERjRb_uvCD7AGY9__Xk0bkrAIVnsd6A3dErAQgIIAToDCgEwQgIIAEoICJfn8a8FEAA?authuser=0 | D25: 1 | E25: Estudo de viabilidade | G25: 2395 | J25: 271 | K25: SUDESTE | L25: CABO FRIO | M25: RJ | N25: A DEFINIR | O25: Parceria | P25: 0 | Q25: Loteamento | R25: - | S25: 2029 | T25: 47391 | U25: 0.7 | V25: 0.3 | W25: =SUM(U25:V25) -> 1 | X25: 0.05 | Y25: 0 | Z25: 0.068 | AA25: 0.198 | AC25: 325041 | AE25: =P25/10^6 -> 0 | AF25: =IF(AL25=0,0,AE25/AL25) -> 0 | AG25: =(AH25*AI25*AJ25)/10^6 -> 26.3082 | AH25: 163 | AI25: 200 | AJ25: 807 | AK25: 800 | AL25: =(AK25*AJ25*AI25)/10^6 -> 129.12 | AM25: =AL25*U25 -> 90.384 | AN25: =AI25*AK25 -> 160000 | AO25: =AH25*AI25 -> 32600 | AP25: =U25+AB25 -> 0.7 | AQ25: =AL25*AP25/(AG25+AE25) -> 3.4355828 | AR25: A lançar
A26: MAP045 | B26: CHACARA PARAISO - UBERABA | C26: https://earth.google.com/web/search/UBERABA/@-19.72044234,-47.90939623,805.08281673a,3321.08224063d,35y,0h,0t,0r/data=CiwiJgokCVPME395-TbAEeHVZYPw-zbAGd2RiiIOvUXAIT6JLXLGv0XAQgIIAToDCgEwQgIIAEoICJfn8a8FEAA?authuser=0 | D26: 1 | E26: Estudo de viabilidade | G26: 2267 | J26: 217 | K26: SUDESTE | L26: UBERABA | M26: MG | N26: CHACARA PARAISO | O26: Parceria | P26: 0 | Q26: Loteamento | R26: - | S26: 2029 | T26: 47299 | U26: 0.687525 | V26: 0.25 | W26: =SUM(U26:V26) -> 0.937525 | X26: 0.05 | Y26: 0 | Z26: 0.068 | AA26: 0.198 | AB26: 0.062475 | AC26: =AI26*AJ26 -> 204000 | AE26: =P26/10^6 -> 0 | AF26: =IF(AL26=0,0,AE26/AL26) -> 0 | AG26: =(AH26*AI26*AJ26)/10^6 -> 28.56 | AH26: 140 | AI26: 300 | AJ26: 680 | AK26: 500 | AL26: =(AK26*AJ26*AI26)/10^6 -> 102 | AM26: =AL26*U26 -> 70.12755 | AN26: =AI26*AK26 -> 150000 | AO26: =AH26*AI26 -> 42000 | AP26: =U26+AB26 -> 0.75 | AQ26: =AL26*AP26/(AG26+AE26) -> 2.6785714 | AR26: A lançar
A27: MAP074 | B27: 1B - CACHOEIRA DO SUL - CACHOEIRA DO SUL | C27: https://earth.google.com/web/search/PORTO+ALEGRE/@-30.02393013,-52.88446203,56.86896845a,3471.83898874d,35y,0h,0t,0r/data=CiwiJgokCdF8eOBcqz3AEVk4mQ0orz3AGW7M2FWxNkrAIVpN-_QgO0rAQgIIAToDCgEwQgIIAEoICJfn8a8FEAA?authuser=0 | D27: 1 | E27: LandBank | G27: 2372 | J27: 274 | K27: SUL | L27: CACHOEIRA DO SUL | M27: RS | N27: 1B - CACHOEIRA DO SUL | O27: Parceria | P27: 0 | Q27: Loteamento | R27: Sim | S27: 2029 | T27: 47208 | U27: 0.572 | V27: 0.285 | W27: =SUM(U27:V27) -> 0.857 | X27: 0.07 | Y27: 0 | Z27: 0.068 | AA27: 0.198 | AB27: 0.143 | AC27: 88108 | AE27: =P27/10^6 -> 0 | AF27: =IF(AL27=0,0,AE27/AL27) -> 0 | AG27: =(AH27*AI27*AJ27)/10^6 -> 15.4126 | AH27: 175 | AI27: 218 | AJ27: 404 | AK27: 600 | AL27: =(AK27*AJ27*AI27)/10^6 -> 52.8432 | AM27: =AL27*U27 -> 30.22631 | AN27: =AI27*AK27 -> 130800 | AO27: =AH27*AI27 -> 38150 | AP27: =U27+AB27 -> 0.715 | AQ27: =AL27*AP27/(AG27+AE27) -> 2.4514286 | AR27: A lançar
A28: MAP075 | B28: 2D - GUAÍBA - GUAÍBA | C28: https://earth.google.com/web/search/PORTO+ALEGRE/@-30.15639376,-51.37950813,15.7953786a,5231.5657715d,35y,360h,0t,0r/data=CiwiJgokCdF8eOBcqz3AEVk4mQ0orz3AGW7M2FWxNkrAIVpN-_QgO0rAQgIIAToDCgEwQgIIAEoICJfn8a8FEAA?authuser=0 | D28: 1 | E28: LandBank | G28: 2377 | J28: 278 | K28: SUL | L28: GUAÍBA | M28: RS | N28: 2D - GUIAÍBA | O28: Parceria | P28: 0 | Q28: Loteamento | R28: - | S28: 2029 | T28: 47483 | U28: 0.56 | V28: 0.3 | W28: =SUM(U28:V28) -> 0.86 | X28: 0.07 | Y28: 0.095 | Z28: 0.068 | AA28: 0.198 | AB28: 0.14 | AC28: =AI28*AJ28 -> 220066.67 | AE28: =P28/10^6 -> 0 | AF28: =IF(AL28=0,0,AE28/AL28) -> 0 | AG28: =(AH28*AI28*AJ28)/10^6 -> 38.511667 | AH28: 175 | AI28: 269.03015 | AJ28: 818 | AK28: 650 | AL28: =(AK28*AJ28*AI28)/10^6 -> 143.04333 | AM28: =AL28*U28 -> 80.104267 | AN28: =AI28*AK28 -> 174869.6 | AO28: =AH28*AI28 -> 47080.277 | AP28: =U28+AB28 -> 0.7 | AQ28: =AL28*AP28/(AG28+AE28) -> 2.6 | AR28: A lançar
A29: MAP078 | B29: 3AB - POA CIDADE NOVA /ARILDO - PORTO ALEGRE | C29: https://earth.google.com/web/search/PORTO+ALEGRE/@-30.12584024,-51.13053681,31.39242651a,5997.00691746d,35y,0h,0t,0r/data=CiwiJgokCdF8eOBcqz3AEVk4mQ0orz3AGW7M2FWxNkrAIVpN-_QgO0rAQgIIAToDCgEwQgIIAEoICJfn8a8FEAA?authuser=0 | D29: 1 | E29: LandBank | G29: 2381 | J29: 281 | K29: SUL | L29: PORTO ALEGRE | M29: RS | N29: 3AB - POA CIDADE NOVA/ ARILDO | O29: Parceria | P29: 0 | Q29: Condominio | R29: Sim | S29: 2029 | T29: 47483 | U29: 0.4341 | V29: 0.4574 | W29: =SUM(U29:V29) -> 0.8915 | X29: 0.07 | Y29: 0.06 | Z29: 0.068 | AA29: 0.198 | AB29: 0.1085 | AC29: =AI29*AJ29 -> 132000 | AE29: =P29/10^6 -> 0 | AF29: =IF(AL29=0,0,AE29/AL29) -> 0 | AG29: =(AH29*AI29*AJ29)/10^6 -> 39.6 | AH29: 300 | AI29: 185.13324 | AJ29: 713 | AK29: 1200 | AL29: =(AK29*AJ29*AI29)/10^6 -> 158.4 | AM29: =AL29*U29 -> 68.76144 | AN29: =AI29*AK29 -> 222159.89 | AO29: =AH29*AI29 -> 55539.972 | AP29: =U29+AB29 -> 0.5426 | AQ29: =AL29*AP29/(AG29+AE29) -> 2.1704 | AR29: A lançar
A30: MAP090 | B30: 6E - CX. SUL - SIVIERO / PEDROTTI - CAXIAS DO SUL | C30: https://earth.google.com/web/search/CAXIAS+DO+SUL/@-29.14851045,-51.12842458,807.83064617a,2723.19233128d,35y,0h,0t,0r/data=CnwaThJICiUweDk1MWViY2QxNjQzNWYwNzM6MHhmNTE0ZjcwN2I1NzczYmY0GVOObimMLD3AIRz3nKoxl0nAKg1DQVhJQVMgRE8gU1VMGAEgASImCiQJ1tRH0utLPcARa0Tc7klTPcAZjiIdAINaScAhKwpGrRhjScBCAggBOgMKATBCAggASggIl-fxrwUQAA?authuser=0 | D30: 1 | E30: LandBank | G30: 2374 | J30: 303 | K30: SUL | L30: CAXIAS DO SUL | M30: RS | N30: 6E - CX. SUL - SIVIERO / PEDROTTI | O30: Parceria | P30: 0 | Q30: Loteamento | R30: - | S30: 2029 | T30: 47391 | U30: 0.4 | V30: 0.5 | W30: =SUM(U30:V30) -> 0.9 | X30: 0.07 | Y30: 0.095 | Z30: 0.068 | AA30: 0.198 | AB30: 0.1 | AC30: =AI30*AJ30 -> 150500 | AE30: =P30/10^6 -> 0 | AF30: =IF(AL30=0,0,AE30/AL30) -> 0 | AG30: =(AH30*AI30*AJ30)/10^6 -> 26.3375 | AH30: 175 | AI30: 446.58754 | AJ30: 337 | AK30: 750 | AL30: =(AK30*AJ30*AI30)/10^6 -> 112.875 | AM30: =AL30*U30 -> 45.15 | AN30: =AI30*AK30 -> 334940.65 | AO30: =AH30*AI30 -> 78152.819 | AP30: =U30+AB30 -> 0.5 | AQ30: =AL30*AP30/(AG30+AE30) -> 2.1428571 | AR30: A lançar
A31: MAP092 | B31: 7 - CANELA II - CANELA | C31: https://earth.google.com/web/search/CANELA/@-29.31096028,-50.74065533,783.58216028a,4290.20961313d,35y,0h,0t,0r/data=CiwiJgokCaHXsZR7Dj7AEYnRurPGEj7AGVFhjI5xgknAIZdzDtB7h0nAQgIIAToDCgEwQgIIAEoICJfn8a8FEAA?authuser=0 | D31: 1 | E31: LandBank | G31: 2373 | J31: 306 | K31: SUL | L31: CANELA | M31: RS | N31: 7 - CANELA II | O31: Parceria | P31: 0 | Q31: Loteamento | R31: - | S31: 2029 | T31: 47299 | U31: 0.5918 | V31: 0.2603 | W31: =SUM(U31:V31) -> 0.8521 | X31: 0.07 | Y31: 0.095 | Z31: 0.068 | AA31: 0.198 | AB31: 0.1479 | AC31: =AI31*AJ31 -> 375000 | AE31: =P31/10^6 -> 0 | AF31: =IF(AL31=0,0,AE31/AL31) -> 0 | AG31: =(AH31*AI31*AJ31)/10^6 -> 65.625 | AH31: 175 | AI31: 400 | AJ31: 937.5 | AK31: 750 | AL31: =(AK31*AJ31*AI31)/10^6 -> 281.25 | AM31: =AL31*U31 -> 166.44375 | AN31: =AI31*AK31 -> 300000 | AO31: =AH31*AI31 -> 70000 | AP31: =U31+AB31 -> 0.7397 | AQ31: =AL31*AP31/(AG31+AE31) -> 3.1701429 | AR31: A lançar
A32: MAP102 | B32: 13 - TORRES - TORRES | C32: https://earth.google.com/web/search/Torres,+RS/@-29.39094249,-49.79542536,11.86627966a,3844.364941d,35y,0h,0t,0r/data=CiwiJgokCUqW-EB3YznAEXs_7PEYaTnAGabKp-VawEnAIVblElawxknAQgIIAToDCgEwQgIIAEoICJfn8a8FEAA?authuser=0 | D32: 1 | E32: Estudo de viabilidade | G32: 2392 | J32: 321 | K32: SUL | L32: TORRES | M32: RS | N32: 13 - TORRES | O32: Parceria | P32: 0 | Q32: Loteamento | R32: - | S32: 2029 | T32: 47299 | U32: 0.536 | V32: 0.33 | W32: =SUM(U32:V32) -> 0.866 | X32: 0.07 | Y32: 0.095 | Z32: 0.068 | AA32: 0.198 | AB32: 0.134 | AC32: =AI32*AJ32 -> 107400 | AE32: =P32/10^6 -> 0 | AF32: =IF(AL32=0,0,AE32/AL32) -> 0 | AG32: =(AH32*AI32*AJ32)/10^6 -> 18.795 | AH32: 175 | AI32: 300 | AJ32: 358 | AK32: 600 | AL32: =(AK32*AJ32*AI32)/10^6 -> 64.44 | AM32: =AL32*U32 -> 34.53984 | AN32: =AI32*AK32 -> 180000 | AO32: =AH32*AI32 -> 52500 | AP32: =U32+AB32 -> 0.67 | AQ32: =AL32*AP32/(AG32+AE32) -> 2.2971429 | AR32: A lançar
A33: MAP105 | B33: 15 - VITORINO - 64HA II - VITORINO | C33: - | D33: 1 | E33: LandBank | G33: 2390 | J33: 325 | K33: SUL | L33: VITORINO | M33: PR | N33: 15 - VITORINO - 64HA II | O33: Parceria | P33: 0 | Q33: Loteamento | R33: - | S33: 2029 | T33: 47483 | U33: 0.592 | V33: 0.26 | W33: =SUM(U33:V33) -> 0.852 | X33: 0.07 | Y33: 0.095 | Z33: 0.068 | AA33: 0.198 | AB33: 0.148 | AC33: =AI33*AJ33 -> 190000 | AE33: =P33/10^6 -> 0 | AF33: =IF(AL33=0,0,AE33/AL33) -> 0 | AG33: =(AH33*AI33*AJ33)/10^6 -> 33.25 | AH33: 175 | AI33: 179.92424 | AJ33: 1056 | AK33: 550 | AL33: =(AK33*AJ33*AI33)/10^6 -> 104.5 | AM33: =AL33*U33 -> 61.864 | AN33: =AI33*AK33 -> 98958.333 | AO33: =AH33*AI33 -> 31486.742 | AP33: =U33+AB33 -> 0.74 | AQ33: =AL33*AP33/(AG33+AE33) -> 2.3257143 | AR33: A lançar
A34: MAP132 | B34: 12B - SAPIRANGA | D34: 1 | E34: LandBank | G34: 2393 | K34: SUL | L34: SAPIRANGA | M34: RS | N34: A DEFINIR | O34: Parceria | P34: 0 | Q34: Loteamento | R34: - | S34: 2029 | U34: 0.56 | V34: 0.3 | W34: =SUM(U34:V34) -> 0.86 | AA34: 0.198 | AC34: =AI34*AJ34 -> 159900 | AE34: =P34/10^6 -> 0 | AF34: =IF(AL34=0,0,AE34/AL34) -> 0 | AG34: =(AH34*AI34*AJ34)/10^6 -> 27.9825 | AH34: 175 | AI34: 300 | AJ34: 533 | AK34: 700 | AL34: =(AK34*AJ34*AI34)/10^6 -> 111.93 | AM34: =AL34*U34 -> 62.6808 | AN34: =AI34*AK34 -> 210000 | AO34: =AH34*AI34 -> 52500 | AP34: =U34+AB34 -> 0.56 | AQ34: =AL34*AP34/(AG34+AE34) -> 2.24 | AR34: A lançar
A35: MAP022 | B35: RESIDENCIAL BURITI GARGEN (SÃO CAMILO) - PALMAS | C35: https://earth.google.com/web/search/Palmas/@-10.25056053,-48.33726188,252.56505595a,47484.59826451d,35y,0h,0t,0r/data=CnQaRhJACiQweDkzM2IzNDM5OTExZjEyNTc6MHg5M2I4MDcwZDA1YzgxOGYZtHQF24h_JMAhUsd0MoIpSMAqBlBhbG1hcxgCIAEiJgokCZ4TQp4rbCTAEd7oz8tIyyTAGZMBVXzHEEjAIR-xYc3lQUjAQgIIAToDCgEwQgIIAEoICJfn8a8FEAA?authuser=0 | D35: 1 | E35: LandBank | G35: PENDENCIA | J35: 180 | K35: TOCANTINS | L35: PALMAS | M35: TO | N35: RESIDENCIAL BURITI GARDEN | O35: Parceria | P35: 0 | Q35: Condominio | R35: - | S35: 2029 | T35: 47483 | U35: 0.438 | V35: 0.27 | W35: =SUM(U35:V35) -> 0.708 | X35: 0.05 | Y35: 0.09 | Z35: 0.068 | AA35: 0.198 | AB35: 0.292 | AC35: =AI35*AJ35 -> 202246.88 | AE35: =P35/10^6 -> 0 | AF35: =IF(AL35=0,0,AE35/AL35) -> 0 | AG35: =(AH35*AI35*AJ35)/10^6 -> 44.494313 | AH35: 220 | AI35: 439.66712 | AJ35: 460 | AK35: 900 | AL35: =(AK35*AJ35*AI35)/10^6 -> 182.02219 | AM35: =AL35*U35 -> 79.725719 | AN35: =AI35*AK35 -> 395700.41 | AO35: =AH35*AI35 -> 96726.767 | AP35: =U35+AB35 -> 0.73 | AQ35: =AL35*AP35/(AG35+AE35) -> 2.9863636 | AR35: A lançar
A36: MAP022 | B36: RESIDENCIAL BURITI GARGEN (SÃO CAMILO) II - PALMAS | C36: https://earth.google.com/web/search/Palmas/@-10.25056053,-48.33726188,252.56505595a,47484.59826451d,35y,0h,0t,0r/data=CnQaRhJACiQweDkzM2IzNDM5OTExZjEyNTc6MHg5M2I4MDcwZDA1YzgxOGYZtHQF24h_JMAhUsd0MoIpSMAqBlBhbG1hcxgCIAEiJgokCZ4TQp4rbCTAEd7oz8tIyyTAGZMBVXzHEEjAIR-xYc3lQUjAQgIIAToDCgEwQgIIAEoICJfn8a8FEAA?authuser=0 | D36: 1 | E36: LandBank | G36: PENDENCIA | J36: 181 | K36: TOCANTINS | L36: PALMAS | M36: TO | N36: RESIDENCIAL BURITI GARDEN II | O36: Parceria | P36: 0 | Q36: Condominio | R36: - | S36: 2029 | T36: 47483 | U36: 0.438 | V36: 0.27 | W36: =SUM(U36:V36) -> 0.708 | X36: 0.05 | Y36: 0.09 | Z36: 0.068 | AA36: 0.198 | AB36: 0.292 | AC36: =AI36*AJ36 -> 202246.88 | AE36: =P36/10^6 -> 0 | AF36: =IF(AL36=0,0,AE36/AL36) -> 0 | AG36: =(AH36*AI36*AJ36)/10^6 -> 44.494313 | AH36: 220 | AI36: 439.66712 | AJ36: 460 | AK36: 900 | AL36: =(AK36*AJ36*AI36)/10^6 -> 182.02219 | AM36: =AL36*U36 -> 79.725719 | AN36: =AI36*AK36 -> 395700.41 | AO36: =AH36*AI36 -> 96726.767 | AP36: =U36+AB36 -> 0.73 | AQ36: =AL36*AP36/(AG36+AE36) -> 2.9863636 | AR36: A lançar
A37: MAP122 | B37: JARDIM DO CERRADO 5 - GOIÂNIA | C37: https://earth.google.com/web/search/GOI%c3%82NIA/@-16.67746594,-49.42770992,858.01737984a,4789.30417081d,35y,9.31126662h,0.18897674t,360r/data=CiwiJgokCTImrsNH8yrAEajobj-t-irAGWOHbhWxkEjAIXn8jCOOlEjAQgIIAToDCgEwQgIIAEoICJfn8a8FEAA?authuser=0 | D37: 1 | E37: LandBank | G37: 2770 | J37: 358 | K37: CENTRO-OESTE II | L37: GOIÂNIA | M37: GO | N37: JARDIM DO CERRADO 5 | O37: Parceria | P37: 0 | Q37: Loteamento | R37: - | S37: 2030 | T37: 47848 | U37: 0.8 | W37: =SUM(U37:V37) -> 0.8 | AA37: 0.198 | AB37: 0.2 | AC37: =AI37*AJ37 -> 260020.4 | AE37: =P37/10^6 -> 0 | AF37: =IF(AL37=0,0,AE37/AL37) -> 0 | AG37: =(AH37*AI37*AJ37)/10^6 -> 38.483019 | AH37: 148 | AI37: 296.82694 | AJ37: 876 | AK37: 500 | AL37: =(AK37*AJ37*AI37)/10^6 -> 130.0102 | AM37: =AL37*U37 -> 104.00816 | AN37: =AI37*AK37 -> 148413.47 | AO37: =AH37*AI37 -> 43930.387 | AP37: =U37+AB37 -> 1 | AQ37: =AL37*AP37/(AG37+AE37) -> 3.3783784 | AR37: A lançar
A38: MAP040 | B38: JARDIM AMERICA III - TAUÁ | C38: https://earth.google.com/web/search/TAU%c3%81/@-5.97683983,-40.30366275,407.4430109a,2966.57752085d,35y,0h,0t,0r/data=CiwiJgokCVwuodN7uSdAEajZ7_kEaz3AGcctYEv-xi1AIcrxv7LiwVjAQgIIAToDCgEwQgIIAEoICJfn8a8FEAA?authuser=0 | D38: 1 | E38: LandBank | G38: 2056 | J38: 208 | K38: NORDESTE II | L38: TAUÁ | M38: CE | N38: JARDIM AMERICA III | O38: Parceria | P38: 0 | Q38: Loteamento | R38: Sim | S38: 2030 | T38: 47572 | U38: 0.79 | V38: 0.21 | W38: =SUM(U38:V38) -> 1 | X38: 0.05 | Y38: 0 | Z38: 0.068 | AA38: 0.198 | AC38: 201305 | AE38: =P38/10^6 -> 0 | AF38: =IF(AL38=0,0,AE38/AL38) -> 0 | AG38: =(AH38*AI38*AJ38)/10^6 -> 21.793536 | AH38: 108 | AI38: 192 | AJ38: 1051 | AK38: 480 | AL38: =(AK38*AJ38*AI38)/10^6 -> 96.86016 | AM38: =AL38*U38 -> 76.519526 | AN38: =AI38*AK38 -> 92160 | AO38: =AH38*AI38 -> 20736 | AP38: =U38+AB38 -> 0.79 | AQ38: =AL38*AP38/(AG38+AE38) -> 3.5111111 | AR38: A lançar
A39: MAP042 | B39: RESIDENCIAL CIDADE JARDIM III - BALSAS | C39: https://earth.google.com/web/search/BALSAS/@-7.55676262,-46.08364445,276.35723714a,5135.12989945d,35y,0h,0t,0r/data=CiwiJgokCeJxBz6CxDDAEQlwGFeXzDDAGfey9riu6UXAIWSXkF1C8kXAQgIIAToDCgEwQgIIAEoICJfn8a8FEAA?authuser=0 | D39: 1 | E39: LandBank | F39: REVER PROJETOS | G39: 2052 | J39: 212 | K39: NORDESTE II | L39: BALSAS | M39: MA | N39: RESIDENCIAL CIDADE JARDIM III | O39: Parceria | P39: 0 | Q39: Loteamento | R39: - | S39: 2030 | T39: 48487 | U39: 0.8 | V39: 0.2 | W39: =SUM(U39:V39) -> 1 | X39: 0.05 | Y39: 0 | Z39: 0.068 | AA39: 0.198 | AC39: =AI39*AJ39 -> 271890 | AE39: =P39/10^6 -> 0 | AF39: =IF(AL39=0,0,AE39/AL39) -> 0 | AG39: =(AH39*AI39*AJ39)/10^6 -> 32.6268 | AH39: 120 | AI39: 265 | AJ39: 1026 | AK39: 500 | AL39: =(AK39*AJ39*AI39)/10^6 -> 135.945 | AM39: =AL39*U39 -> 108.756 | AN39: =AI39*AK39 -> 132500 | AO39: =AH39*AI39 -> 31800 | AP39: =U39+AB39 -> 0.8 | AQ39: =AL39*AP39/(AG39+AE39) -> 3.3333333 | AR39: A lançar
A40: MAP010 | B40: CIDADE JARDIM V - SANTARÉM | C40: https://earth.google.com/web/search/CIDADE+JARDIM+12+-+PARAUAPEBAS/@-2.45795692,-54.77217012,46.50042218a,6405.178905d,35y,-0h,0t,0r/data=CiwiJgokCdmVqMeMyQbAESVW3mJaMwnAGYI6tUF7jUfAIaCAQToN3EfAQgIIAToDCgEwQgIIAEoICJfn8a8FEAA | D40: 1 | E40: LandBank | G40: 2121 | J40: 150 | K40: NORTE | L40: SANTARÉM | M40: PA | N40: CIDADE JARDIM V | O40: Aquisição de Cotas | P40: 4800000 | Q40: Loteamento | R40: Sim | S40: 2030 | T40: 47848 | U40: 1 | W40: =SUM(U40:V40) -> 1 | AA40: 0.198 | AC40: =AI40*AJ40 -> 61214.16 | AE40: =P40/10^6 -> 4.8 | AF40: =IF(AL40=0,0,AE40/AL40) -> 0.15682646 | AG40: =(AH40*AI40*AJ40)/10^6 -> 8.1476047 | AH40: 133.1 | AI40: 275.73946 | AJ40: 222 | AK40: 500 | AL40: =(AK40*AJ40*AI40)/10^6 -> 30.60708 | AM40: =AL40*U40 -> 30.60708 | AN40: =AI40*AK40 -> 137869.73 | AO40: =AH40*AI40 -> 36700.922 | AP40: =U40+AB40 -> 1 | AQ40: =AL40*AP40/(AG40+AE40) -> 2.3639183 | AR40: A lançar
A41: MAP013 | B41: RESIDENCIAL CIDADE JARDIM III - SANTANA DO ARAGUAIA | C41: https://earth.google.com/web/search/SANTANA+DO+ARAGUAIA/@-9.33586436,-50.36139721,175.24087708a,6146.88773774d,35y,0.00000002h,0t,0r/data=CoIBGlQSTgolMHg5MzFmMzU2MjJhMTljZmQxOjB4NDBiYzMzMTdkYTkxODA2NxkY0GYwoa0iwCGS2Q9nNCtJwCoTU0FOVEFOQSBETyBBUkFHVUFJQRgCIAEiJgokCSW03oMpdxzAEQai9168gBzAGSqKf2w09UjAIfPbVLWn90jAQgIIAToDCgEwQgIIAEoICJfn8a8FEAA?authuser=0 | D41: 1 | E41: LandBank | G41: 2123 | J41: 154 | K41: NORTE | L41: SANTANA DO ARAGUAIA | M41: PA | N41: RESIDENCIAL CIDADE JARDIM III | O41: Compra e Venda | P41: 114285.71 | Q41: Loteamento | R41: Sim | S41: 2030 | T41: 47848 | U41: 1 | W41: =SUM(U41:V41) -> 1 | AA41: 0.198 | AC41: =AI41*AJ41 -> 105000 | AE41: =P41/10^6 -> 0.11428571 | AF41: =IF(AL41=0,0,AE41/AL41) -> 0.0027908598 | AG41: =(AH41*AI41*AJ41)/10^6 -> 13.9755 | AH41: 133.1 | AI41: 210 | AJ41: 500 | AK41: 390 | AL41: =(AK41*AJ41*AI41)/10^6 -> 40.95 | AM41: =AL41*U41 -> 40.95 | AN41: =AI41*AK41 -> 81900 | AO41: =AH41*AI41 -> 27951 | AP41: =U41+AB41 -> 1 | AQ41: =AL41*AP41/(AG41+AE41) -> 2.9063607 | AR41: A lançar
A42: MAP113 | B42: BURITI GARDEN PRIME - VARZEA GRANDE | C42: https://earth.google.com/web/search/CUIAB%c3%81/@-15.61005921,-56.15084275,175.93804739a,4592.0123658d,35y,0h,0t,0r/data=CiwiJgokCTDbVLh45ybAEXD1A07O7ybAGaZZUBA5uU7AIdT4-d2KvU7AQgIIAToDCgEwQgIIAEoICJfn8a8FEAA?authuser=0 | D42: 1 | E42: LandBank | G42: 1930 | J42: 346 | K42: OESTE | L42: VARZEA GRANDE | M42: MT | N42: BURITI GARDEN PRIME | O42: Parceria | P42: 0 | Q42: Condominio | R42: - | S42: 2030 | T42: 47664 | U42: 0.7 | V42: 0.3 | W42: =SUM(U42:V42) -> 1 | X42: 0.05 | Y42: 0.09 | Z42: 0.068 | AA42: 0.198 | AC42: =AI42*AJ42 -> 139700 | AE42: =P42/10^6 -> 0 | AF42: =IF(AL42=0,0,AE42/AL42) -> 0 | AG42: =(AH42*AI42*AJ42)/10^6 -> 36.322 | AH42: 260 | AI42: 220 | AJ42: 635 | AK42: 1200 | AL42: =(AK42*AJ42*AI42)/10^6 -> 167.64 | AM42: =AL42*U42 -> 117.348 | AN42: =AI42*AK42 -> 264000 | AO42: =AH42*AI42 -> 57200 | AP42: =U42+AB42 -> 0.7 | AQ42: =AL42*AP42/(AG42+AE42) -> 3.2307692 | AR42: A lançar
A43: MAP112 | B43: RESIDENCIAL CIDADE JARDIM II - TANGARÁ DA SERRA | C43: https://earth.google.com/web/search/TANGAR%c3%81+DA+SERRA/@-14.62032689,-57.54082084,346.92096178a,5258.20888551d,35y,0h,0t,0r/data=CiwiJgokCXA9rQptMS_AEXKWStZFPy_AGehdnQKoD0zAIeamtZ71FkzAQgIIAToDCgEwQgIIAEoICJfn8a8FEAA?authuser=0 | D43: 1 | E43: LandBank | G43: 2107 | J43: 342 | K43: OESTE | L43: TANGARÁ DA SERRA | M43: MT | N43: RESIDENCIAL CIDADE JARDIM II | O43: Compra e Venda | P43: 10682.93 | Q43: Loteamento | R43: - | S43: 2030 | T43: 47848 | U43: 0.7 | V43: 0.3 | W43: =SUM(U43:V43) -> 1 | X43: 0.05 | Y43: 0.09 | Z43: 0.068 | AA43: 0.198 | AC43: =AI43*AJ43 -> 240799.25 | AE43: =P43/10^6 -> 0.01068293 | AF43: =IF(AL43=0,0,AE43/AL43) -> 8.8728931e-05 | AG43: =(AH43*AI43*AJ43)/10^6 -> 32.0263 | AH43: 133 | AI43: 264.90566 | AJ43: 909 | AK43: 500 | AL43: =(AK43*AJ43*AI43)/10^6 -> 120.39962 | AM43: =AL43*U43 -> 84.279737 | AN43: =AI43*AK43 -> 132452.83 | AO43: =AH43*AI43 -> 35232.453 | AP43: =U43+AB43 -> 0.7 | AQ43: =AL43*AP43/(AG43+AE43) -> 2.6307014 | AR43: A lançar
A44: MAP043 | B44: RESIDENCIAL CIDADE JARDIM III - MONTES CLAROS | C44: https://earth.google.com/web/search/MONTES+CLAROS/@-16.78340211,-43.85914746,708.18079241a,4857.74891966d,35y,0h,0t,0r/data=CiwiJgokCaYkZ-ZvtTPAEWpwuK9tuzPAGWYZIm4r8UfAIR546sKi90fAQgIIAToDCgEwQgIIAEoICJfn8a8FEAA?authuser=0 | D44: 1 | E44: LandBank | G44: 2288 | J44: 215 | K44: SUDESTE | L44: MONTES CLAROS | M44: MG | N44: RESIDENCIAL CIDADE JARDIM III | O44: Parceria | P44: 0 | Q44: Loteamento | R44: - | S44: 2030 | T44: 47756 | U44: 0.45835 | V44: 0.5 | W44: =SUM(U44:V44) -> 0.95835 | X44: 0.05 | Y44: 0 | Z44: 0.068 | AA44: 0.198 | AB44: 0.04165 | AC44: =AI44*AJ44 -> 242000 | AE44: =P44/10^6 -> 0 | AF44: =IF(AL44=0,0,AE44/AL44) -> 0 | AG44: =(AH44*AI44*AJ44)/10^6 -> 39.446 | AH44: 163 | AI44: 220 | AJ44: 1100 | AK44: 600 | AL44: =(AK44*AJ44*AI44)/10^6 -> 145.2 | AM44: =AL44*U44 -> 66.55242 | AN44: =AI44*AK44 -> 132000 | AO44: =AH44*AI44 -> 35860 | AP44: =U44+AB44 -> 0.5 | AQ44: =AL44*AP44/(AG44+AE44) -> 1.8404908 | AR44: A lançar
A45: MAP047 | B45: BURITI GARDEN PREMIUM - RIO WATER PLANET | C45: https://earth.google.com/web/search/Rio+Water+Planet+-+Vargem+Grande,+Rio+de+Janeiro+-+RJ/@-22.97932476,-43.48761622,7.82165637a,1689.89378841d,35y,0h,0t,0r/data=CiwiJgokCTgPgsbnOzDAEf3Z-ywSUjbAGak7SsebOEDAIc0sY3wO7EbAQgIIAToDCgEwQgIIAEoICJfn8a8FEAA?authuser=0 | D45: 1 | E45: LandBank | G45: 2299 | J45: 221 | K45: SUDESTE | L45: RIO DE JANEIRO | M45: RJ | N45: BURITI GARDEN PREMIUM | O45: Parceria | P45: 0 | Q45: Condominio | R45: - | S45: 2030 | T45: 47756 | U45: 0.4134 | V45: 0.38 | W45: =SUM(U45:V45) -> 0.7934 | X45: 0.05 | Y45: 0.09 | Z45: 0.068 | AA45: 0.198 | AB45: 0.2066 | AC45: =AI45*AJ45 -> 213918.34 | AE45: =P45/10^6 -> 0 | AF45: =IF(AL45=0,0,AE45/AL45) -> 0 | AG45: =(AH45*AI45*AJ45)/10^6 -> 77.010602 | AH45: 360 | AI45: 250.19689 | AJ45: 855 | AK45: 2000 | AL45: =(AK45*AJ45*AI45)/10^6 -> 427.83668 | AM45: =AL45*U45 -> 176.86768 | AN45: =AI45*AK45 -> 500393.78 | AO45: =AH45*AI45 -> 90070.88 | AP45: =U45+AB45 -> 0.62 | AQ45: =AL45*AP45/(AG45+AE45) -> 3.4444444 | AR45: A lançar
A46: MAP056 | B46: A DEFINIR II - ARRAIAL DO CABO | C46: https://earth.google.com/web/search/ARRAIAL+DO+CABO/@-22.93536918,-42.19797612,2.57990512a,8028.28875861d,35y,0h,0t,0r/data=CnwaThJICiMweDk3MTk3YmEwMTFkM2E5OjB4M2M0YTJiN2IxNGUwMDMwORnXiSarffc2wCH54BAFjgNFwCoPQVJSQUlBTCBETyBDQUJPGAEgASImCiQJ3jIbZ5OdN8AR8LcycgejN8AZIoh5YJwISMAhtPiWdKgOSMBCAggBOgMKATBCAggASggIl-fxrwUQAA?authuser=0 | D46: 1 | E46: LandBank | G46: 2269 | J46: 239 | K46: SUDESTE | L46: ARRAIAL DO CABO | M46: RJ | N46: A DEFINIR | O46: Parceria | P46: 0 | Q46: Loteamento | R46: Sim | S46: 2030 | T46: 47664 | U46: 0.6875 | V46: 0.25 | W46: =SUM(U46:V46) -> 0.9375 | X46: 0.05 | Y46: 0 | Z46: 0.068 | AA46: 0.198 | AB46: 0.0625 | AC46: =AI46*AJ46 -> 241875 | AE46: =P46/10^6 -> 0 | AF46: =IF(AL46=0,0,AE46/AL46) -> 0 | AG46: =(AH46*AI46*AJ46)/10^6 -> 39.425625 | AH46: 163 | AI46: 249.87087 | AJ46: 968 | AK46: 800 | AL46: =(AK46*AJ46*AI46)/10^6 -> 193.5 | AM46: =AL46*U46 -> 133.03125 | AN46: =AI46*AK46 -> 199896.69 | AO46: =AH46*AI46 -> 40728.951 | AP46: =U46+AB46 -> 0.75 | AQ46: =AL46*AP46/(AG46+AE46) -> 3.6809816 | AR46: A lançar
A47: MAP061 | B47: RESIDENCIAL CIDADE JARDIM III - LORENA | C47: https://earth.google.com/web/search/LORENA/@-22.76355759,-45.11165622,554.79907101a,2424.9160967d,35y,0h,0t,0r/data=CiwiJgokCdDYYcMpEDbAEb-si-d6FTbAGdP8OMJ1sEnAIeq0yPtJtknAQgIIAToDCgEwQgIIAEoICJfn8a8FEAA?authuser=0 | D47: 1 | E47: LandBank | G47: 2286 | J47: 251 | K47: SUDESTE | L47: LORENA | M47: SP | N47: RESIDENCIAL CIDADE JARDIM III | O47: Parceria | P47: 0 | Q47: Loteamento | R47: - | S47: 2030 | T47: 47664 | U47: 0.45 | V47: 0.5 | W47: =SUM(U47:V47) -> 0.95 | X47: 0.05 | Y47: 0.09 | Z47: 0.068 | AA47: 0.198 | AB47: 0.05 | AC47: =AI47*AJ47 -> 308574.72 | AE47: =P47/10^6 -> 0 | AF47: =IF(AL47=0,0,AE47/AL47) -> 0 | AG47: =(AH47*AI47*AJ47)/10^6 -> 50.29768 | AH47: 163 | AI47: 299.00651 | AJ47: 1032 | AK47: 605 | AL47: =(AK47*AJ47*AI47)/10^6 -> 186.68771 | AM47: =AL47*U47 -> 84.009468 | AN47: =AI47*AK47 -> 180898.94 | AO47: =AH47*AI47 -> 48738.062 | AP47: =U47+AB47 -> 0.5 | AQ47: =AL47*AP47/(AG47+AE47) -> 1.8558282 | AR47: A lançar
A48: MAP070 | B48: A DEFINIR - POÇOS DE CALDAS | C48: https://earth.google.com/web/search/PO%c3%87OS+DE+CALDAS/@-21.78752103,-46.62526154,1239.73456507a,4634.91540016d,35y,0h,0t,0r/data=Cn8aURJLCiUweDk0YzljMmMzMmU1YTE1MWI6MHg5MGM3ODc3Mzg3NDU4OWZjGcjJafQPyTXAIYDAuXXtR0fAKhBQT8OHT1MgREUgQ0FMREFTGAEgASImCiQJvqqkfAn8NsAR9cW7viP-NsAZjS2Rv8vERcAhTKeEvR3HRcBCAggBOgMKATBCAggASggIl-fxrwUQAA?authuser=0 | D48: 0 | E48: LandBank | G48: 2290 | J48: 265 | K48: SUDESTE | L48: POÇOS DE CALDAS | M48: MG | N48: A DEFINIR | O48: Parceria | P48: 0 | Q48: Loteamento | R48: Sim | S48: 2030 | T48: 47756 | U48: 0.7 | V48: 0.3 | W48: =SUM(U48:V48) -> 1 | X48: 0.05 | Y48: 0 | Z48: 0.068 | AA48: 0.198 | AC48: =AI48*AJ48 -> 269699.39 | AE48: =P48/10^6 -> 0 | AF48: =IF(AL48=0,0,AE48/AL48) -> 0 | AG48: =(AH48*AI48*AJ48)/10^6 -> 43.961001 | AH48: 163 | AI48: 269.16107 | AJ48: 1002 | AK48: 600 | AL48: =(AK48*AJ48*AI48)/10^6 -> 161.81964 | AM48: =AL48*U48 -> 113.27374 | AN48: =AI48*AK48 -> 161496.64 | AO48: =AH48*AI48 -> 43873.254 | AP48: =U48+AB48 -> 0.7 | AQ48: =AL48*AP48/(AG48+AE48) -> 2.5766871 | AR48: A lançar
A49: MAP098 | B49: 10B - RIO GRANDE - AQUARIO/IBOTY - RIO GRANDE DO SUL | C49: https://earth.google.com/web/search/RIO+GRANDE+DO+SUL/@-32.11183503,-52.18658908,5.40403187a,4423.26572132d,35y,-0h,0t,0r/data=CoABGlISTAolMHg5NTA0NzIwYzQwYjQ1ODAzOjB4YWQ5ZmIzZGJhZjlmNzNkZRnYHgdvWV09wCGQV9bsN9VJwCoRUklPIEdSQU5ERSBETyBTVUwYASABIiYKJAkw_JT_K_M9wBEf1nHWmAI-wBmH-JguXXlJwCFODtDCdYtJwEICCAE6AwoBMEICCABKCAiX5_GvBRAA?authuser=0 | D49: 1 | E49: LandBank | G49: 2383 | J49: 315 | K49: SUL | L49: RIO GRANDE | M49: RS | N49: 10B - RIO GRANDE - AQUARIO/IBOTY | O49: Parceria | P49: 0 | Q49: Loteamento | R49: - | S49: 2030 | T49: 47664 | U49: 0.648 | V49: 0.19 | W49: =SUM(U49:V49) -> 0.838 | X49: 0.07 | Y49: 0.095 | Z49: 0.068 | AA49: 0.198 | AB49: 0.162 | AC49: =AI49*AJ49 -> 166770 | AE49: =P49/10^6 -> 0 | AF49: =IF(AL49=0,0,AE49/AL49) -> 0 | AG49: =(AH49*AI49*AJ49)/10^6 -> 29.18475 | AH49: 175 | AI49: 160.04798 | AJ49: 1042 | AK49: 550 | AL49: =(AK49*AJ49*AI49)/10^6 -> 91.7235 | AM49: =AL49*U49 -> 59.436828 | AN49: =AI49*AK49 -> 88026.392 | AO49: =AH49*AI49 -> 28008.397 | AP49: =U49+AB49 -> 0.81 | AQ49: =AL49*AP49/(AG49+AE49) -> 2.5457143 | AR49: A lançar
A50: MAP075 | B50: 2C - GUAÍBA - GUAÍBA | C50: https://earth.google.com/web/search/PORTO+ALEGRE/@-30.15639376,-51.37950813,15.7953786a,5231.5657715d,35y,360h,0t,0r/data=CiwiJgokCdF8eOBcqz3AEVk4mQ0orz3AGW7M2FWxNkrAIVpN-_QgO0rAQgIIAToDCgEwQgIIAEoICJfn8a8FEAA?authuser=0 | D50: 1 | E50: LandBank | G50: 2377 | J50: 277 | K50: SUL | L50: GUAÍBA | M50: RS | N50: 2C - GUIAÍBA | O50: Parceria | P50: 0 | Q50: Loteamento | R50: Sim | S50: 2030 | T50: 47848 | U50: 0.56 | V50: 0.3 | W50: =SUM(U50:V50) -> 0.86 | X50: 0.07 | Y50: 0.095 | Z50: 0.068 | AA50: 0.198 | AB50: 0.14 | AC50: =AI50*AJ50 -> 188921.6 | AE50: =P50/10^6 -> 0 | AF50: =IF(AL50=0,0,AE50/AL50) -> 0 | AG50: =(AH50*AI50*AJ50)/10^6 -> 33.061279 | AH50: 175 | AI50: 203.1415 | AJ50: 930 | AK50: 650 | AL50: =(AK50*AJ50*AI50)/10^6 -> 122.79904 | AM50: =AL50*U50 -> 68.767461 | AN50: =AI50*AK50 -> 132041.98 | AO50: =AH50*AI50 -> 35549.763 | AP50: =U50+AB50 -> 0.7 | AQ50: =AL50*AP50/(AG50+AE50) -> 2.6 | AR50: A lançar
A51: MAP078 | B51: 3AC - POA CIDADE NOVA /ARILDO - PORTO ALEGRE | C51: https://earth.google.com/web/search/PORTO+ALEGRE/@-30.12584024,-51.13053681,31.39242651a,5997.00691746d,35y,0h,0t,0r/data=CiwiJgokCdF8eOBcqz3AEVk4mQ0orz3AGW7M2FWxNkrAIVpN-_QgO0rAQgIIAToDCgEwQgIIAEoICJfn8a8FEAA?authuser=0 | D51: 1 | E51: LandBank | G51: 2381 | J51: 285 | K51: SUL | L51: PORTO ALEGRE | M51: RS | N51: 3AC - POA CIDADE NOVA/ ARILDO | O51: Parceria | P51: 0 | Q51: Loteamento | R51: - | S51: 2030 | T51: 47848 | U51: 0.4341 | V51: 0.299 | W51: =SUM(U51:V51) -> 0.7331 | X51: 0.07 | Y51: 0.06 | Z51: 0.068 | AA51: 0.198 | AB51: 0.2669 | AC51: =AI51*AJ51 -> 168000 | AE51: =P51/10^6 -> 0 | AF51: =IF(AL51=0,0,AE51/AL51) -> 0 | AG51: =(AH51*AI51*AJ51)/10^6 -> 29.4 | AH51: 175 | AI51: 200 | AJ51: 840 | AK51: 700 | AL51: =(AK51*AJ51*AI51)/10^6 -> 117.6 | AM51: =AL51*U51 -> 51.05016 | AN51: =AI51*AK51 -> 140000 | AO51: =AH51*AI51 -> 35000 | AP51: =U51+AB51 -> 0.701 | AQ51: =AL51*AP51/(AG51+AE51) -> 2.804 | AR51: A lançar
A52: MAP078 | B52: 3AD - POA C. NOVA/ARILDO (COMPRA 24HA) - PORTO ALEGRE | C52: https://earth.google.com/web/search/PORTO+ALEGRE/@-30.12584024,-51.13053681,31.39242651a,5997.00691746d,35y,0h,0t,0r/data=CiwiJgokCdF8eOBcqz3AEVk4mQ0orz3AGW7M2FWxNkrAIVpN-_QgO0rAQgIIAToDCgEwQgIIAEoICJfn8a8FEAA?authuser=0 | D52: 1 | E52: LandBank | G52: 2381 | J52: 287 | K52: SUL | L52: PORTO ALEGRE | M52: RS | N52: 3AD - POA C. NOVA/ARILDO (COMPRA 24HA) | O52: Parceria | P52: 0 | Q52: Condominio | R52: - | S52: 2030 | T52: 47848 | U52: 0.8 | W52: =SUM(U52:V52) -> 0.8 | AA52: 0.198 | AB52: 0.2 | AC52: =AI52*AJ52 -> 120000 | AE52: =P52/10^6 -> 0 | AF52: =IF(AL52=0,0,AE52/AL52) -> 0 | AG52: =(AH52*AI52*AJ52)/10^6 -> 42 | AH52: 350 | AI52: 180.45113 | AJ52: 665 | AK52: 700 | AL52: =(AK52*AJ52*AI52)/10^6 -> 84 | AM52: =AL52*U52 -> 67.2 | AN52: =AI52*AK52 -> 126315.79 | AO52: =AH52*AI52 -> 63157.895 | AP52: =U52+AB52 -> 1 | AQ52: =AL52*AP52/(AG52+AE52) -> 2 | AR52: A lançar
A53: MAP091 | B53: 6F - CAXIAS DO SUL - FAMÍLIA STEDILE - CAXIAS DO SUL | C53: https://earth.google.com/web/search/CAXIAS+DO+SUL/@-29.10724565,-51.11635957,827.09427571a,2319.35937575d,35y,0h,0t,0r/data=CiwiJgokCdbUR9LrSz3AEWtE3O5JUz3AGY4iHQCDWknAISsKRq0YY0nAQgIIAToDCgEwQgIIAEoICJfn8a8FEAA?authuser=0 | D53: 1 | E53: LandBank | G53: 2376 | J53: 304 | K53: SUL | L53: CAXIAS DO SUL | M53: RS | N53: 6F - CAXIAS DO SUL - FAMÍLIA STEDILE | O53: Parceria | P53: 0 | Q53: Loteamento | R53: - | S53: 2030 | T53: 47848 | U53: 0.472 | V53: 0.41 | W53: =SUM(U53:V53) -> 0.882 | X53: 0.07 | Y53: 0.095 | Z53: 0.068 | AA53: 0.198 | AB53: 0.118 | AC53: =AI53*AJ53 -> 82440 | AE53: =P53/10^6 -> 0 | AF53: =IF(AL53=0,0,AE53/AL53) -> 0 | AG53: =(AH53*AI53*AJ53)/10^6 -> 14.427 | AH53: 175 | AI53: 360 | AJ53: 229 | AK53: 1000 | AL53: =(AK53*AJ53*AI53)/10^6 -> 82.44 | AM53: =AL53*U53 -> 38.91168 | AN53: =AI53*AK53 -> 360000 | AO53: =AH53*AI53 -> 63000 | AP53: =U53+AB53 -> 0.59 | AQ53: =AL53*AP53/(AG53+AE53) -> 3.3714286 | AR53: A lançar
A54: MAP100 | B54: 11 - ALVORADA - ALVORADA | C54: https://earth.google.com/web/search/ALVORADA/@-29.98003623,-51.01884373,10.54575489a,10609.79123323d,35y,-0h,0t,0r/data=CncaSRJDCiUweDk1MTk3NTU3M2Y5YTZmYjc6MHg2YmI2ODAzY2NiYzUwNjI5GUoMXeT5_z3AIYjS3uALiknAKghBTFZPUkFEQRgBIAEiJgokCZR_4psFoz3AERQVkKILqD3AGVvKRmTueUnAIc72lsLNf0nAQgIIAToDCgEwQgIIAEoICJfn8a8FEAA?authuser=0 | D54: 1 | E54: Estudo de viabilidade | G54: 2391 | J54: 318 | K54: SUL | L54: ALVORADA | M54: TO | N54: 11 - ALVORADA | O54: Parceria | P54: 0 | Q54: Loteamento | R54: - | S54: 2030 | T54: 47756 | U54: 0.6 | V54: 0.25 | W54: =SUM(U54:V54) -> 0.85 | X54: 0.07 | Y54: 0.07 | Z54: 0.068 | AA54: 0.198 | AB54: 0.15 | AC54: =AI54*AJ54 -> 283242.12 | AE54: =P54/10^6 -> 0 | AF54: =IF(AL54=0,0,AE54/AL54) -> 0 | AG54: =(AH54*AI54*AJ54)/10^6 -> 49.567372 | AH54: 175 | AI54: 224.97389 | AJ54: 1259 | AK54: 550 | AL54: =(AK54*AJ54*AI54)/10^6 -> 155.78317 | AM54: =AL54*U54 -> 93.469901 | AN54: =AI54*AK54 -> 123735.64 | AO54: =AH54*AI54 -> 39370.43 | AP54: =U54+AB54 -> 0.75 | AQ54: =AL54*AP54/(AG54+AE54) -> 2.3571429 | AR54: A lançar
A55: MAP021 | B55: A DEFINIR - AREA AEROPORTO I - PALMAS | C55: https://earth.google.com/web/search/Palmas,+TO/@-10.3121257,-48.32472401,257.8116143a,12197.49387353d,35y,0h,0t,0r/data=CngaShJECiQweDkzM2IzNDM5OTExZjEyNTc6MHg5M2I4MDcwZDA1YzgxOGYZtHQF24h_JMAhUsd0MoIpSMAqClBhbG1hcywgVE8YASABIiYKJAnKmUn74gAbwBGE16-ZZBobwBm4d1Wa5ohJwCHUhDGVbI9JwEICCAE6AwoBMEICCABKCAiX5_GvBRAA?authuser=0 | D55: 1 | E55: LandBank | G55: PENDENCIA | J55: 164 | K55: TOCANTINS | L55: PALMAS | M55: TO | N55: A DEFINIR - AREA AEROPORTO I | O55: Compra e Venda | P55: 2781250 | Q55: Loteamento | R55: - | S55: 2030 | T55: 47848 | U55: 0.3696 | W55: =SUM(U55:V55) -> 0.3696 | AA55: 0.198 | AB55: 0.6304 | AC55: =AI55*AJ55 -> 202400 | AE55: =P55/10^6 -> 2.78125 | AF55: =IF(AL55=0,0,AE55/AL55) -> 0.025927083 | AG55: =(AH55*AI55*AJ55)/10^6 -> 25.9072 | AH55: 128 | AI55: 275 | AJ55: 736 | AK55: 530 | AL55: =(AK55*AJ55*AI55)/10^6 -> 107.272 | AM55: =AL55*U55 -> 39.647731 | AN55: =AI55*AK55 -> 145750 | AO55: =AH55*AI55 -> 35200 | AP55: =U55+AB55 -> 1 | AQ55: =AL55*AP55/(AG55+AE55) -> 3.7392052 | AR55: A lançar
A56: MAP022 | B56: RESIDENCIAL BURITI GARGEN PRIME - PALMAS | C56: https://earth.google.com/web/search/Palmas/@-10.25056053,-48.33726188,252.56505595a,47484.59826451d,35y,0h,0t,0r/data=CnQaRhJACiQweDkzM2IzNDM5OTExZjEyNTc6MHg5M2I4MDcwZDA1YzgxOGYZtHQF24h_JMAhUsd0MoIpSMAqBlBhbG1hcxgCIAEiJgokCZ4TQp4rbCTAEd7oz8tIyyTAGZMBVXzHEEjAIR-xYc3lQUjAQgIIAToDCgEwQgIIAEoICJfn8a8FEAA?authuser=0 | D56: 1 | E56: LandBank | G56: PENDENCIA | J56: 182 | K56: TOCANTINS | L56: PALMAS | M56: TO | N56: RESIDENCIAL BURITI GARDEN PRIME | O56: Parceria | P56: 0 | Q56: Condominio | R56: - | S56: 2030 | T56: 47848 | U56: 0.442 | V56: 0.35 | W56: =SUM(U56:V56) -> 0.792 | X56: 0.05 | Y56: 0.07 | Z56: 0.068 | AA56: 0.198 | AB56: 0.208 | AC56: =AI56*AJ56 -> 178172.5 | AE56: =P56/10^6 -> 0 | AF56: =IF(AL56=0,0,AE56/AL56) -> 0 | AG56: =(AH56*AI56*AJ56)/10^6 -> 46.32485 | AH56: 260 | AI56: 350 | AJ56: 509.06429 | AK56: 1250 | AL56: =(AK56*AJ56*AI56)/10^6 -> 222.71562 | AM56: =AL56*U56 -> 98.440306 | AN56: =AI56*AK56 -> 437500 | AO56: =AH56*AI56 -> 91000 | AP56: =U56+AB56 -> 0.65 | AQ56: =AL56*AP56/(AG56+AE56) -> 3.125 | AR56: A lançar
A57: MAP046 | B57: JARDIM DO VALE IV - COLATINA | C57: https://earth.google.com/web/search/COLATINA/@-19.52647784,-40.60231088,138.19641271a,3370.80950192d,35y,360h,0t,0r/data=CiwiJgokCW0IAtKljDbAEcH4TEmVtzbAGTR6r34gk0XAIZ1xJ4dpwkXAQgIIAToDCgEwQgIIAEoICJfn8a8FEAA?authuser=0 | D57: 1 | E57: LandBank | G57: 2284 | J57: 220 | K57: SUDESTE | L57: COLATINA | M57: ES | N57: JARDIM DO VALE IV | O57: Parceria | P57: 0 | Q57: Loteamento | R57: - | S57: 2031 | T57: 48029 | U57: 0.504185 | V57: 0.45 | W57: =SUM(U57:V57) -> 0.954185 | X57: 0.05 | Y57: 0.09 | Z57: 0.068 | AA57: 0.198 | AB57: 0.045815 | AC57: =AI57*AJ57 -> 202882 | AE57: =P57/10^6 -> 0 | AF57: =IF(AL57=0,0,AE57/AL57) -> 0 | AG57: =(AH57*AI57*AJ57)/10^6 -> 34.48994 | AH57: 170 | AI57: 361 | AJ57: 562 | AK57: 650 | AL57: =(AK57*AJ57*AI57)/10^6 -> 131.8733 | AM57: =AL57*U57 -> 66.48854 | AN57: =AI57*AK57 -> 234650 | AO57: =AH57*AI57 -> 61370 | AP57: =U57+AB57 -> 0.55 | AQ57: =AL57*AP57/(AG57+AE57) -> 2.1029412 | AR57: A lançar
A58: MAP051 | B58: RESIDENCIAL CIDADE JARDIM III - ITATIAIA | C58: https://earth.google.com/web/search/Itatiaia,+RJ/@-22.45992895,-44.52068364,423.46245411a,8948.36825161d,35y,0h,0t,0r/data=CiwiJgokCZ6WBhqISi_AEVBldJnBEzjAGf8jZD_WyULAIQ_8zVvgN0zAQgIIAToDCgEwQgIIAEoICJfn8a8FEAA?authuser=0 | D58: 1 | E58: LandBank | G58: 2278 | J58: 229 | K58: SUDESTE | L58: ITATIAIA | M58: RJ | N58: RESIDENCIAL CIDADE JARDIM III | O58: Parceria | P58: 0 | Q58: Loteamento | R58: - | S58: 2031 | T58: 48213 | U58: 0.595855 | V58: 0.35 | W58: =SUM(U58:V58) -> 0.945855 | X58: 0.05 | Y58: 0.09 | Z58: 0.068 | AA58: 0.198 | AB58: 0.054145 | AC58: =AI58*AJ58 -> 220800 | AE58: =P58/10^6 -> 0 | AF58: =IF(AL58=0,0,AE58/AL58) -> 0 | AG58: =(AH58*AI58*AJ58)/10^6 -> 35.9904 | AH58: 163 | AI58: 276 | AJ58: 800 | AK58: 650 | AL58: =(AK58*AJ58*AI58)/10^6 -> 143.52 | AM58: =AL58*U58 -> 85.51711 | AN58: =AI58*AK58 -> 179400 | AO58: =AH58*AI58 -> 44988 | AP58: =U58+AB58 -> 0.65 | AQ58: =AL58*AP58/(AG58+AE58) -> 2.5920245 | AR58: A lançar
A59: MAP066 | B59: ROBERTO NEGRAO II - PRESIDENTE PRUDENTE | C59: https://earth.google.com/web/search/PRESIDENTE+PRUDENTE/@-22.14871306,-51.33335737,421.19686992a,3065.92913489d,35y,0h,0t,0r/data=CiwiJgokCQO2VLUNETfAEV-ipG2MFTfAGcVo9EuN20bAIW53qAeE4EbAQgIIAToDCgEwQgIIAEoICJfn8a8FEAA?authuser=0 | D59: 1 | E59: LandBank | G59: 2281 | J59: 260 | K59: SUDESTE | L59: PRESIDENTE PRUDENTE | M59: SP | N59: ROBERTO NEGRAO II | O59: Parceria | P59: 0 | Q59: Loteamento | R59: - | S59: 2031 | T59: 48121 | U59: 0.650857 | V59: 0.29 | W59: =SUM(U59:V59) -> 0.940857 | X59: 0.05 | Y59: 0.09 | Z59: 0.068 | AA59: 0.198 | AB59: 0.059143 | AC59: =AI59*AJ59 -> 153158.75 | AE59: =P59/10^6 -> 0 | AF59: =IF(AL59=0,0,AE59/AL59) -> 0 | AG59: =(AH59*AI59*AJ59)/10^6 -> 24.964876 | AH59: 163 | AI59: 160.04049 | AJ59: 957 | AK59: 600 | AL59: =(AK59*AJ59*AI59)/10^6 -> 91.89525 | AM59: =AL59*U59 -> 59.810667 | AN59: =AI59*AK59 -> 96024.295 | AO59: =AH59*AI59 -> 26086.6 | AP59: =U59+AB59 -> 0.71 | AQ59: =AL59*AP59/(AG59+AE59) -> 2.6134969 | AR59: A lançar
A60: MAP071 | B60: A DEFINIR - GUARATIBA - RIO DE JANEIRO | C60: https://earth.google.com/web/search/RIO+DE+JANEIRO/@-22.98862614,-43.54653162,5.6419623a,1442.52576017d,35y,0h,0t,0r/data=CiwiJgokCRTrwKfDnzbAEaD090t2ojbAGapL29TAo0XAIYIA7fu4pkXAQgIIAToDCgEwQgIIAEoICJfn8a8FEAA?authuser=0 | D60: 1 | E60: Estudo de viabilidade | G60: 2656 | J60: 267 | K60: SUDESTE | L60: RIO DE JANEIRO | M60: RJ | N60: A DEFINIR - GUARATIBA | O60: Parceria | P60: 0 | Q60: Loteamento | R60: - | S60: 2031 | T60: 48212 | U60: 0.7 | V60: 0.3 | W60: =SUM(U60:V60) -> 1 | X60: 0.05 | Y60: 0 | Z60: 0.068 | AA60: 0.198 | AC60: =AI60*AJ60 -> 211978.4 | AE60: =P60/10^6 -> 0 | AF60: =IF(AL60=0,0,AE60/AL60) -> 0 | AG60: =(AH60*AI60*AJ60)/10^6 -> 34.552479 | AH60: 163 | AI60: 289.58798 | AJ60: 732 | AK60: 600 | AL60: =(AK60*AJ60*AI60)/10^6 -> 127.18704 | AM60: =AL60*U60 -> 89.030928 | AN60: =AI60*AK60 -> 173752.79 | AO60: =AH60*AI60 -> 47202.84 | AP60: =U60+AB60 -> 0.7 | AQ60: =AL60*AP60/(AG60+AE60) -> 2.5766871 | AR60: A lançar
A61: MAP076 | B61: 2D - GUAÍBA II - GUAÍBA | C61: https://earth.google.com/web/search/PORTO+ALEGRE/@-30.15639376,-51.37950813,15.7953786a,5231.5657715d,35y,360h,0t,0r/data=CiwiJgokCdF8eOBcqz3AEVk4mQ0orz3AGW7M2FWxNkrAIVpN-_QgO0rAQgIIAToDCgEwQgIIAEoICJfn8a8FEAA?authuser=0 | D61: 1 | E61: LandBank | G61: 2377 | J61: 279 | K61: SUL | L61: GUAÍBA | M61: RS | N61: 2D - GUIAÍBA II | O61: Parceria | P61: 0 | Q61: Loteamento | R61: - | S61: 2031 | T61: 48213 | U61: 0.56 | V61: 0.3 | W61: =SUM(U61:V61) -> 0.86 | X61: 0.07 | Y61: 0.095 | Z61: 0.068 | AA61: 0.198 | AB61: 0.14 | AC61: =AI61*AJ61 -> 220066.67 | AE61: =P61/10^6 -> 0 | AF61: =IF(AL61=0,0,AE61/AL61) -> 0 | AG61: =(AH61*AI61*AJ61)/10^6 -> 38.511667 | AH61: 175 | AI61: 269.35945 | AJ61: 817 | AK61: 650 | AL61: =(AK61*AJ61*AI61)/10^6 -> 143.04333 | AM61: =AL61*U61 -> 80.104267 | AN61: =AI61*AK61 -> 175083.64 | AO61: =AH61*AI61 -> 47137.903 | AP61: =U61+AB61 -> 0.7 | AQ61: =AL61*AP61/(AG61+AE61) -> 2.6 | AR61: A lançar
A62: MAP078 | B62: 3AB - POA CIDADE NOVA /ARILDO - PORTO ALEGRE | C62: https://earth.google.com/web/search/PORTO+ALEGRE/@-30.12584024,-51.13053681,31.39242651a,5997.00691746d,35y,0h,0t,0r/data=CiwiJgokCdF8eOBcqz3AEVk4mQ0orz3AGW7M2FWxNkrAIVpN-_QgO0rAQgIIAToDCgEwQgIIAEoICJfn8a8FEAA?authuser=0 | D62: 1 | E62: LandBank | G62: 2381 | J62: 282 | K62: SUL | L62: PORTO ALEGRE | M62: RS | N62: 3AB - POA CIDADE NOVA/ ARILDO | O62: Parceria | P62: 0 | Q62: Condominio | R62: Sim | S62: 2031 | T62: 48213 | U62: 0.4341 | V62: 0.4574 | W62: =SUM(U62:V62) -> 0.8915 | X62: 0.07 | Y62: 0.06 | Z62: 0.068 | AA62: 0.198 | AB62: 0.1085 | AC62: =AI62*AJ62 -> 132000 | AE62: =P62/10^6 -> 0 | AF62: =IF(AL62=0,0,AE62/AL62) -> 0 | AG62: =(AH62*AI62*AJ62)/10^6 -> 39.6 | AH62: 300 | AI62: 184.87395 | AJ62: 714 | AK62: 1200 | AL62: =(AK62*AJ62*AI62)/10^6 -> 158.4 | AM62: =AL62*U62 -> 68.76144 | AN62: =AI62*AK62 -> 221848.74 | AO62: =AH62*AI62 -> 55462.185 | AP62: =U62+AB62 -> 0.5426 | AQ62: =AL62*AP62/(AG62+AE62) -> 2.1704 | AR62: A lançar
A63: MAP092 | B63: 7 - CANELA III - CANELA | C63: https://earth.google.com/web/search/CANELA/@-29.31096028,-50.74065533,783.58216028a,4290.20961313d,35y,0h,0t,0r/data=CiwiJgokCaHXsZR7Dj7AEYnRurPGEj7AGVFhjI5xgknAIZdzDtB7h0nAQgIIAToDCgEwQgIIAEoICJfn8a8FEAA?authuser=0 | D63: 1 | E63: LandBank | G63: 2373 | J63: 307 | K63: SUL | L63: CANELA | M63: RS | N63: 7 - CANELA III | O63: Parceria | P63: 0 | Q63: Loteamento | R63: - | S63: 2031 | T63: 48029 | U63: 0.5918 | V63: 0.2603 | W63: =SUM(U63:V63) -> 0.8521 | X63: 0.07 | Y63: 0.095 | Z63: 0.068 | AA63: 0.198 | AB63: 0.1479 | AC63: =AI63*AJ63 -> 375000 | AE63: =P63/10^6 -> 0 | AF63: =IF(AL63=0,0,AE63/AL63) -> 0 | AG63: =(AH63*AI63*AJ63)/10^6 -> 65.625 | AH63: 175 | AI63: 400 | AJ63: 937.5 | AK63: 750 | AL63: =(AK63*AJ63*AI63)/10^6 -> 281.25 | AM63: =AL63*U63 -> 166.44375 | AN63: =AI63*AK63 -> 300000 | AO63: =AH63*AI63 -> 70000 | AP63: =U63+AB63 -> 0.7397 | AQ63: =AL63*AP63/(AG63+AE63) -> 3.1701429 | AR63: A lançar
A64: MAP021 | B64: A DEFINIR - AREA AEROPORTO II - PALMAS | C64: https://earth.google.com/web/search/Palmas,+TO/@-10.3121257,-48.32472401,257.8116143a,12197.49387353d,35y,0h,0t,0r/data=CngaShJECiQweDkzM2IzNDM5OTExZjEyNTc6MHg5M2I4MDcwZDA1YzgxOGYZtHQF24h_JMAhUsd0MoIpSMAqClBhbG1hcywgVE8YASABIiYKJAnKmUn74gAbwBGE16-ZZBobwBm4d1Wa5ohJwCHUhDGVbI9JwEICCAE6AwoBMEICCABKCAiX5_GvBRAA?authuser=0 | D64: 1 | E64: LandBank | G64: PENDENCIA | J64: 165 | K64: TOCANTINS | L64: PALMAS | M64: TO | N64: A DEFINIR - AREA AEROPORTO II | O64: Compra e Venda | P64: 2781250 | Q64: Loteamento | R64: - | S64: 2031 | T64: 48213 | U64: 0.3696 | W64: =SUM(U64:V64) -> 0.3696 | AA64: 0.198 | AB64: 0.6304 | AC64: =AI64*AJ64 -> 202400 | AE64: =P64/10^6 -> 2.78125 | AF64: =IF(AL64=0,0,AE64/AL64) -> 0.02498428 | AG64: =(AH64*AI64*AJ64)/10^6 -> 25.9072 | AH64: 128 | AI64: 275 | AJ64: 736 | AK64: 550 | AL64: =(AK64*AJ64*AI64)/10^6 -> 111.32 | AM64: =AL64*U64 -> 41.143872 | AN64: =AI64*AK64 -> 151250 | AO64: =AH64*AI64 -> 35200 | AP64: =U64+AB64 -> 1 | AQ64: =AL64*AP64/(AG64+AE64) -> 3.8803072 | AR64: A lançar
A65: MAP022 | B65: RESIDENCIAL BURITI GARGEN PRIME II - PALMAS | C65: https://earth.google.com/web/search/Palmas/@-10.25056053,-48.33726188,252.56505595a,47484.59826451d,35y,0h,0t,0r/data=CnQaRhJACiQweDkzM2IzNDM5OTExZjEyNTc6MHg5M2I4MDcwZDA1YzgxOGYZtHQF24h_JMAhUsd0MoIpSMAqBlBhbG1hcxgCIAEiJgokCZ4TQp4rbCTAEd7oz8tIyyTAGZMBVXzHEEjAIR-xYc3lQUjAQgIIAToDCgEwQgIIAEoICJfn8a8FEAA?authuser=0 | D65: 1 | E65: LandBank | G65: PENDENCIA | J65: 183 | K65: TOCANTINS | L65: PALMAS | M65: TO | N65: RESIDENCIAL BURITI GARDEN PRIME II | O65: Parceria | P65: 0 | Q65: Condominio | R65: - | S65: 2031 | T65: 48213 | U65: 0.442 | V65: 0.35 | W65: =SUM(U65:V65) -> 0.792 | X65: 0.05 | Y65: 0.07 | Z65: 0.068 | AA65: 0.198 | AB65: 0.208 | AC65: =AI65*AJ65 -> 178172.5 | AE65: =P65/10^6 -> 0 | AF65: =IF(AL65=0,0,AE65/AL65) -> 0 | AG65: =(AH65*AI65*AJ65)/10^6 -> 46.32485 | AH65: 260 | AI65: 350 | AJ65: 509.06429 | AK65: 1250 | AL65: =(AK65*AJ65*AI65)/10^6 -> 222.71562 | AM65: =AL65*U65 -> 98.440306 | AN65: =AI65*AK65 -> 437500 | AO65: =AH65*AI65 -> 91000 | AP65: =U65+AB65 -> 0.65 | AQ65: =AL65*AP65/(AG65+AE65) -> 3.125 | AR65: A lançar
A66: MAP013 | B66: RESIDENCIAL CIDADE JARDIM IV - SANTANA DO ARAGUAIA | C66: https://earth.google.com/web/search/SANTANA+DO+ARAGUAIA/@-9.33586436,-50.36139721,175.24087708a,6146.88773774d,35y,0.00000002h,0t,0r/data=CoIBGlQSTgolMHg5MzFmMzU2MjJhMTljZmQxOjB4NDBiYzMzMTdkYTkxODA2NxkY0GYwoa0iwCGS2Q9nNCtJwCoTU0FOVEFOQSBETyBBUkFHVUFJQRgCIAEiJgokCSW03oMpdxzAEQai9168gBzAGSqKf2w09UjAIfPbVLWn90jAQgIIAToDCgEwQgIIAEoICJfn8a8FEAA?authuser=0 | D66: 1 | E66: LandBank | G66: 2123 | J66: 155 | K66: NORTE | L66: SANTANA DO ARAGUAIA | M66: PA | N66: RESIDENCIAL CIDADE JARDIM IV | O66: Compra e Venda | P66: 114285.71 | Q66: Loteamento | R66: Sim | S66: 2032 | T66: 48579 | U66: 1 | W66: =SUM(U66:V66) -> 1 | AA66: 0.198 | AC66: =AI66*AJ66 -> 105000 | AE66: =P66/10^6 -> 0.11428571 | AF66: =IF(AL66=0,0,AE66/AL66) -> 0.0027908598 | AG66: =(AH66*AI66*AJ66)/10^6 -> 13.9755 | AH66: 133.1 | AI66: 210 | AJ66: 500 | AK66: 390 | AL66: =(AK66*AJ66*AI66)/10^6 -> 40.95 | AM66: =AL66*U66 -> 40.95 | AN66: =AI66*AK66 -> 81900 | AO66: =AH66*AI66 -> 27951 | AP66: =U66+AB66 -> 1 | AQ66: =AL66*AP66/(AG66+AE66) -> 2.9063607 | AR66: A lançar
A67: MAP112 | B67: RESIDENCIAL CIDADE JARDIM III - TANGARÁ DA SERRA | C67: https://earth.google.com/web/search/TANGAR%c3%81+DA+SERRA/@-14.62032689,-57.54082084,346.92096178a,5258.20888551d,35y,0h,0t,0r/data=CiwiJgokCXA9rQptMS_AEXKWStZFPy_AGehdnQKoD0zAIeamtZ71FkzAQgIIAToDCgEwQgIIAEoICJfn8a8FEAA?authuser=0 | D67: 1 | E67: LandBank | G67: 2107 | J67: 344 | K67: OESTE | L67: TANGARÁ DA SERRA | M67: MT | N67: RESIDENCIAL CIDADE JARDIM III | O67: Compra e Venda | P67: 10682.93 | Q67: Loteamento | R67: - | S67: 2032 | T67: 48579 | U67: 0.7 | V67: 0.3 | W67: =SUM(U67:V67) -> 1 | X67: 0.05 | Y67: 0.09 | Z67: 0.068 | AA67: 0.198 | AC67: =AI67*AJ67 -> 365843.31 | AE67: =P67/10^6 -> 0.01068293 | AF67: =IF(AL67=0,0,AE67/AL67) -> 5.8401669e-05 | AG67: =(AH67*AI67*AJ67)/10^6 -> 48.65716 | AH67: 133 | AI67: 263.7659 | AJ67: 1387 | AK67: 500 | AL67: =(AK67*AJ67*AI67)/10^6 -> 182.92165 | AM67: =AL67*U67 -> 128.04516 | AN67: =AI67*AK67 -> 131882.95 | AO67: =AH67*AI67 -> 35080.865 | AP67: =U67+AB67 -> 0.7 | AQ67: =AL67*AP67/(AG67+AE67) -> 2.6310013 | AR67: A lançar
A68: MAP069 | B68: A DEFINIR - FERNANDOPOLIS | C68: https://earth.google.com/web/search/Fernand%c3%b3polis,+SP/@-20.28018739,-50.27505914,502.32219773a,2203.4530223d,35y,0h,0t,0r/data=CoEBGlMSTQolMHg5NDk3ZjYxY2I3ZDkzM2VkOjB4ZDE4MmY0ZTc4OTRmNzUxYhmJ3MKpxUg0wCEGFEWjlh9JwCoSRmVybmFuZMOzcG9saXMsIFNQGAEgASImCiQJgnysRFGlMMARwB6b_Yj8OMAZwQm5IOWMQ8Ah3LyfaYryTMBCAggBOgMKATBCAggASggIl-fxrwUQAA?authuser=0 | D68: 1 | E68: LandBank | G68: PENDENCIA | J68: 264 | K68: SUDESTE | L68: FERNANDOPOLIS | M68: SP | N68: A DEFINIR | O68: Parceria | P68: 0 | Q68: Loteamento | R68: - | S68: 2032 | T68: 48395 | U68: 0.7 | V68: 0.3 | W68: =SUM(U68:V68) -> 1 | X68: 0.05 | Y68: 0 | Z68: 0.068 | AA68: 0.198 | AC68: =AI68*AJ68 -> 167923 | AE68: =P68/10^6 -> 0 | AF68: =IF(AL68=0,0,AE68/AL68) -> 0 | AG68: =(AH68*AI68*AJ68)/10^6 -> 27.371449 | AH68: 163 | AI68: 203.29661 | AJ68: 826 | AK68: 600 | AL68: =(AK68*AJ68*AI68)/10^6 -> 100.7538 | AM68: =AL68*U68 -> 70.52766 | AN68: =AI68*AK68 -> 121977.97 | AO68: =AH68*AI68 -> 33137.347 | AP68: =U68+AB68 -> 0.7 | AQ68: =AL68*AP68/(AG68+AE68) -> 2.5766871 | AR68: A lançar
A69: MAP061 | B69: RESIDENCIAL CIDADE JARDIM IV - LORENA | C69: https://earth.google.com/web/search/LORENA/@-22.76355759,-45.11165622,554.79907101a,2424.9160967d,35y,0h,0t,0r/data=CiwiJgokCdDYYcMpEDbAEb-si-d6FTbAGdP8OMJ1sEnAIeq0yPtJtknAQgIIAToDCgEwQgIIAEoICJfn8a8FEAA?authuser=0 | D69: 1 | E69: LandBank | G69: 2286 | J69: 252 | K69: SUDESTE | L69: LORENA | M69: SP | N69: RESIDENCIAL CIDADE JARDIM IV | O69: Parceria | P69: 0 | Q69: Loteamento | R69: - | S69: 2032 | T69: 48395 | U69: 0.45 | V69: 0.5 | W69: =SUM(U69:V69) -> 0.95 | X69: 0.05 | Y69: 0.09 | Z69: 0.068 | AA69: 0.198 | AB69: 0.05 | AC69: =AI69*AJ69 -> 308574.72 | AE69: =P69/10^6 -> 0 | AF69: =IF(AL69=0,0,AE69/AL69) -> 0 | AG69: =(AH69*AI69*AJ69)/10^6 -> 50.29768 | AH69: 163 | AI69: 299.00651 | AJ69: 1032 | AK69: 665 | AL69: =(AK69*AJ69*AI69)/10^6 -> 205.20219 | AM69: =AL69*U69 -> 92.340986 | AN69: =AI69*AK69 -> 198839.33 | AO69: =AH69*AI69 -> 48738.062 | AP69: =U69+AB69 -> 0.5 | AQ69: =AL69*AP69/(AG69+AE69) -> 2.0398773 | AR69: A lançar
A70: MAP070 | B70: A DEFINIR II - POÇOS DE CALDAS | C70: https://earth.google.com/web/search/PO%c3%87OS+DE+CALDAS/@-21.78752103,-46.62526154,1239.73456507a,4634.91540016d,35y,0h,0t,0r/data=Cn8aURJLCiUweDk0YzljMmMzMmU1YTE1MWI6MHg5MGM3ODc3Mzg3NDU4OWZjGcjJafQPyTXAIYDAuXXtR0fAKhBQT8OHT1MgREUgQ0FMREFTGAEgASImCiQJvqqkfAn8NsAR9cW7viP-NsAZjS2Rv8vERcAhTKeEvR3HRcBCAggBOgMKATBCAggASggIl-fxrwUQAA?authuser=0 | D70: 0 | E70: LandBank | G70: 2290 | J70: 266 | K70: SUDESTE | L70: POÇOS DE CALDAS | M70: MG | N70: A DEFINIR | O70: Parceria | P70: 0 | Q70: Loteamento | R70: - | S70: 2032 | T70: 48487 | U70: 0.7 | V70: 0.3 | W70: =SUM(U70:V70) -> 1 | X70: 0.05 | Y70: 0 | Z70: 0.068 | AA70: 0.198 | AC70: =AI70*AJ70 -> 134500 | AE70: =P70/10^6 -> 0 | AF70: =IF(AL70=0,0,AE70/AL70) -> 0 | AG70: =(AH70*AI70*AJ70)/10^6 -> 21.9235 | AH70: 163 | AI70: 269 | AJ70: 500 | AK70: 600 | AL70: =(AK70*AJ70*AI70)/10^6 -> 80.7 | AM70: =AL70*U70 -> 56.49 | AN70: =AI70*AK70 -> 161400 | AO70: =AH70*AI70 -> 43847 | AP70: =U70+AB70 -> 0.7 | AQ70: =AL70*AP70/(AG70+AE70) -> 2.5766871 | AR70: A lançar
A71: MAP072 | B71: A DEFINIR - XEREM | C71: https://earth.google.com/web/search/XEREM/@-22.62934881,-43.29092126,11.53185275a,1846.58826664d,35y,0h,0t,0r/data=CnIaRBI-CiMweDk5MGQwNjA1MjJjMGUzOjB4ZTM3ZThkMTkwODViNTk3Yxl8qenEL5Q2wCG4OCo3UahFwCoFWEVSRU0YASABIiYKJAkYhbQqHtE2wBHp-EcQSdU2wBmmAdj5rAFFwCFFf4T1RAZFwEICCAE6AwoBMEICCABKCAiX5_GvBRAA?authuser=0 | D71: 1 | E71: LandBank | G71: PENDENCIA | J71: 268 | K71: SUDESTE | L71: XEREM | M71: RJ | N71: A DEFINIR | O71: Parceria | P71: 0 | Q71: Loteamento | R71: - | S71: 2032 | T71: 48578 | U71: 0.7 | V71: 0.3 | W71: =SUM(U71:V71) -> 1 | X71: 0.05 | Y71: 0 | Z71: 0.068 | AA71: 0.198 | AC71: =AI71*AJ71 -> 96864 | AE71: =P71/10^6 -> 0 | AF71: =IF(AL71=0,0,AE71/AL71) -> 0 | AG71: =(AH71*AI71*AJ71)/10^6 -> 15.788832 | AH71: 163 | AI71: 232.28777 | AJ71: 417 | AK71: 600 | AL71: =(AK71*AJ71*AI71)/10^6 -> 58.1184 | AM71: =AL71*U71 -> 40.68288 | AN71: =AI71*AK71 -> 139372.66 | AO71: =AH71*AI71 -> 37862.906 | AP71: =U71+AB71 -> 0.7 | AQ71: =AL71*AP71/(AG71+AE71) -> 2.5766871 | AR71: A lançar
A72: MAP077 | B72: 2D - GUAÍBA III - GUAÍBA | C72: https://earth.google.com/web/search/PORTO+ALEGRE/@-30.15639376,-51.37950813,15.7953786a,5231.5657715d,35y,360h,0t,0r/data=CiwiJgokCdF8eOBcqz3AEVk4mQ0orz3AGW7M2FWxNkrAIVpN-_QgO0rAQgIIAToDCgEwQgIIAEoICJfn8a8FEAA?authuser=0 | D72: 1 | E72: LandBank | G72: 2377 | J72: 280 | K72: SUL | L72: GUAÍBA | M72: RS | N72: 2D - GUIAÍBA III | O72: Parceria | P72: 0 | Q72: Loteamento | R72: - | S72: 2032 | T72: 48579 | U72: 0.56 | V72: 0.3 | W72: =SUM(U72:V72) -> 0.86 | X72: 0.07 | Y72: 0.095 | Z72: 0.068 | AA72: 0.198 | AB72: 0.14 | AC72: =AI72*AJ72 -> 220066.67 | AE72: =P72/10^6 -> 0 | AF72: =IF(AL72=0,0,AE72/AL72) -> 0 | AG72: =(AH72*AI72*AJ72)/10^6 -> 38.511667 | AH72: 175 | AI72: 269.03015 | AJ72: 818 | AK72: 650 | AL72: =(AK72*AJ72*AI72)/10^6 -> 143.04333 | AM72: =AL72*U72 -> 80.104267 | AN72: =AI72*AK72 -> 174869.6 | AO72: =AH72*AI72 -> 47080.277 | AP72: =U72+AB72 -> 0.7 | AQ72: =AL72*AP72/(AG72+AE72) -> 2.6 | AR72: A lançar
A73: MAP078 | B73: 3AC - POA CIDADE NOVA /ARILDO - PORTO ALEGRE | C73: https://earth.google.com/web/search/PORTO+ALEGRE/@-30.12584024,-51.13053681,31.39242651a,5997.00691746d,35y,0h,0t,0r/data=CiwiJgokCdF8eOBcqz3AEVk4mQ0orz3AGW7M2FWxNkrAIVpN-_QgO0rAQgIIAToDCgEwQgIIAEoICJfn8a8FEAA?authuser=0 | D73: 1 | E73: LandBank | G73: 2381 | J73: 286 | K73: SUL | L73: PORTO ALEGRE | M73: RS | N73: 3AC - POA CIDADE NOVA/ ARILDO | O73: Parceria | P73: 0 | Q73: Loteamento | R73: - | S73: 2032 | T73: 48579 | U73: 0.4341 | V73: 0.299 | W73: =SUM(U73:V73) -> 0.7331 | X73: 0.07 | Y73: 0.06 | Z73: 0.068 | AA73: 0.198 | AB73: 0.2669 | AC73: =AI73*AJ73 -> 168000 | AE73: =P73/10^6 -> 0 | AF73: =IF(AL73=0,0,AE73/AL73) -> 0 | AG73: =(AH73*AI73*AJ73)/10^6 -> 29.4 | AH73: 175 | AI73: 200 | AJ73: 840 | AK73: 700 | AL73: =(AK73*AJ73*AI73)/10^6 -> 117.6 | AM73: =AL73*U73 -> 51.05016 | AN73: =AI73*AK73 -> 140000 | AO73: =AH73*AI73 -> 35000 | AP73: =U73+AB73 -> 0.701 | AQ73: =AL73*AP73/(AG73+AE73) -> 2.804 | AR73: A lançar
A74: MAP078 | B74: 3B - POA CIDADE NOVA/FML - PORTO ALEGRE | C74: https://earth.google.com/web/search/PORTO+ALEGRE/@-30.12584024,-51.13053681,31.39242651a,5997.00691746d,35y,0h,0t,0r/data=CiwiJgokCdF8eOBcqz3AEVk4mQ0orz3AGW7M2FWxNkrAIVpN-_QgO0rAQgIIAToDCgEwQgIIAEoICJfn8a8FEAA?authuser=0 | D74: 1 | E74: LandBank | G74: 2381 | J74: 288 | K74: SUL | L74: PORTO ALEGRE | M74: RS | N74: 3B - POA CIDADE NOVA/FML | O74: Parceria | P74: 0 | Q74: Loteamento | R74: - | S74: 2032 | T74: 48579 | U74: 0.44 | V74: 0.32 | W74: =SUM(U74:V74) -> 0.76 | X74: 0.07 | Y74: 0.095 | Z74: 0.068 | AA74: 0.198 | AB74: 0.24 | AC74: =AI74*AJ74 -> 232500 | AE74: =P74/10^6 -> 0 | AF74: =IF(AL74=0,0,AE74/AL74) -> 0 | AG74: =(AH74*AI74*AJ74)/10^6 -> 40.6875 | AH74: 175 | AI74: 180 | AJ74: 1291.6667 | AK74: 700 | AL74: =(AK74*AJ74*AI74)/10^6 -> 162.75 | AM74: =AL74*U74 -> 71.61 | AN74: =AI74*AK74 -> 126000 | AO74: =AH74*AI74 -> 31500 | AP74: =U74+AB74 -> 0.68 | AQ74: =AL74*AP74/(AG74+AE74) -> 2.72 | AR74: A lançar
A75: MAP099 | B75: 10C - RIO GRANDE - AUGUSTO OTERO - RIO GRANDE DO SUL | C75: https://earth.google.com/web/search/RIO+GRANDE+DO+SUL/@-32.11183503,-52.18658908,5.40403187a,4423.26572132d,35y,-0h,0t,0r/data=CoABGlISTAolMHg5NTA0NzIwYzQwYjQ1ODAzOjB4YWQ5ZmIzZGJhZjlmNzNkZRnYHgdvWV09wCGQV9bsN9VJwCoRUklPIEdSQU5ERSBETyBTVUwYASABIiYKJAkw_JT_K_M9wBEf1nHWmAI-wBmH-JguXXlJwCFODtDCdYtJwEICCAE6AwoBMEICCABKCAiX5_GvBRAA?authuser=0 | D75: 1 | E75: LandBank | G75: 2383 | J75: 316 | K75: SUL | L75: RIO GRANDE | M75: RS | N75: 10C - RIO GRANDE - AUGUSTO OTERO | O75: Parceria | P75: 0 | Q75: Loteamento | R75: - | S75: 2032 | T75: 48395 | U75: 0.648 | V75: 0.19 | W75: =SUM(U75:V75) -> 0.838 | X75: 0.07 | Y75: 0.08 | Z75: 0.068 | AA75: 0.198 | AB75: 0.162 | AC75: =AI75*AJ75 -> 269500 | AE75: =P75/10^6 -> 0 | AF75: =IF(AL75=0,0,AE75/AL75) -> 0 | AG75: =(AH75*AI75*AJ75)/10^6 -> 47.1625 | AH75: 175 | AI75: 245 | AJ75: 1100 | AK75: 550 | AL75: =(AK75*AJ75*AI75)/10^6 -> 148.225 | AM75: =AL75*U75 -> 96.0498 | AN75: =AI75*AK75 -> 134750 | AO75: =AH75*AI75 -> 42875 | AP75: =U75+AB75 -> 0.81 | AQ75: =AL75*AP75/(AG75+AE75) -> 2.5457143 | AR75: A lançar
A76: MAP100 | B76: 11 - ALVORADA - ALVORADA | C76: https://earth.google.com/web/search/ALVORADA/@-29.98003623,-51.01884373,10.54575489a,10609.79123323d,35y,-0h,0t,0r/data=CncaSRJDCiUweDk1MTk3NTU3M2Y5YTZmYjc6MHg2YmI2ODAzY2NiYzUwNjI5GUoMXeT5_z3AIYjS3uALiknAKghBTFZPUkFEQRgBIAEiJgokCZR_4psFoz3AERQVkKILqD3AGVvKRmTueUnAIc72lsLNf0nAQgIIAToDCgEwQgIIAEoICJfn8a8FEAA?authuser=0 | D76: 1 | E76: Estudo de viabilidade | G76: 2391 | J76: 319 | K76: SUL | L76: ALVORADA | M76: TO | N76: 11 - ALVORADA | O76: Parceria | P76: 0 | Q76: Loteamento | R76: - | S76: 2032 | T76: 48487 | U76: 0.6 | V76: 0.25 | W76: =SUM(U76:V76) -> 0.85 | X76: 0.07 | Y76: 0.07 | Z76: 0.068 | AA76: 0.198 | AB76: 0.15 | AC76: =AI76*AJ76 -> 283242.12 | AE76: =P76/10^6 -> 0 | AF76: =IF(AL76=0,0,AE76/AL76) -> 0 | AG76: =(AH76*AI76*AJ76)/10^6 -> 49.567372 | AH76: 175 | AI76: 224.97389 | AJ76: 1259 | AK76: 550 | AL76: =(AK76*AJ76*AI76)/10^6 -> 155.78317 | AM76: =AL76*U76 -> 93.469901 | AN76: =AI76*AK76 -> 123735.64 | AO76: =AH76*AI76 -> 39370.43 | AP76: =U76+AB76 -> 0.75 | AQ76: =AL76*AP76/(AG76+AE76) -> 2.3571429 | AR76: A lançar
A77: MAP021 | B77: A DEFINIR - AREA AEROPORTO III - PALMAS | C77: https://earth.google.com/web/search/Palmas,+TO/@-10.3121257,-48.32472401,257.8116143a,12197.49387353d,35y,0h,0t,0r/data=CngaShJECiQweDkzM2IzNDM5OTExZjEyNTc6MHg5M2I4MDcwZDA1YzgxOGYZtHQF24h_JMAhUsd0MoIpSMAqClBhbG1hcywgVE8YASABIiYKJAnKmUn74gAbwBGE16-ZZBobwBm4d1Wa5ohJwCHUhDGVbI9JwEICCAE6AwoBMEICCABKCAiX5_GvBRAA?authuser=0 | D77: 1 | E77: LandBank | G77: PENDENCIA | J77: 166 | K77: TOCANTINS | L77: PALMAS | M77: TO | N77: A DEFINIR - AREA AEROPORTO III | O77: Compra e Venda | P77: 2781250 | Q77: Loteamento | R77: - | S77: 2032 | T77: 48579 | U77: 0.3696 | W77: =SUM(U77:V77) -> 0.3696 | AA77: 0.198 | AB77: 0.6304 | AC77: =AI77*AJ77 -> 202400 | AE77: =P77/10^6 -> 2.78125 | AF77: =IF(AL77=0,0,AE77/AL77) -> 0.02498428 | AG77: =(AH77*AI77*AJ77)/10^6 -> 25.9072 | AH77: 128 | AI77: 275 | AJ77: 736 | AK77: 550 | AL77: =(AK77*AJ77*AI77)/10^6 -> 111.32 | AM77: =AL77*U77 -> 41.143872 | AN77: =AI77*AK77 -> 151250 | AO77: =AH77*AI77 -> 35200 | AP77: =U77+AB77 -> 1 | AQ77: =AL77*AP77/(AG77+AE77) -> 3.8803072 | AR77: A lançar
A78: MAP107 | B78: RESIDENCIAL CIDADE JARDIM IV - RIO BRANCO | C78: https://earth.google.com/web/search/RIO+BRANCO/@-9.9098996,-67.78102104,162.15508008a,8113.58158257d,35y,360h,0t,0r/data=CnkaSxJFCiUweDkxN2Y3YmI2OGFjYzk2ZjM6MHg4YWI4OGYxZDdmMWQ5YjNjGbb6RWSz8iPAIUaLfRPU81DAKgpSSU8gQlJBTkNPGAEgASImCiQJfzD99xEWMMAR4w_EqB0hMMAZ8L7dRwvPTMAhtzjkj7naTMBCAggBOgMKATBCAggASggIl-fxrwUQAA?authuser=0 | D78: 1 | E78: LandBank | G78: 2106 | J78: 328 | K78: OESTE | L78: RIO BRANCO | M78: AC | N78: RESIDENCIAL CIDADE JARDIM III | O78: Compra e Venda | P78: 1436252.3 | Q78: Loteamento | R78: - | S78: 2033 | T78: 48760 | U78: 0.7 | V78: 0.3 | W78: =SUM(U78:V78) -> 1 | X78: 0.05 | Y78: 0.09 | Z78: 0.068 | AA78: 0.198 | AC78: =AI78*AJ78 -> 232066.43 | AE78: =P78/10^6 -> 1.4362523 | AF78: =IF(AL78=0,0,AE78/AL78) -> 0.012377941 | AG78: =(AH78*AI78*AJ78)/10^6 -> 37.130628 | AH78: 160 | AI78: 270.15882 | AJ78: 859 | AK78: 500 | AL78: =(AK78*AJ78*AI78)/10^6 -> 116.03321 | AM78: =AL78*U78 -> 81.223249 | AN78: =AI78*AK78 -> 135079.41 | AO78: =AH78*AI78 -> 43225.411 | AP78: =U78+AB78 -> 0.7 | AQ78: =AL78*AP78/(AG78+AE78) -> 2.1060363 | AR78: A lançar
A79: MAP059 | B79: A DEFINIR I - ITAPETININGA | C79: https://earth.google.com/web/search/ITAPETININGA/@-23.60041566,-48.11054145,648.36741354a,7499.34108211d,35y,0h,0t,0r/data=CiwiJgokCSTz4KZOwTbAEWUEDjqixTbAGTHHXZ3oi0bAId3jN-OskEbAQgIIAToDCgEwQgIIAEoICJfn8a8FEAA?authuser=0 | D79: 1 | E79: LandBank | G79: 2277 | J79: 242 | K79: SUDESTE | L79: ITAPETININGA | M79: SP | N79: A DEFINIR I | O79: Parceria | P79: 0 | Q79: Loteamento | R79: - | S79: 2033 | T79: 48943 | U79: 0.55 | V79: 0.40002 | W79: =SUM(U79:V79) -> 0.95002 | X79: 0.05 | Y79: 0.09 | Z79: 0.068 | AA79: 0.198 | AB79: 0.04998 | AC79: =AI79*AJ79 -> 315000 | AE79: =P79/10^6 -> 0 | AF79: =IF(AL79=0,0,AE79/AL79) -> 0 | AG79: =(AH79*AI79*AJ79)/10^6 -> 51.345 | AH79: 163 | AI79: 210 | AJ79: 1500 | AK79: 550 | AL79: =(AK79*AJ79*AI79)/10^6 -> 173.25 | AM79: =AL79*U79 -> 95.2875 | AN79: =AI79*AK79 -> 115500 | AO79: =AH79*AI79 -> 34230 | AP79: =U79+AB79 -> 0.59998 | AQ79: =AL79*AP79/(AG79+AE79) -> 2.0244724 | AR79: A lançar
A80: MAP051 | B80: RESIDENCIAL CIDADE JARDIM IV - ITATIAIA | C80: https://earth.google.com/web/search/Itatiaia,+RJ/@-22.45992895,-44.52068364,423.46245411a,8948.36825161d,35y,0h,0t,0r/data=CiwiJgokCZ6WBhqISi_AEVBldJnBEzjAGf8jZD_WyULAIQ_8zVvgN0zAQgIIAToDCgEwQgIIAEoICJfn8a8FEAA?authuser=0 | D80: 1 | E80: LandBank | G80: 2278 | J80: 230 | K80: SUDESTE | L80: ITATIAIA | M80: RJ | N80: RESIDENCIAL CIDADE JARDIM IV | O80: Parceria | P80: 0 | Q80: Loteamento | R80: - | S80: 2033 | T80: 48944 | U80: 0.595855 | V80: 0.35 | W80: =SUM(U80:V80) -> 0.945855 | X80: 0.05 | Y80: 0.09 | Z80: 0.068 | AA80: 0.198 | AB80: 0.054145 | AC80: =AI80*AJ80 -> 220800 | AE80: =P80/10^6 -> 0 | AF80: =IF(AL80=0,0,AE80/AL80) -> 0 | AG80: =(AH80*AI80*AJ80)/10^6 -> 35.9904 | AH80: 163 | AI80: 276 | AJ80: 800 | AK80: 650 | AL80: =(AK80*AJ80*AI80)/10^6 -> 143.52 | AM80: =AL80*U80 -> 85.51711 | AN80: =AI80*AK80 -> 179400 | AO80: =AH80*AI80 -> 44988 | AP80: =U80+AB80 -> 0.65 | AQ80: =AL80*AP80/(AG80+AE80) -> 2.5920245 | AR80: A lançar
A81: MAP061 | B81: RESIDENCIAL CIDADE JARDIM V - LORENA | C81: https://earth.google.com/web/search/LORENA/@-22.76355759,-45.11165622,554.79907101a,2424.9160967d,35y,0h,0t,0r/data=CiwiJgokCdDYYcMpEDbAEb-si-d6FTbAGdP8OMJ1sEnAIeq0yPtJtknAQgIIAToDCgEwQgIIAEoICJfn8a8FEAA?authuser=0 | D81: 1 | E81: LandBank | G81: 2286 | J81: 253 | K81: SUDESTE | L81: LORENA | M81: SP | N81: RESIDENCIAL CIDADE JARDIM V | O81: Parceria | P81: 0 | Q81: Loteamento | R81: - | S81: 2033 | T81: 48760 | U81: 0.45 | V81: 0.5 | W81: =SUM(U81:V81) -> 0.95 | X81: 0.05 | Y81: 0.09 | Z81: 0.068 | AA81: 0.198 | AB81: 0.05 | AC81: =AI81*AJ81 -> 308574.72 | AE81: =P81/10^6 -> 0 | AF81: =IF(AL81=0,0,AE81/AL81) -> 0 | AG81: =(AH81*AI81*AJ81)/10^6 -> 50.29768 | AH81: 163 | AI81: 299.00651 | AJ81: 1032 | AK81: 732 | AL81: =(AK81*AJ81*AI81)/10^6 -> 225.8767 | AM81: =AL81*U81 -> 101.64451 | AN81: =AI81*AK81 -> 218872.77 | AO81: =AH81*AI81 -> 48738.062 | AP81: =U81+AB81 -> 0.5 | AQ81: =AL81*AP81/(AG81+AE81) -> 2.2453988 | AR81: A lançar
A82: MAP078 | B82: 3AB - POA CIDADE NOVA /ARILDO - PORTO ALEGRE | C82: https://earth.google.com/web/search/PORTO+ALEGRE/@-30.12584024,-51.13053681,31.39242651a,5997.00691746d,35y,0h,0t,0r/data=CiwiJgokCdF8eOBcqz3AEVk4mQ0orz3AGW7M2FWxNkrAIVpN-_QgO0rAQgIIAToDCgEwQgIIAEoICJfn8a8FEAA?authuser=0 | D82: 1 | E82: LandBank | G82: 2381 | J82: 283 | K82: SUL | L82: PORTO ALEGRE | M82: RS | N82: 3AB - POA CIDADE NOVA/ ARILDO | O82: Parceria | P82: 0 | Q82: Condominio | R82: Sim | S82: 2033 | T82: 48944 | U82: 0.4341 | V82: 0.4574 | W82: =SUM(U82:V82) -> 0.8915 | X82: 0.07 | Y82: 0.06 | Z82: 0.068 | AA82: 0.198 | AB82: 0.1085 | AC82: =AI82*AJ82 -> 132000 | AE82: =P82/10^6 -> 0 | AF82: =IF(AL82=0,0,AE82/AL82) -> 0 | AG82: =(AH82*AI82*AJ82)/10^6 -> 39.6 | AH82: 300 | AI82: 184.87395 | AJ82: 714 | AK82: 1200 | AL82: =(AK82*AJ82*AI82)/10^6 -> 158.4 | AM82: =AL82*U82 -> 68.76144 | AN82: =AI82*AK82 -> 221848.74 | AO82: =AH82*AI82 -> 55462.185 | AP82: =U82+AB82 -> 0.5426 | AQ82: =AL82*AP82/(AG82+AE82) -> 2.1704 | AR82: A lançar
A83: MAP079 | B83: 3DB - POA/CALHA DE PEDRA II - PORTO ALEGRE | C83: https://earth.google.com/web/search/PORTO+ALEGRE/@-30.11127632,-51.12148809,52.85283914a,2914.98585346d,35y,0.00000001h,0t,0r/data=CiwiJgokCdF8eOBcqz3AEVk4mQ0orz3AGW7M2FWxNkrAIVpN-_QgO0rAQgIIAToDCgEwQgIIAEoICJfn8a8FEAA?authuser=0 | D83: 1 | E83: LandBank | G83: 2381 | J83: 291 | K83: SUL | L83: PORTO ALEGRE | M83: RS | N83: 3DB - POA/CALHA DE PEDRA II | O83: Parceria | P83: 0 | Q83: Loteamento | R83: Sim | S83: 2033 | T83: 48944 | U83: 0.328 | V83: 0.18 | W83: =SUM(U83:V83) -> 0.508 | X83: 0.07 | Y83: 0.07 | Z83: 0.068 | AA83: 0.198 | AB83: 0.492 | AC83: =AI83*AJ83 -> 98136 | AE83: =P83/10^6 -> 0 | AF83: =IF(AL83=0,0,AE83/AL83) -> 0 | AG83: =(AH83*AI83*AJ83)/10^6 -> 17.1738 | AH83: 175 | AI83: 185.16226 | AJ83: 530 | AK83: 1300 | AL83: =(AK83*AJ83*AI83)/10^6 -> 127.5768 | AM83: =AL83*U83 -> 41.84519 | AN83: =AI83*AK83 -> 240710.94 | AO83: =AH83*AI83 -> 32403.396 | AP83: =U83+AB83 -> 0.82 | AQ83: =AL83*AP83/(AG83+AE83) -> 6.0914286 | AR83: A lançar
A84: MAP092 | B84: 7 - CANELA IV - CANELA | C84: https://earth.google.com/web/search/CANELA/@-29.31096028,-50.74065533,783.58216028a,4290.20961313d,35y,0h,0t,0r/data=CiwiJgokCaHXsZR7Dj7AEYnRurPGEj7AGVFhjI5xgknAIZdzDtB7h0nAQgIIAToDCgEwQgIIAEoICJfn8a8FEAA?authuser=0 | D84: 1 | E84: LandBank | G84: 2373 | J84: 308 | K84: SUL | L84: CANELA | M84: RS | N84: 7 - CANELA IV | O84: Parceria | P84: 0 | Q84: Loteamento | R84: - | S84: 2033 | T84: 48760 | U84: 0.5918 | V84: 0.2603 | W84: =SUM(U84:V84) -> 0.8521 | X84: 0.07 | Y84: 0.095 | Z84: 0.068 | AA84: 0.198 | AB84: 0.1479 | AC84: =AI84*AJ84 -> 375000 | AE84: =P84/10^6 -> 0 | AF84: =IF(AL84=0,0,AE84/AL84) -> 0 | AG84: =(AH84*AI84*AJ84)/10^6 -> 65.625 | AH84: 175 | AI84: 400 | AJ84: 937.5 | AK84: 750 | AL84: =(AK84*AJ84*AI84)/10^6 -> 281.25 | AM84: =AL84*U84 -> 166.44375 | AN84: =AI84*AK84 -> 300000 | AO84: =AH84*AI84 -> 70000 | AP84: =U84+AB84 -> 0.7397 | AQ84: =AL84*AP84/(AG84+AE84) -> 3.1701429 | AR84: A lançar
A85: MAP021 | B85: A DEFINIR - AREA AEROPORTO IV - PALMAS | C85: https://earth.google.com/web/search/Palmas,+TO/@-10.3121257,-48.32472401,257.8116143a,12197.49387353d,35y,0h,0t,0r/data=CngaShJECiQweDkzM2IzNDM5OTExZjEyNTc6MHg5M2I4MDcwZDA1YzgxOGYZtHQF24h_JMAhUsd0MoIpSMAqClBhbG1hcywgVE8YASABIiYKJAnKmUn74gAbwBGE16-ZZBobwBm4d1Wa5ohJwCHUhDGVbI9JwEICCAE6AwoBMEICCABKCAiX5_GvBRAA?authuser=0 | D85: 1 | E85: LandBank | G85: PENDENCIA | J85: 167 | K85: TOCANTINS | L85: PALMAS | M85: TO | N85: A DEFINIR - AREA AEROPORTO IV | O85: Compra e Venda | P85: 2781250 | Q85: Loteamento | R85: - | S85: 2033 | T85: 48944 | U85: 0.3696 | W85: =SUM(U85:V85) -> 0.3696 | AA85: 0.198 | AB85: 0.6304 | AC85: =AI85*AJ85 -> 202400 | AE85: =P85/10^6 -> 2.78125 | AF85: =IF(AL85=0,0,AE85/AL85) -> 0.02498428 | AG85: =(AH85*AI85*AJ85)/10^6 -> 25.9072 | AH85: 128 | AI85: 275 | AJ85: 736 | AK85: 550 | AL85: =(AK85*AJ85*AI85)/10^6 -> 111.32 | AM85: =AL85*U85 -> 41.143872 | AN85: =AI85*AK85 -> 151250 | AO85: =AH85*AI85 -> 35200 | AP85: =U85+AB85 -> 1 | AQ85: =AL85*AP85/(AG85+AE85) -> 3.8803072 | AR85: A lançar
A86: MAP013 | B86: RESIDENCIAL CIDADE JARDIM V - SANTANA DO ARAGUAIA | C86: https://earth.google.com/web/search/SANTANA+DO+ARAGUAIA/@-9.33586436,-50.36139721,175.24087708a,6146.88773774d,35y,0.00000002h,0t,0r/data=CoIBGlQSTgolMHg5MzFmMzU2MjJhMTljZmQxOjB4NDBiYzMzMTdkYTkxODA2NxkY0GYwoa0iwCGS2Q9nNCtJwCoTU0FOVEFOQSBETyBBUkFHVUFJQRgCIAEiJgokCSW03oMpdxzAEQai9168gBzAGSqKf2w09UjAIfPbVLWn90jAQgIIAToDCgEwQgIIAEoICJfn8a8FEAA?authuser=0 | D86: 1 | E86: LandBank | G86: 2123 | J86: 156 | K86: NORTE | L86: SANTANA DO ARAGUAIA | M86: PA | N86: RESIDENCIAL CIDADE JARDIM V | O86: Compra e Venda | P86: 114285.71 | Q86: Loteamento | R86: Sim | S86: 2034 | T86: 49309 | U86: 1 | W86: =SUM(U86:V86) -> 1 | AA86: 0.198 | AC86: =AI86*AJ86 -> 105000 | AE86: =P86/10^6 -> 0.11428571 | AF86: =IF(AL86=0,0,AE86/AL86) -> 0.0027908598 | AG86: =(AH86*AI86*AJ86)/10^6 -> 13.9755 | AH86: 133.1 | AI86: 210 | AJ86: 500 | AK86: 390 | AL86: =(AK86*AJ86*AI86)/10^6 -> 40.95 | AM86: =AL86*U86 -> 40.95 | AN86: =AI86*AK86 -> 81900 | AO86: =AH86*AI86 -> 27951 | AP86: =U86+AB86 -> 1 | AQ86: =AL86*AP86/(AG86+AE86) -> 2.9063607 | AR86: A lançar
A87: MAP112 | B87: RESIDENCIAL CIDADE JARDIM IV - TANGARÁ DA SERRA | C87: https://earth.google.com/web/search/TANGAR%c3%81+DA+SERRA/@-14.62032689,-57.54082084,346.92096178a,5258.20888551d,35y,0h,0t,0r/data=CiwiJgokCXA9rQptMS_AEXKWStZFPy_AGehdnQKoD0zAIeamtZ71FkzAQgIIAToDCgEwQgIIAEoICJfn8a8FEAA?authuser=0 | D87: 1 | E87: LandBank | G87: 2107 | J87: 345 | K87: OESTE | L87: TANGARÁ DA SERRA | M87: MT | N87: RESIDENCIAL CIDADE JARDIM IV | O87: Compra e Venda | P87: 10682.93 | Q87: Loteamento | R87: - | S87: 2034 | T87: 49309 | U87: 0.7 | V87: 0.3 | W87: =SUM(U87:V87) -> 1 | X87: 0.05 | Y87: 0.09 | Z87: 0.068 | AA87: 0.198 | AC87: =AI87*AJ87 -> 252026.52 | AE87: =P87/10^6 -> 0.01068293 | AF87: =IF(AL87=0,0,AE87/AL87) -> 8.4776237e-05 | AG87: =(AH87*AI87*AJ87)/10^6 -> 33.519527 | AH87: 133 | AI87: 259.02006 | AJ87: 973 | AK87: 500 | AL87: =(AK87*AJ87*AI87)/10^6 -> 126.01326 | AM87: =AL87*U87 -> 88.209282 | AN87: =AI87*AK87 -> 129510.03 | AO87: =AH87*AI87 -> 34449.668 | AP87: =U87+AB87 -> 0.7 | AQ87: =AL87*AP87/(AG87+AE87) -> 2.6307405 | AR87: A lançar
A88: - | B88: - | D88: - | E88: - | F88: - | G88: - | H88: - | I88: - | J88: - | K88: OESTE | L88: TANGARÁ DA SERRA | M88: MT | N88: RESIDENCIAL CIDADE JARDIM IV | O88: Compra e Venda | P88: 10682.93 | Q88: Loteamento | R88: - | S88: 2034 | T88: 49309 | U88: 0.7 | V88: 0.3 | W88: =SUM(U88:V88) -> 1 | X88: 0.05 | Y88: 0.09 | Z88: 0.068 | AA88: 0.198 | AC88: =AI88*AJ88 -> 252026.52 | AE88: =P88/10^6 -> 0.01068293 | AF88: =IF(AL88=0,0,AE88/AL88) -> 8.4776237e-05 | AG88: =(AH88*AI88*AJ88)/10^6 -> 33.519527 | AH88: 133 | AI88: 259.02006 | AJ88: 973 | AK88: 500 | AL88: =(AK88*AJ88*AI88)/10^6 -> 126.01326 | AM88: =AL88*U88 -> 88.209282 | AN88: =AI88*AK88 -> 129510.03 | AO88: =AH88*AI88 -> 34449.668 | AP88: =U88+AB88 -> 0.7 | AQ88: =AL88*AP88/(AG88+AE88) -> 2.6307405 | AR88: A lançar
A89: MAP042 | B89: RESIDENCIAL CIDADE JARDIM III - BALSAS | C89: https://earth.google.com/web/search/BALSAS/@-7.55676262,-46.08364445,276.35723714a,5135.12989945d,35y,0h,0t,0r/data=CiwiJgokCeJxBz6CxDDAEQlwGFeXzDDAGfey9riu6UXAIWSXkF1C8kXAQgIIAToDCgEwQgIIAEoICJfn8a8FEAA?authuser=0 | D89: 1 | E89: LandBank | F89: REVER PROJETOS | G89: 2052 | J89: 212 | K89: NORDESTE II | L89: BALSAS | M89: MA | N89: RESIDENCIAL CIDADE JARDIM III | O89: Parceria | P89: 0 | Q89: Loteamento | R89: - | S89: 2030 | T89: 48487 | U89: 0.8 | V89: 0.2 | W89: =SUM(U89:V89) -> 1 | X89: 0.05 | Y89: 0 | Z89: 0.068 | AA89: 0.198 | AC89: =AI89*AJ89 -> 271890 | AE89: =P89/10^6 -> 0 | AF89: =IF(AL89=0,0,AE89/AL89) -> 0 | AG89: =(AH89*AI89*AJ89)/10^6 -> 32.6268 | AH89: 120 | AI89: 265 | AJ89: 1026 | AK89: 500 | AL89: =(AK89*AJ89*AI89)/10^6 -> 135.945 | AM89: =AL89*U89 -> 108.756 | AN89: =AI89*AK89 -> 132500 | AO89: =AH89*AI89 -> 31800 | AP89: =U89+AB89 -> 0.8 | AQ89: =AL89*AP89/(AG89+AE89) -> 3.3333333
A90: MAP040 | B90: JARDIM AMERICA III - TAUÁ | C90: https://earth.google.com/web/search/TAU%c3%81/@-5.97683983,-40.30366275,407.4430109a,2966.57752085d,35y,0h,0t,0r/data=CiwiJgokCVwuodN7uSdAEajZ7_kEaz3AGcctYEv-xi1AIcrxv7LiwVjAQgIIAToDCgEwQgIIAEoICJfn8a8FEAA?authuser=0 | D90: 1 | E90: LandBank | G90: 2056 | J90: 208 | K90: NORDESTE II | L90: TAUÁ | M90: CE | N90: JARDIM AMERICA III | O90: Parceria | P90: 0 | Q90: Loteamento | R90: Sim | S90: 2030 | T90: 47572 | U90: 0.79 | V90: 0.21 | W90: =SUM(U90:V90) -> 1 | X90: 0.05 | Y90: 0 | Z90: 0.068 | AA90: 0.198 | AC90: 201305 | AE90: =P90/10^6 -> 0 | AF90: =IF(AL90=0,0,AE90/AL90) -> 0 | AG90: =(AH90*AI90*AJ90)/10^6 -> 21.793536 | AH90: 108 | AI90: 192 | AJ90: 1051 | AK90: 480 | AL90: =(AK90*AJ90*AI90)/10^6 -> 96.86016 | AM90: =AL90*U90 -> 76.519526 | AN90: =AI90*AK90 -> 92160 | AO90: =AH90*AI90 -> 20736 | AP90: =U90+AB90 -> 0.79 | AQ90: =AL90*AP90/(AG90+AE90) -> 3.5111111
A91: MAP008 | B91: CIDADE JARDIM III - SUBETAPA 1 - SANTARÉM | C91: https://earth.google.com/web/search/CIDADE+JARDIM+12+-+PARAUAPEBAS/@-2.45795692,-54.77217012,46.50042218a,6405.178905d,35y,-0h,0t,0r/data=CiwiJgokCdmVqMeMyQbAESVW3mJaMwnAGYI6tUF7jUfAIaCAQToN3EfAQgIIAToDCgEwQgIIAEoICJfn8a8FEAA | D91: 1 | E91: LandBank | G91: 2121 | J91: 147 | K91: NORTE | L91: SANTARÉM | M91: PA | N91: CIDADE JARDIM III - SUBETAPA 1 | O91: Aquisição de Cotas | P91: 4800000 | Q91: Loteamento | R91: Sim | S91: 2026 | T91: 46387 | U91: 1 | W91: =SUM(U91:V91) -> 1 | AA91: 0.198 | AC91: =AI91*AJ91 -> 268937.01 | AE91: =P91/10^6 -> 4.8 | AF91: =IF(AL91=0,0,AE91/AL91) -> 0.027458532 | AG91: =(AH91*AI91*AJ91)/10^6 -> 35.795516 | AH91: 133.1 | AI91: 279.27 | AJ91: 963 | AK91: 650 | AL91: =(AK91*AJ91*AI91)/10^6 -> 174.80906 | AM91: =AL91*U91 -> 174.80906 | AN91: =AI91*AK91 -> 181525.5 | AO91: =AH91*AI91 -> 37170.837 | AP91: =U91+AB91 -> 1 | AQ91: =AL91*AP91/(AG91+AE91) -> 4.3061174
A92: MAP008 | B92: CIDADE JARDIM III - SUBETAPA 2 - SANTARÉM | C92: https://earth.google.com/web/search/CIDADE+JARDIM+12+-+PARAUAPEBAS/@-2.45795692,-54.77217012,46.50042218a,6405.178905d,35y,-0h,0t,0r/data=CiwiJgokCdmVqMeMyQbAESVW3mJaMwnAGYI6tUF7jUfAIaCAQToN3EfAQgIIAToDCgEwQgIIAEoICJfn8a8FEAA | D92: 1 | E92: LandBank | G92: 2121 | J92: 148 | K92: NORTE | L92: SANTARÉM | M92: PA | N92: CIDADE JARDIM III - SUBETAPA 2 | O92: Aquisição de Cotas | P92: 4800000 | Q92: Loteamento | R92: Sim | S92: 2027 | T92: 46752 | U92: 1 | W92: =SUM(U92:V92) -> 1 | AA92: 0.198 | AC92: =AI92*AJ92 -> 269216.28 | AE92: =P92/10^6 -> 4.8 | AF92: =IF(AL92=0,0,AE92/AL92) -> 0.027430048 | AG92: =(AH92*AI92*AJ92)/10^6 -> 35.832687 | AH92: 133.1 | AI92: 279.27 | AJ92: 964 | AK92: 650 | AL92: =(AK92*AJ92*AI92)/10^6 -> 174.99058 | AM92: =AL92*U92 -> 174.99058 | AN92: =AI92*AK92 -> 181525.5 | AO92: =AH92*AI92 -> 37170.837 | AP92: =U92+AB92 -> 1 | AQ92: =AL92*AP92/(AG92+AE92) -> 4.3066456
A93: MAP051 | B93: RESIDENCIAL CIDADE JARDIM IV - ITATIAIA | C93: https://earth.google.com/web/search/Itatiaia,+RJ/@-22.45992895,-44.52068364,423.46245411a,8948.36825161d,35y,0h,0t,0r/data=CiwiJgokCZ6WBhqISi_AEVBldJnBEzjAGf8jZD_WyULAIQ_8zVvgN0zAQgIIAToDCgEwQgIIAEoICJfn8a8FEAA?authuser=0 | D93: 1 | E93: LandBank | G93: 2278 | J93: 230 | K93: SUDESTE | L93: ITATIAIA | M93: RJ | N93: RESIDENCIAL CIDADE JARDIM IV | O93: Parceria | P93: 0 | Q93: Loteamento | R93: - | S93: 2033 | T93: 48944 | U93: 0.595855 | V93: 0.35 | W93: =SUM(U93:V93) -> 0.945855 | X93: 0.05 | Y93: 0.09 | Z93: 0.068 | AA93: 0.198 | AB93: 0.054145 | AC93: =AI93*AJ93 -> 220800 | AE93: =P93/10^6 -> 0 | AF93: =IF(AL93=0,0,AE93/AL93) -> 0 | AG93: =(AH93*AI93*AJ93)/10^6 -> 35.9904 | AH93: 163 | AI93: 276 | AJ93: 800 | AK93: 650 | AL93: =(AK93*AJ93*AI93)/10^6 -> 143.52 | AM93: =AL93*U93 -> 85.51711 | AN93: =AI93*AK93 -> 179400 | AO93: =AH93*AI93 -> 44988 | AP93: =U93+AB93 -> 0.65 | AQ93: =AL93*AP93/(AG93+AE93) -> 2.5920245
A94: MAP051 | B94: RESIDENCIAL CIDADE JARDIM - ITATIAIA | C94: https://earth.google.com/web/search/Itatiaia,+RJ/@-22.45992895,-44.52068364,423.46245411a,8948.36825161d,35y,0h,0t,0r/data=CiwiJgokCZ6WBhqISi_AEVBldJnBEzjAGf8jZD_WyULAIQ_8zVvgN0zAQgIIAToDCgEwQgIIAEoICJfn8a8FEAA?authuser=0 | D94: 1 | E94: LandBank | G94: 2278 | J94: 226 | K94: SUDESTE | L94: ITATIAIA | M94: RJ | N94: RESIDENCIAL CIDADE JARDIM | O94: Parceria | P94: 0 | Q94: Loteamento | R94: Sim | S94: 2029 | T94: 47483 | U94: 0.595855 | V94: 0.35 | W94: =SUM(U94:V94) -> 0.945855 | X94: 0.05 | Y94: 0.09 | Z94: 0.068 | AA94: 0.198 | AB94: 0.054145 | AC94: =AI94*AJ94 -> 202308 | AE94: =P94/10^6 -> 0 | AF94: =IF(AL94=0,0,AE94/AL94) -> 0 | AG94: =(AH94*AI94*AJ94)/10^6 -> 32.976204 | AH94: 163 | AI94: 276 | AJ94: 733 | AK94: 715 | AL94: =(AK94*AJ94*AI94)/10^6 -> 144.65022 | AM94: =AL94*U94 -> 86.190557 | AN94: =AI94*AK94 -> 197340 | AO94: =AH94*AI94 -> 44988 | AP94: =U94+AB94 -> 0.65 | AQ94: =AL94*AP94/(AG94+AE94) -> 2.851227
A95: MAP061 | B95: RESIDENCIAL CIDADE JARDIM VI - LORENA | C95: https://earth.google.com/web/search/LORENA/@-22.76355759,-45.11165622,554.79907101a,2424.9160967d,35y,0h,0t,0r/data=CiwiJgokCdDYYcMpEDbAEb-si-d6FTbAGdP8OMJ1sEnAIeq0yPtJtknAQgIIAToDCgEwQgIIAEoICJfn8a8FEAA?authuser=0 | D95: 1 | E95: LandBank | G95: 2286 | J95: 254 | K95: SUDESTE | L95: LORENA | M95: SP | N95: RESIDENCIAL CIDADE JARDIM VI | O95: Parceria | P95: 0 | Q95: Loteamento | R95: - | S95: 2034 | T95: 49125 | U95: 0.45 | V95: 0.5 | W95: =SUM(U95:V95) -> 0.95 | X95: 0.05 | Y95: 0.09 | Z95: 0.068 | AA95: 0.198 | AB95: 0.05 | AC95: =AI95*AJ95 -> 308574.72 | AE95: =P95/10^6 -> 0 | AF95: =IF(AL95=0,0,AE95/AL95) -> 0 | AG95: =(AH95*AI95*AJ95)/10^6 -> 50.29768 | AH95: 163 | AI95: 299.00651 | AJ95: 1032 | AK95: 805 | AL95: =(AK95*AJ95*AI95)/10^6 -> 248.40265 | AM95: =AL95*U95 -> 111.78119 | AN95: =AI95*AK95 -> 240700.24 | AO95: =AH95*AI95 -> 48738.062 | AP95: =U95+AB95 -> 0.5 | AQ95: =AL95*AP95/(AG95+AE95) -> 2.4693252
A96: MAP055 | B96: A DEFINIR II - MACAE | C96: https://earth.google.com/web/search/MACAE/@-22.36624118,-41.8234272,34.24557963a,6150.26313789d,35y,0h,0t,0r/data=CiwiJgokCcmdsN-e6TbAEVdlXJdI9TbAGUMWAjLoEkXAIbglujnGH0XAQgIIAToDCgEwQgIIAEoICJfn8a8FEAA?authuser=0 | D96: 1 | E96: Estudo de viabilidade | G96: 2642 | J96: 237 | K96: SUDESTE | L96: MACAE | M96: RJ | N96: A DEFINIR | O96: Parceria | P96: 0 | Q96: Loteamento | R96: - | S96: 2029 | T96: 47483 | U96: 0.595855 | V96: 0.35 | W96: =SUM(U96:V96) -> 0.945855 | X96: 0.05 | Y96: 0.09 | Z96: 0.068 | AA96: 0.198 | AB96: 0.054145 | AC96: =AI96*AJ96 -> 260596 | AE96: =P96/10^6 -> 0 | AF96: =IF(AL96=0,0,AE96/AL96) -> 0 | AG96: =(AH96*AI96*AJ96)/10^6 -> 42.477148 | AH96: 163 | AI96: 227 | AJ96: 1148 | AK96: 650 | AL96: =(AK96*AJ96*AI96)/10^6 -> 169.3874 | AM96: =AL96*U96 -> 100.93033 | AN96: =AI96*AK96 -> 147550 | AO96: =AH96*AI96 -> 37001 | AP96: =U96+AB96 -> 0.65 | AQ96: =AL96*AP96/(AG96+AE96) -> 2.5920245
A98: MAP066 | B98: ROBERTO NEGRAO II - PRESIDENTE PRUDENTE | C98: https://earth.google.com/web/search/PRESIDENTE+PRUDENTE/@-22.14871306,-51.33335737,421.19686992a,3065.92913489d,35y,0h,0t,0r/data=CiwiJgokCQO2VLUNETfAEV-ipG2MFTfAGcVo9EuN20bAIW53qAeE4EbAQgIIAToDCgEwQgIIAEoICJfn8a8FEAA?authuser=0 | D98: 1 | E98: LandBank | G98: 2281 | J98: 260 | K98: SUDESTE | L98: PRESIDENTE PRUDENTE | M98: SP | N98: ROBERTO NEGRAO II | O98: Parceria | P98: 0 | Q98: Loteamento | R98: - | S98: 2031 | T98: 48121 | U98: 0.650857 | V98: 0.29 | W98: =SUM(U98:V98) -> 0.940857 | X98: 0.05 | Y98: 0.09 | Z98: 0.068 | AA98: 0.198 | AB98: 0.059143 | AC98: =AI98*AJ98 -> 153158.75 | AE98: =P98/10^6 -> 0 | AF98: =IF(AL98=0,0,AE98/AL98) -> 0 | AG98: =(AH98*AI98*AJ98)/10^6 -> 24.964876 | AH98: 163 | AI98: 160.04049 | AJ98: 957 | AK98: 600 | AL98: =(AK98*AJ98*AI98)/10^6 -> 91.89525 | AM98: =AL98*U98 -> 59.810667 | AN98: =AI98*AK98 -> 96024.295 | AO98: =AH98*AI98 -> 26086.6 | AP98: =U98+AB98 -> 0.71 | AQ98: =AL98*AP98/(AG98+AE98) -> 2.6134969
A99: MAP105 | B99: 15 - VITORINO - 64HA II - VITORINO | C99: - | D99: 1 | E99: LandBank | G99: 2390 | J99: 325 | K99: SUL | L99: VITORINO | M99: PR | N99: 15 - VITORINO - 64HA II | O99: Parceria | P99: 0 | Q99: Loteamento | R99: - | S99: 2029 | T99: 47483 | U99: 0.592 | V99: 0.26 | W99: =SUM(U99:V99) -> 0.852 | X99: 0.07 | Y99: 0.095 | Z99: 0.068 | AA99: 0.198 | AB99: 0.148 | AC99: =AI99*AJ99 -> 190000 | AE99: =P99/10^6 -> 0 | AF99: =IF(AL99=0,0,AE99/AL99) -> 0 | AG99: =(AH99*AI99*AJ99)/10^6 -> 33.25 | AH99: 175 | AI99: 179.92424 | AJ99: 1056 | AK99: 550 | AL99: =(AK99*AJ99*AI99)/10^6 -> 104.5 | AM99: =AL99*U99 -> 61.864 | AN99: =AI99*AK99 -> 98958.333 | AO99: =AH99*AI99 -> 31486.742 | AP99: =U99+AB99 -> 0.74 | AQ99: =AL99*AP99/(AG99+AE99) -> 2.3257143
